Workbook
Name \A: #REF!
Name \aa: #REF!
Name \aaa: #REF!
Name \aaaa: #REF!
Name \activa: #REF!
Name \alcant: #REF!
Name \almace: #REF!
Name \b: #REF!
Name \bb: #REF!
Name \bbb: #REF!
Name \bbbb: #REF!
Name \bbbbb: #REF!
Name \bombe: #REF!
Name \capt: #REF!
Name \cond: #REF!
Name \cruda: #REF!
Name \d: #REF!
Name \Dato: #REF!
Name \dd: #REF!
Name \desa: #REF!
Name \Diag: #REF!
Name \e: #REF!
Name \lagu: #REF!
Name \m: #REF!
Name \medido: #REF!
Name \Metas: #REF!
Name \mm: #REF!
Name \mmm: #REF!
Name \mmmm: #REF!
Name \n: #REF!
Name \nn: #REF!
Name \nnn: #REF!
Name \nnnn: #REF!
Name \oferta: #REF!
Name \Pasiva: #REF!
Name \pobla: #REF!
Name \pre: #REF!
Name \prima: #REF!
Name \Q: #REF!
Name \QQ: #REF!
Name \QQQ: #REF!
Name \QQQQ: #REF!
Name \r: #REF!
Name \rr: #REF!
Name \rrrr: #REF!
Name \RRRRR: #REF!
Name \TOTAL: #REF!
Name \trata: #REF!
Name \tribu: #REF!
Name \tt: #REF!
Name \ttt: #REF!
Name \tttt: #REF!
Name \UsuarP: #REF!
Name __PP1: '[4]Red 12Piletas'!$E$99
Name __PP1: '[4]Red 12Piletas'!$E$99
Name __PP1: '[4]Red 12Piletas'!$E$99
Name __PP1: '[4]Red 12Piletas'!$E$99
Name __PP1: '[5]Red 12Piletas'!$E$99
Name __PP1: '[5]Red 12Piletas'!$E$99
Name __PP1: '[5]Red 12Piletas'!$E$99

Sheet 1.1 MIT. AMB.
A1: METRADOS SISTEMA DE AGUA POTABLE
A2: "CREACION DEL SERVICIO DE AGUA POTABLE RURAL Y CREACION DEL SERVICIO DE ALCANTARILLADO U OTRAS FORMAS DE DISPOSICION SANITARIA DE EXCRETAS EN EL SECTOR NUEVA ESPERANZA DE LA CC.NN. BAJO PITOCUNA DISTRITO DE RIO NEGRO, PROVINCIA DE SATIPO, DEPARTAMENTO DE JUNIN"
A3: OBRAS PROVISIONALES
A5: PARTIDA | B5: DESCRIPCION | C5: UNID. | D5: VECES | E5: LONG. | F5: ANCHO | G5: ALTURA | H5: SUB-TOTAL | I5: TOTAL
A6: 1.01 | B6: OBRAS PROVISIONALES
A7: =A6 & ".01" -> 1.01.01 | B7: CARTEL DE IDENTIFICACION DE OBRA DE 3.60m x 2.40m | C7: UND | H7: 1 | I7: =+H7 -> 1
A9: =A6 & ".02" -> 1.01.02 | B9: MOVILIZACION Y DESMOVILIZACION DE EQUIPOS Y MAQUINARIA PARA LA OBRA | C9: GLB | H9: 1 | I9: =+H9 -> 1

Sheet 1.2 CAP. T- LADERA
A1: HOJA DE METRADOS DEL SISTEMA DE AGUA POTABLE
A3: PROYECTO: | B3: "CREACION DEL SERVICIO DE AGUA POTABLE RURAL Y CREACION DEL SERVICIO DE ALCANTARILLADO U OTRAS FORMAS DE DISPOSICION SANITARIA DE EXCRETAS EN EL SECTOR NUEVA ESPERANZA DE LA CC.NN. BAJO PITOCUNA DISTRITO DE RIO NEGRO, PROVINCIA DE SATIPO, DEPARTAMENTO DE JUNIN"
A5: CAPTACION TIPO LADERA "PROSPERO"
A23: PARTIDA | B23: DESCRIPCION | C23: UNI | D23: CANT | E23: LARGO | F23: ANCHO | G23: ALTURA | H23: SUB-TOTAL | I23: TOTAL
A24: 01.02 | B24: CAPTACION DE LADERA - "PROSPERO" CONSTRUCCION (01 UND)
A25: =A$24 & ".01" -> 01.02.01 | B25: ESTRUCTURAS
A26: =A$25 & ".01" -> 01.02.01.01 | B26: TRABAJOS PRELIMINARES
A27: =A$26 & ".01" -> 01.02.01.01.01 | B27: LIMPIEZA DE TERRENO Y DESBROCE DE TERRENO MANUAL | C27: m2 | I27: =+H28 -> 37.0368
B28: Captación | D28: 1 | E28: 5.76 | F28: 6.43 | H28: =+F28*E28*D28 -> 37.0368
A29: =A$26 & ".02" -> 01.02.01.01.02 | B29: TRAZO Y REPLANTEO PRELIMINAR | C29: m2 | I29: =+H30 -> 37.0368
B30: Captación | D30: 1 | E30: =+E28 -> 5.76 | F30: =F28 -> 6.43 | H30: =+F30*E30*D30 -> 37.0368
A31: =A$26 & ".03" -> 01.02.01.01.03 | B31: TRAZO Y REPLANTEO DURANTE EL PROCESO | C31: m2 | I31: =SUM(H32:H34) -> 6.3025
B32: Aletas de protección | D32: 1 | E32: área | F32: 3.9 | H32: =PRODUCT(D32:G32) -> 3.9
B33: Cámara húmeda | D33: 1 | E33: 1.3 | F33: 1.3 | H33: =PRODUCT(D33:G33) -> 1.69
B34: Cámara seca | D34: 1 | E34: 0.95 | F34: 0.75 | H34: =PRODUCT(D34:G34) -> 0.7125
A36: =A$25 & ".02" -> 01.02.01.02 | B36: MOVIMIENTO DE TIERRAS
A37: =A$36 & ".01" -> 01.02.01.02.01 | B37: EXCAVACION MANUAL EN TERRENO NORMAL | C37: m3 | I37: =SUM(H38) -> 16.5
B38: Area de perfil y seccion | D38: 1 | E38: volumen | G38: 16.5 | H38: =+PRODUCT(D38:G38) -> 16.5
A41: =A$36 & ".02" -> 01.02.01.02.02 | B41: NIVELACION INTERIOR Y APISONADO (MANUAL) | C41: m2 | I41: =SUM(H42:H44) -> 6.3025
B42: Aletas de protección | D42: 1 | E42: área | F42: 3.9 | H42: =F42*D42 -> 3.9
B43: Cámara húmeda | D43: 1 | E43: 1.3 | F43: 1.3 | H43: =+F43*E43*D43 -> 1.69
B44: Cámara seca | D44: 1 | E44: 0.95 | F44: 0.75 | H44: =+F44*E44*D44 -> 0.7125
A46: =A$36 & ".03" -> 01.02.01.02.03 | B46: RELLENO COMPACTADO CON MATERIAL PROPIO SELECCIONADO | C46: m3 | I46: =SUM(H47) -> 4.5
D47: 1 | E47: volumen | G47: 4.5 | H47: =+PRODUCT(D47:G47) -> 4.5
A49: =A$36 & ".04" -> 01.02.01.02.04 | B49: ACARREO DE MAT. PARA RELLENO EN CAPTACIÓN | C49: m3 | I49: =+H50+H51 -> 14.625
B50: Excavacion - Esponjamiento 20% | D50: 1 | E50: 1.2 | F50: Volumen | G50: =I37 -> 16.5 | H50: =PRODUCT(D50:G50) -> 19.8
B51: Relleno - Compactacion | D51: -1 | E51: 1.15 | F51: Volumen | G51: =I46 -> 4.5 | H51: =PRODUCT(D51:G51) -> -5.175
A52: =A$25 & ".03" -> 01.02.01.03 | B52: OBRAS DE CONCRETO SIMPLE
A53: =A$52 & ".01" -> 01.02.01.03.01 | B53: CONCRETO SIMPLE F'C=100 KG/CM2, PARA SOLADO e=10cm | C53: m2 | I53: =SUM(H54:H59) -> 3.3825
B54: Alas de protección | D54: 2 | E54: 2 | F54: 0.25 | H54: =+D54*E54*F54 -> 1
B55: Pantalla de captación | D55: 1 | E55: 1.2 | F55: 0.2 | H55: =+D55*E55*F55 -> 0.24
B56: Piso de la cámara Húmeda | D56: 1 | E56: 0.9 | F56: 0.9 | H56: =+D56*E56*F56 -> 0.81
B57: Cimiento de la cámara Húmeda | D57: 2 | E57: 1.1 | F57: 0.2 | H57: =+D57*E57*F57 -> 0.44
D58: 1 | E58: 0.9 | F58: 0.2 | H58: =+D58*E58*F58 -> 0.18
B59: Cámara Seca | D59: 1 | E59: 0.75 | F59: 0.95 | H59: =+D59*E59*F59 -> 0.7125
A61: =A$52 & ".02" -> 01.02.01.03.02 | B61: CONCRETO f'c=140 kg/cm2 + 30 %PM. | C61: m3 | I61: =SUM(H62:H63) -> 1.946
B62: Dado asentado 0.50x0.50m | D62: 1 | E62: 0.5 | F62: 0.5 | G62: 0.2 | H62: =+D62*E62*F62*G62 -> 0.05
B63: En la base de la zona de afloramiento | D63: 1 | E63: área | F63: 0.79 | G63: 2.4 | H63: =+F63*D63*G63 -> 1.896
A65: =A$52 & ".03" -> 01.02.01.03.03 | B65: CONCRETO f'c=140 kg/cm2, EN DADOS | C65: m3 | I65: =+H66 -> 0.018
B66: Dado móvil de tubería de rebose y limpia | D66: 1 | E66: 0.3 | F66: 0.3 | G66: 0.2 | H66: =+PRODUCT(D66:G66) -> 0.018
A68: =A$25 & ".04" -> 01.02.01.04 | B68: OBRAS DE CONCRETO ARMADO
A69: =A$68 & ".01" -> 01.02.01.04.01 | B69: CONCRETO F'C=210 KG/CM2 S/MEZCLADORA PARA CIMENTACIÓN | C69: m3 | I69: =SUM(H71:H76) -> 0.6
B70: Cámara de filtros
B71: Cimentación de aletas de protección | D71: 2 | E71: 2 | F71: 0.15 | G71: 0.55 | H71: =+PRODUCT(D71:G71) -> 0.33
B72: Cámara humeda
B73: Cimentación de muro frontal de ingreso a cámara humeda | D73: 1 | E73: 1.3 | F73: 0.15 | G73: 0.55 | H73: =+PRODUCT(D73:G73) -> 0.10725
B74: Cimentación de muros laterales | D74: 2 | E74: 1.1 | F74: 0.15 | G74: 0.35 | H74: =+PRODUCT(D74:G74) -> 0.1155
B75: Cámara seca
B76: Cimentación de muro de salida a camará seca | D76: 1 | E76: 0.9 | F76: 0.15 | G76: 0.35 | H76: =+PRODUCT(D76:G76) -> 0.04725
A77: =A$68 & ".02" -> 01.02.01.04.02 | B77: CONCRETO F'C=210 KG/CM2 S/MEZCLADORA PARA MUROS | C77: m3 | I77: =SUM(H79:H85) -> 1.135
B78: Cámara de filtros
B79: Muros de aletas de protección | D79: 2 | E79: 2 | F79: 0.15 | G79: 1 | H79: =+PRODUCT(D79:G79) -> 0.6
B80: Cámara humeda
B81: Muro frontal de ingreso a cámara húmeda | D81: 1 | E81: 0.9 | F81: 0.15 | G81: 0.95 | H81: =+PRODUCT(D81:G81) -> 0.12825
B82: Muros laterales | D82: 2 | E82: 1.05 | F82: 0.15 | G82: 0.95 | H82: =+PRODUCT(D82:G82) -> 0.29925
B83: Cámara seca
B84: Muros laterales cámara seca | D84: 2 | E84: 0.75 | F84: 0.1 | G84: 0.5 | H84: =+PRODUCT(D84:G84) -> 0.075
B85: Muro de salida de cámara seca | D85: 1 | E85: 0.65 | F85: 0.1 | G85: 0.5 | H85: =+PRODUCT(D85:G85) -> 0.0325
A87: =A$68 & ".03" -> 01.02.01.04.03 | B87: CONCRETO F'C=210 KG/CM2 S/MEZCLADORA PARA LOSA DE FONDO | C87: m3 | I87: =SUM(H88:H91) -> 0.1975
B88: Cámara humeda
B89: Cámara húmeda losa de fondo | D89: 1 | E89: 0.9 | F89: 0.9 | G89: 0.15 | H89: =+D89*E89*F89*G89 -> 0.1215
B90: Cámara seca
B91: Cámara seca losa de fondo | D91: 1 | E91: 0.95 | F91: 0.8 | G91: 0.1 | H91: =+PRODUCT(D91:G91) -> 0.076
A92: =A$68 & ".04" -> 01.02.01.04.04 | B92: CONCRETO F'C=210 KG/CM2 S/MEZCLADORA PARA LOSA SUPERIOR | C92: m3 | I92: =SUM(H94:H101) -> 0.69325
B93: Cámara de filtros
B94: Sello sanitario superior (trapecio) | D94: 1 | E94: área | F94: 3.97 | G94: 0.15 | H94: =+PRODUCT(D94:G94) -> 0.5955
B95: Descuento tapa | D95: -1 | E95: 0.6 | F95: 0.6 | G95: 0.15 | H95: =+PRODUCT(D95:G95) -> -0.054
B96: Cámara humeda
B97: Cámara húmeda losa superior | D97: 1 | E97: 1.2 | F97: 1.2 | G97: 0.1 | H97: =+PRODUCT(D97:G97) -> 0.144
B98: Descuento tapa | D98: -1 | E98: 0.6 | F98: 0.6 | G98: 0.1 | H98: =+PRODUCT(D98:G98) -> -0.036
B99: Cámara seca
B100: Cámara seca losa superior | D100: 1 | E100: 0.85 | F100: 0.75 | G100: 0.1 | H100: =+PRODUCT(D100:G100) -> 0.06375
B101: Descuento tapa | D101: -1 | E101: 0.5 | F101: 0.4 | G101: 0.1 | H101: =+PRODUCT(D101:G101) -> -0.02
A103: =A$68 & ".05" -> 01.02.01.04.05 | B103: ENCOFRADO Y DESENCOFRADO EN MUROS | C103: m2 | I103: =SUM(H105:H114) -> 17.845
B104: Cámara de filtros
B105: Muros de aletas de protección interior | D105: 2 | E105: 2 | G105: 1 | H105: =+PRODUCT(D105:G105) -> 4
B106: Muros de aletas de protección exterior | D106: 2 | E106: 2 | G106: 1 | H106: =+PRODUCT(D106:G106) -> 4
B107: Cámara humeda
B108: Muro frontal de ingreso a cámara húmeda | D108: 2 | E108: 0.9 | G108: 0.95 | H108: =+G108*E108*D108 -> 1.71
B109: Muros internos de cámara húmeda | D109: 3 | E109: 0.9 | G109: 0.95 | H109: =+G109*E109*D109 -> 2.565
B110: Muros externos de cámara húmeda | D110: 3 | E110: 1.2 | G110: 0.95 | H110: =+G110*E110*D110 -> 3.42
B111: Cámara seca
B112: Muros internos de cámara seca | D112: 3 | E112: 0.65 | G112: 0.5 | H112: =+G112*E112*D112 -> 0.975
B113: Muros externos de cámara seca | D113: 1 | E113: 0.85 | G113: 0.5 | H113: =+G113*E113*D113 -> 0.425
D114: 2 | E114: 0.75 | G114: 0.5 | H114: =+G114*E114*D114 -> 0.75
A116: =A$68 & ".06" -> 01.02.01.04.06 | B116: ENCOFRADO Y DESENCOFRADO EN LOSAS | C116: m2 | I116: =SUM(H118:H133) -> 5.7975
B117: Cámara de filtros
B118: Sello sanitario superior para cámara de filtros | D118: 1 | E118: area | F118: 3.39 | H118: =+PRODUCT(D118:G118) -> 3.39
B119: Descuento tapa | D119: -1 | E119: 0.6 | F119: 0.6 | H119: =+PRODUCT(D119:G119) -> -0.36
B120: Lados laterales de la losa sanitaria superior para cámara de filtros | D120: 2 | E120: 2 | G120: 0.15 | H120: =+PRODUCT(D120:G120) -> 0.6
B121: Lados del borde de tapa | D121: 4 | E121: 0.6 | G121: 0.15 | H121: =+PRODUCT(D121:G121) -> 0.36
B122: Cámara humeda
B123: Losa superior de cámara húmeda | D123: 1 | E123: 0.9 | F123: 0.9 | H123: =+F123*E123*D123 -> 0.81
B124: Descuento tapa | D124: -1 | E124: 0.6 | F124: 0.6 | H124: =+F124*E124*D124 -> -0.36
B125: Lados laterales de losa superior de cámara húmeda | D125: 3 | E125: 1.2 | G125: 0.1 | H125: =+G125*E125*D125 -> 0.36
B126: Lados del borde de tapa | D126: 4 | E126: 0.6 | G126: 0.15 | H126: =+G126*E126*D126 -> 0.36
B127: Cámara seca
B128: Losa superior cámara seca | D128: 1 | E128: 0.65 | F128: 0.65 | H128: =+F128*E128*D128 -> 0.4225
B129: Descuento tapa | D129: -1 | E129: 0.5 | F129: 0.4 | H129: =+F129*E129*D129 -> -0.2
B130: Lados laterales de losa superior de cámara seca | D130: 2 | E130: 0.75 | G130: 0.1 | H130: =+G130*E130*D130 -> 0.15
...

Sheet 1.2 MET. DE ACERO
B2: METRADO DE ACERO DE REFUERZO
B3: PROYECTO | D3: "CREACION DEL SERVICIO DE AGUA POTABLE RURAL Y CREACION DEL SERVICIO DE ALCANTARILLADO U OTRAS FORMAS DE DISPOSICION SANITARIA DE EXCRETAS EN EL SECTOR NUEVA ESPERANZA DE LA CC.NN. BAJO PITOCUNA DISTRITO DE RIO NEGRO, PROVINCIA DE SATIPO, DEPARTAMENTO DE JUNIN" | P3: ESTRUCTURA :
P4: CAPTACIÓN TIPO LADERA
P5: CÁMARA DE FILTROS
B7: ITEM | C7: DESCRIPCION | D7: FORMA | J7: Ø (Pulg) | K7: LONG. (m) | L7: # BARRAS | M7: # ELEMEN. | N7: LARGO TOTAL | S7: OBSERV.
L8: ELEMENTO | M8: ELEMENTO | N8: 0.25 | O8: 0.375 | P8: 0.5 | Q8: 0.625 | R8: 0.75
C9: Acero cimiento - vertical
B12: 1 | G12: 0.63 | J12: 0.375 | K12: =SUM(D9:I14) -> 0.72 | L12: 10 | M12: 2 | N12: =IF(J12=1/4,L12*K12*M12,"-") -> - | O12: =IF(J12=3/8,K12*L12*M12,"-") -> 14.4 | P12: =IF(J12=1/2,L12*K12*M12,"-") -> - | Q12: =IF(J12=5/8,L12*K12*M12,"-") -> - | R12: =IF(J12=3/4,K12*L12,"-") -> -
F13: 0.09
C15: Acero cimiento y muro - horizontal
B16: 2 | D16: 0.15 | F16: 2.03 | J16: 0.375 | K16: =SUM(D15:I17) -> 2.18 | L16: 6 | M16: 2 | N16: =IF(J16=1/4,L16*K16*M16,"-") -> - | O16: =IF(J16=3/8,K16*L16*M16,"-") -> 26.16 | P16: =IF(J16=1/2,L16*K16*M16,"-") -> - | Q16: =IF(J16=5/8,L16*K16*M16,"-") -> - | R16: =IF(J16=3/4,K16*L16,"-") -> -
C18: Acero muro - vertical | F18: 0.15
F20: 1.51
B21: 3 | J21: 0.375 | K21: =SUM(D18:I23) -> 1.81 | L21: 10 | M21: 2 | N21: =IF(J21=1/4,L21*K21*M21,"-") -> - | O21: =IF(J21=3/8,K21*L21*M21,"-") -> 36.2 | P21: =IF(J21=1/2,L21*K21*M21,"-") -> - | Q21: =IF(J21=5/8,L21*K21*M21,"-") -> - | R21: =IF(J21=3/4,K21*L21,"-") -> -
G23: 0.15
C24: Acero en losa - transversal
F25: promedio
F26: 2.87
B27: 4 | J27: 0.375 | K27: =SUM(D24:I29) -> 3.17 | L27: 7 | M27: 1 | N27: =IF(J27=1/4,L27*K27*M27,"-") -> - | O27: =IF(J27=3/8,K27*L27*M27,"-") -> 22.19 | P27: =IF(J27=1/2,L27*K27*M27,"-") -> - | Q27: =IF(J27=5/8,L27*K27*M27,"-") -> - | R27: =IF(J27=3/4,K27*L27,"-") -> -
E28: 0.15 | H28: 0.15
C30: Acero en losa - longitudinal
F31: promedio
F32: 1.05
B33: 5 | J33: 0.375 | K33: =SUM(D30:I35) -> 1.35 | L33: 18 | M33: 1 | N33: =IF(J33=1/4,L33*K33*M33,"-") -> - | O33: =IF(J33=3/8,K33*L33*M33,"-") -> 24.3 | P33: =IF(J33=1/2,L33*K33*M33,"-") -> - | Q33: =IF(J33=5/8,L33*K33*M33,"-") -> - | R33: =IF(J33=3/4,K33*L33,"-") -> -
E34: 0.15 | H34: 0.15
J36: LONGITUD TOTAL (M) | N36: =SUM(N9:N29) -> 0 | O36: =SUM(O9:O35) -> 123.25 | P36: =SUM(P9:P29) -> 0 | Q36: =SUM(Q9:Q29) -> 0 | R36: =SUM(R9:R29) -> 0
J37: PESO x M.L (kg) | N37: 0.22 | O37: 0.56 | P37: 0.994 | Q37: 1.552 | R37: 2.235
J38: SUB TOTAL | N38: =N36*N37 -> 0 | O38: =O36*O37 -> 69.02 | P38: =P36*P37 -> 0 | Q38: =Q36*Q37 -> 0 | R38: =R36*R37 -> 0
J39: N° DE UNIDADES | M39: 1
J40: PESO TOTAL (KG) | M40: =SUM(N38:S38)*M39 -> 69.02
B43: METRADO DE ACERO DE REFUERZO
B44: PROYECTO | D44: "CREACION DEL SERVICIO DE AGUA POTABLE RURAL Y CREACION DEL SERVICIO DE ALCANTARILLADO U OTRAS FORMAS DE DISPOSICION SANITARIA DE EXCRETAS EN EL SECTOR NUEVA ESPERANZA DE LA CC.NN. BAJO PITOCUNA DISTRITO DE RIO NEGRO, PROVINCIA DE SATIPO, DEPARTAMENTO DE JUNIN" | P44: ESTRUCTURA :
P45: CAPTACIÓN TIPO LADERA
P46: CÁMARA HÚMEDA
B48: ITEM | C48: DESCRIPCION | D48: FORMA | J48: Ø (Pulg) | K48: LONG. (m) | L48: # BARRAS | M48: # ELEMEN. | N48: LARGO TOTAL | S48: OBSERV.
L49: ELEMENTO | M49: ELEMENTO | N49: 0.25 | O49: 0.375 | P49: 0.5 | Q49: 0.625 | R49: 0.75
C50: Acero cimiento de muro de entrada - vertical
B53: 1 | G53: 0.63 | J53: 0.375 | K53: =SUM(D50:I55) -> 0.69 | L53: 7 | M53: 1 | N53: =IF(J53=1/4,L53*K53*M53,"-") -> - | O53: =IF(J53=3/8,K53*L53*M53,"-") -> 4.83 | P53: =IF(J53=1/2,L53*K53*M53,"-") -> - | Q53: =IF(J53=5/8,L53*K53*M53,"-") -> - | R53: =IF(J53=3/4,K53*L53,"-") -> -
F54: 0.06
C56: Acero cimiento de muro de entrada - horizontal
B57: 2 | E57: 0.15 | F57: 1.11 | H57: 0.15 | J57: 0.375 | K57: =SUM(D56:I58) -> 1.41 | L57: 3 | M57: 1 | N57: =IF(J57=1/4,L57*K57*M57,"-") -> - | O57: =IF(J57=3/8,K57*L57*M57,"-") -> 4.23 | P57: =IF(J57=1/2,L57*K57*M57,"-") -> - | Q57: =IF(J57=5/8,L57*K57*M57,"-") -> - | R57: =IF(J57=3/4,K57*L57,"-") -> -
C59: Acero cimiento de muro de salida - vertical
G61: 1.32
B62: 3 | F62: 0.08 | J62: 0.375 | K62: =SUM(D59:I64) -> 1.4 | L62: 6 | M62: 1 | N62: =IF(J62=1/4,L62*K62*M62,"-") -> - | O62: =IF(J62=3/8,K62*L62*M62,"-") -> 8.4 | P62: =IF(J62=1/2,L62*K62*M62,"-") -> - | Q62: =IF(J62=5/8,L62*K62*M62,"-") -> - | R62: =IF(J62=3/4,K62*L62,"-") -> -
C65: Acero cimiento de muro de salida- horizontales
F66: 1.13
B68: 4 | E68: 0.15 | H68: 0.15 | J68: 0.375 | K68: =SUM(D65:I70) -> 1.43 | L68: 5 | M68: 1 | N68: =IF(J68=1/4,L68*K68*M68,"-") -> - | O68: =IF(J68=3/8,K68*L68*M68,"-") -> 7.15 | P68: =IF(J68=1/2,L68*K68*M68,"-") -> - | Q68: =IF(J68=5/8,L68*K68*M68,"-") -> - | R68: =IF(J68=3/4,K68*L68,"-") -> -
C71: Acero cimiento de muros laterales - vertical
F73: 0.31
B74: 5 | F74: 0.08 | J74: 0.375 | K74: =SUM(D71:I76) -> 0.39 | L74: 5 | M74: 2 | N74: =IF(J74=1/4,L74*K74*M74,"-") -> - | O74: =IF(J74=3/8,K74*L74*M74,"-") -> 3.9 | P74: =IF(J74=1/2,L74*K74*M74,"-") -> - | Q74: =IF(J74=5/8,L74*K74*M74,"-") -> - | R74: =IF(J74=3/4,K74*L74,"-") -> -
C77: Acero cimiento de muros laterales - horizontales
F78: 1.11
B80: 6 | E80: 0.15 | H80: 0.15 | J80: 0.375 | K80: =SUM(D77:I82) -> 1.41 | L80: 1 | M80: 2 | N80: =IF(J80=1/4,L80*K80*M80,"-") -> - | O80: =IF(J80=3/8,K80*L80*M80,"-") -> 2.82 | P80: =IF(J80=1/2,L80*K80*M80,"-") -> - | Q80: =IF(J80=5/8,L80*K80*M80,"-") -> - | R80: =IF(J80=3/4,K80*L80,"-") -> -
C83: Acero de muro de entrada - verticales | F83: 0.15
G85: 1.03
B86: 7 | J86: 0.375 | K86: =SUM(D83:I88) -> 1.18 | L86: 7 | M86: 1 | N86: =IF(J86=1/4,L86*K86*M86,"-") -> - | O86: =IF(J86=3/8,K86*L86*M86,"-") -> 8.26 | P86: =IF(J86=1/2,L86*K86*M86,"-") -> - | Q86: =IF(J86=5/8,L86*K86*M86,"-") -> - | R86: =IF(J86=3/4,K86*L86,"-") -> -
C89: Acero de muro de entrada - horizontales
F90: 1.11
B92: 8 | E92: 0.15 | H92: 0.15 | J92: 0.375 | K92: =SUM(D89:I94) -> 1.41 | L92: 7 | M92: 1 | N92: =IF(J92=1/4,L92*K92*M92,"-") -> - | O92: =IF(J92=3/8,K92*L92*M92,"-") -> 9.87 | P92: =IF(J92=1/2,L92*K92*M92,"-") -> - | Q92: =IF(J92=5/8,L92*K92*M92,"-") -> - | R92: =IF(J92=3/4,K92*L92,"-") -> -
C95: Acero de muro de salida - verticakes | F95: 0.15
B98: 9 | F98: 1.03 | J98: 0.375 | K98: =SUM(D95:I100) -> 1.18 | L98: 6 | M98: 1 | N98: =IF(J98=1/4,L98*K98*M98,"-") -> - | O98: =IF(J98=3/8,K98*L98*M98,"-") -> 7.08 | P98: =IF(J98=1/2,L98*K98*M98,"-") -> - | Q98: =IF(J98=5/8,L98*K98*M98,"-") -> - | R98: =IF(J98=3/4,K98*L98,"-") -> -
C101: Acero de muro de salida - horizontales
F102: 1.11
B104: 10 | E104: 0.15 | H104: 0.15 | J104: 0.375 | K104: =SUM(D101:I106) -> 1.41 | L104: 6 | M104: 1 | N104: =IF(J104=1/4,L104*K104*M104,"-") -> - | O104: =IF(J104=3/8,K104*L104*M104,"-") -> 8.46 | P104: =IF(J104=1/2,L104*K104*M104,"-") -> - | Q104: =IF(J104=5/8,L104*K104*M104,"-") -> - | R104: =IF(J104=3/4,K104*L104,"-") -> -
C107: Acero de muros laterales - verticales | F107: 0.15
B110: 11 | F110: 1.03 | J110: 0.375 | K110: =SUM(D107:I112) -> 1.18 | L110: 5 | M110: 2 | N110: =IF(J110=1/4,L110*K110*M110,"-") -> - | O110: =IF(J110=3/8,K110*L110*M110,"-") -> 11.8 | P110: =IF(J110=1/2,L110*K110*M110,"-") -> - | Q110: =IF(J110=5/8,L110*K110*M110,"-") -> - | R110: =IF(J110=3/4,K110*L110,"-") -> -
C113: Acero de muro de salida - horizontales
F114: 1.11
B116: 12 | E116: 0.15 | H116: 0.15 | J116: 0.375 | K116: =SUM(D113:I118) -> 1.41 | L116: 5 | M116: 2 | N116: =IF(J116=1/4,L116*K116*M116,"-") -> - | O116: =IF(J116=3/8,K116*L116*M116,"-") -> 14.1 | P116: =IF(J116=1/2,L116*K116*M116,"-") -> - | Q116: =IF(J116=5/8,L116*K116*M116,"-") -> - | R116: =IF(J116=3/4,K116*L116,"-") -> -
C119: Acero de losa de fondo - eje x-x
E120: 0.15 | F120: 1.18
B122: 13 | H122: 0.15 | J122: 0.375 | K122: =SUM(D119:I124) -> 1.48 | L122: 7 | M122: 1 | N122: =IF(J122=1/4,L122*K122*M122,"-") -> - | O122: =IF(J122=3/8,K122*L122*M122,"-") -> 10.36 | P122: =IF(J122=1/2,L122*K122*M122,"-") -> - | Q122: =IF(J122=5/8,L122*K122*M122,"-") -> - | R122: =IF(J122=3/4,K122*L122,"-") -> -
C125: Acero de losa de fondo - eje y-y
F126: 1.18
B128: 14 | E128: 0.15 | H128: 0.15 | J128: 0.375 | K128: =SUM(D125:I130) -> 1.48 | L128: 7 | M128: 1 | N128: =IF(J128=1/4,L128*K128*M128,"-") -> - | O128: =IF(J128=3/8,K128*L128*M128,"-") -> 10.36 | P128: =IF(J128=1/2,L128*K128*M128,"-") -> - | Q128: =IF(J128=5/8,L128*K128*M128,"-") -> - | R128: =IF(J128=3/4,K128*L128,"-") -> -
C131: Acero de losa superior - eje x-x
F132: 1.1
B134: 15 | E134: 0.15 | H134: 0.15 | J134: 0.375 | K134: =SUM(D131:I136) -> 1.4 | L134: 5 | M134: 1 | N134: =IF(J134=1/4,L134*K134*M134,"-") -> - | O134: =IF(J134=3/8,K134*L134*M134,"-") -> 7 | P134: =IF(J134=1/2,L134*K134*M134,"-") -> - | Q134: =IF(J134=5/8,L134*K134*M134,"-") -> - | R134: =IF(J134=3/4,K134*L134,"-") -> -
C137: Acero de losa superior - eje y-y
F138: 1.1
B140: 16 | E140: 0.15 | H140: 0.15 | J140: 0.375 | K140: =SUM(D137:I142) -> 1.4 | L140: 5 | M140: 1 | N140: =IF(J140=1/4,L140*K140*M140,"-") -> - | O140: =IF(J140=3/8,K140*L140*M140,"-") -> 7 | P140: =IF(J140=1/2,L140*K140*M140,"-") -> - | Q140: =IF(J140=5/8,L140*K140*M140,"-") -> - | R140: =IF(J140=3/4,K140*L140,"-") -> -
J143: LONGITUD TOTAL (M) | N143: =SUM(N50:N70) -> 0 | O143: =SUM(O50:O142) -> 125.62 | P143: =SUM(P50:P70) -> 0 | Q143: =SUM(Q50:Q70) -> 0 | R143: =SUM(R50:R70) -> 0
J144: PESO x M.L (kg) | N144: 0.22 | O144: 0.56 | P144: 0.994 | Q144: 1.552 | R144: 2.235
J145: SUB TOTAL | N145: =N143*N144 -> 0 | O145: =O143*O144 -> 70.3472 | P145: =P143*P144 -> 0 | Q145: =Q143*Q144 -> 0 | R145: =R143*R144 -> 0
J146: N° DE UNIDADES | M146: 1
J147: PESO TOTAL (KG) | M147: =SUM(N145:S145)*M146 -> 70.3472
B150: METRADO DE ACERO DE REFUERZO
B151: PROYECTO | D151: "CREACION DEL SERVICIO DE AGUA POTABLE RURAL Y CREACION DEL SERVICIO DE ALCANTARILLADO U OTRAS FORMAS DE DISPOSICION SANITARIA DE EXCRETAS EN EL SECTOR NUEVA ESPERANZA DE LA CC.NN. BAJO PITOCUNA DISTRITO DE RIO NEGRO, PROVINCIA DE SATIPO, DEPARTAMENTO DE JUNIN" | P151: ESTRUCTURA :
P152: CAPTACIÓN TIPO LADERA
P153: CÁMARA SECA
B155: ITEM | C155: DESCRIPCION | D155: FORMA | J155: Ø (Pulg) | K155: LONG. (m) | L155: # BARRAS | M155: # ELEMEN. | N155: LARGO TOTAL | S155: OBSERV.
L156: ELEMENTO | M156: ELEMENTO | N156: 0.25 | O156: 0.375 | P156: 0.5 | Q156: 0.625 | R156: 0.75
C157: Acero losa de fondo eje x-x
B160: 1 | E160: 0.15 | H160: 0.15 | J160: 0.375 | K160: =SUM(D157:I162) -> 1.13 | L160: 5 | M160: 1 | N160: =IF(J160=1/4,L160*K160*M160,"-") -> - | O160: =IF(J160=3/8,K160*L160*M160,"-") -> 5.65 | P160: =IF(J160=1/2,L160*K160*M160,"-") -> - | Q160: =IF(J160=5/8,L160*K160*M160,"-") -> - | R160: =IF(J160=3/4,K160*L160,"-") -> -
F162: 0.83
C163: Acero losa de fondo eje y-y
B166: 2 | E166: 0.15 | H166: 0.15 | J166: 0.375 | K166: =SUM(D163:I168) -> 1.09 | L166: 3 | M166: 1 | N166: =IF(J166=1/4,L166*K166*M166,"-") -> - | O166: =IF(J166=3/8,K166*L166*M166,"-") -> 3.27 | P166: =IF(J166=1/2,L166*K166*M166,"-") -> - | Q166: =IF(J166=5/8,L166*K166*M166,"-") -> - | R166: =IF(J166=3/4,K166*L166,"-") -> -
F168: 0.79
C169: Acero muro de salida- vertical
G171: 0.63
...

Sheet 1.3 L-COND.
A2: HOJA DE METRADOS DE AGUA POTABLE
A3: "CREACION DEL SERVICIO DE AGUA POTABLE RURAL Y CREACION DEL SERVICIO DE ALCANTARILLADO U OTRAS FORMAS DE DISPOSICION SANITARIA DE EXCRETAS EN EL SECTOR NUEVA ESPERANZA DE LA CC.NN. BAJO PITOCUNA DISTRITO DE RIO NEGRO, PROVINCIA DE SATIPO, DEPARTAMENTO DE JUNIN"
A4: LINEA DE CONDUCCIÓN
B6: Zanja Tipica | C6: =+C8&" x "&C7&" m" -> 0.5 x 0.7 m | D6: normal | E6: MANGUERA HDPE - 1 1/2"
B7: Altura | C7: 0.7 | D7: m
B8: Ancho | C8: 0.5 | D8: m
B9: Cama de Apoyo | C9: 0.1 | D9: m
B10: Capas de relleno con material propio | C10: =C7-C9 -> 0.6 | D10: m
A12: PARTIDA | B12: DESCRIPCION | C12: UNIDAD | D12: VECES | E12: LONGITUD | F12: ANCHO | G12: ALTURA | H12: SUB-TOTAL | I12: TOTAL
A13: =+"01.03" -> 01.03 | B13: =A4&" L= "&E17&"m" -> LINEA DE CONDUCCIÓN L= 139.7m | E13: =SUM(E14:E14) -> 139.7
B14: MANGUERA HDPE Ø 1 1/2" PN-8 TERRENO SUELTOS | C14: ML | D14: 1 | E14: 139.7
A16: =A$13 & ".01" -> 01.03.01 | B16: TRABAJOS PRELIMINARES
A17: =A$16 & ".01" -> 01.03.01.01 | B17: LIMPIEZA Y DESBROCE DE TERRENO MANUAL | C17: ML | D17: 1 | E17: =E13 -> 139.7 | H17: =+ROUND(PRODUCT(D17:G17),2) -> 139.7 | I17: =+H17 -> 139.7
A18: =A$16 & ".02" -> 01.03.01.02 | B18: TRAZO Y REPLANTEO PRELIMINAR EN LINEAS Y REDES | C18: ML | D18: 1 | E18: =E13 -> 139.7 | H18: =+ROUND(PRODUCT(D18:G18),2) -> 139.7 | I18: =+H18 -> 139.7
A19: =A$16 & ".03" -> 01.03.01.03 | B19: TRAZO Y REPLANTEO DURANTE EL PROCESO DE EJECUCION EN LINEAS Y REDES | C19: ML | D19: 1 | E19: =E13 -> 139.7 | H19: =+ROUND(PRODUCT(D19:G19),2) -> 139.7 | I19: =+H19 -> 139.7
A21: =A$13 & ".02" -> 01.03.02 | B21: MOVIMIENTO DE TIERRAS
A22: =$A$21 & ".01" -> 01.03.02.01 | B22: EXCAVACION MANUAL EN TERRENO SUELTO DE ZANJA DE 0.40 x 0.30 m P/MANGUERA HDPE | C22: ML | D22: 1 | E22: =E14 -> 139.7 | H22: =+ROUND(PRODUCT(D22:G22),2) -> 139.7 | I22: =+H22 -> 139.7
A23: =$A$21 & ".02" -> 01.03.02.02 | B23: RELLENO DE ZANJA, CON MAT. PROPIO, E=0.40m A=0.30m P/MANGUERA HDPE | C23: ML | D23: 1 | E23: =+E13 -> 139.7 | H23: =+ROUND(PRODUCT(D23:G23),2) -> 139.7 | I23: =+H23 -> 139.7
A24: =$A$21 & ".03" -> 01.03.02.03 | B24: ACARREO Y ELIMINACION DE MAT. EXCEDENTE Dmax=30 m | C24: M3 | H24: =SUM(H25:H26) -> 3.31 | I24: =+H24 -> 3.31
B25: Excavacion - Esponjamiento 25% terreno herbaceo | D25: 1.25 | E25: =E13 -> 139.7 | F25: 0.4 | G25: 0.3 | H25: =+ROUND(PRODUCT(D25:G25),2) -> 20.96
B26: Relleno | D26: =-1/0.95 -> -1.0526316 | E26: =+I22 -> 139.7 | F26: =+F25 -> 0.4 | G26: =G25 -> 0.3 | H26: =+ROUND(PRODUCT(D26:G26),2) -> -17.65
A28: =A$13 & ".03" -> 01.03.03 | B28: SUMINISTRO E INSTALACION DE TUBERIAS
A29: =A28 & ".01" -> 01.03.03.01 | B29: SUMINISTRO E INSTALACION DE MANGUERA HDPE NTP - ISO 4427: 2008 PE 80, PN=10, ø=44.4mm | C29: ML | D29: 1 | E29: =SUM(E14:E14) -> 139.7 | H29: =+ROUND(PRODUCT(D29:G29),2) -> 139.7 | I29: =+H29 -> 139.7
A31: =A$13 & ".04" -> 01.03.04 | B31: SUMINISTRO E INSTALACION DE ACCESORIOS
A32: =A31 & ".01" -> 01.03.04.01 | B32: SUMINISTRO E INSTALACION DE UNION ENLACE P/MANG. HDPE, PN-8 ø=44.4mm | C32: UND | D32: 1 | H32: =+ROUND(PRODUCT(D32:G32),2) -> 1 | I32: =+H32 -> 1
A34: =A$13 & ".05" -> 01.03.05 | B34: PRUEBA HIDRAULICA
A35: =A34 &".01" -> 01.03.05.01 | B35: PRUEBA HIDRÁULICA Y DESINFECCIÓN DE LA MANGUERA HDPE | C35: ML | D35: 1 | E35: =SUM(E14:E14) -> 139.7 | H35: =+ROUND(PRODUCT(D35:G35),2) -> 139.7 | I35: =+H35 -> 139.7

Sheet 1.4 RESERV. 5M3
A2: HOJA DE METRADOS DE SISTEMA DE AGUA POTABLE
A3: "CREACION DEL SERVICIO DE AGUA POTABLE RURAL Y CREACION DEL SERVICIO DE ALCANTARILLADO U OTRAS FORMAS DE DISPOSICION SANITARIA DE EXCRETAS EN EL SECTOR NUEVA ESPERANZA DE LA CC.NN. BAJO PITOCUNA DISTRITO DE RIO NEGRO, PROVINCIA DE SATIPO, DEPARTAMENTO DE JUNIN"
A5: RESERVORIO CUADRADO APOYADO DE V=5 m3
A25: PARTIDA | B25: DESCRIPCION | C25: UNID. | D25: VECES | E25: LONG. | F25: ANCHO/AREA | G25: ALTURA | H25: SUB-TOTAL | I25: TOTAL
A26: 01.04 | B26: =+A5 -> RESERVORIO CUADRADO APOYADO DE V=5 m3 | D26: 1
A27: =A$26 & ".01" -> 01.04.01 | B27: ESTRUCTURAS
A28: =A$27 & ".01" -> 01.04.01.01 | B28: TRABAJOS PRELIMINARES
A30: =A$28 & ".01" -> 01.04.01.01.01 | B30: LIMPIEZA Y DESBROCE DE TERRENO MANUAL | C30: m2 | I30: =+SUM(H31:H31) -> 47.88
D31: 1 | E31: 7.6 | F31: 6.3 | H31: =+ROUND(PRODUCT(D31:G31),2) -> 47.88
A33: =A$28 & ".02" -> 01.04.01.01.02 | B33: TRAZO Y REPLANTEO PRILIMINAR | C33: m2 | I33: =+SUM(H34:H34) -> 47.88
D34: 1 | E34: =+E31 -> 7.6 | F34: =+F31 -> 6.3 | H34: =+ROUND(PRODUCT(D34:G34),2) -> 47.88
A36: =A$28 & ".03" -> 01.04.01.01.03 | B36: TRAZO Y REPLANTEO DURANTE EL PROCESO | C36: m2 | I36: =SUM(H37:H39) -> 22.89
B37: Cámara húmeda | D37: 1 | E37: 2.8 | F37: 2.8 | H37: =+ROUND(PRODUCT(D37:G37),2) -> 7.84
B38: Cámara de válvulas | D38: 1 | E38: 1.6 | F38: 1.4 | H38: =+ROUND(PRODUCT(D38:G38),2) -> 2.24
B39: Vereda | D39: 1 | E39: área | F39: 12.81 | H39: =+ROUND(PRODUCT(D39:G39),2) -> 12.81
A41: =A$27 & ".02" -> 01.04.01.02 | B41: MOVIMIENTO DE TIERRAS
A43: =A41& ".01" -> 01.04.01.02.01 | B43: EXCAVACION MANUAL EN TERRENO NORMAL | C43: m3 | I43: =+SUM(H44:H44) -> 13.37
B44: Ver plano de movimiento de tierras - CTL-PMT-01 | D44: 1 | G44: Volumen | H44: 13.37
A46: =A41& ".02" -> 01.04.01.02.02 | B46: NIVELACIÓN INTERIOR Y APISONADO (MANUAL) | C46: m2 | I46: =+SUM(H47:H49) -> 22.89
B47: Cámara húmeda | D47: 1 | E47: 2.8 | F47: 2.8 | H47: =+ROUND(PRODUCT(D47:G47),2) -> 7.84
B48: Cámara de válvulas | D48: 1 | E48: 1.6 | F48: 1.4 | H48: =+ROUND(PRODUCT(D48:G48),2) -> 2.24
B49: Vereda | D49: 1 | E49: área | F49: 12.81 | H49: =+ROUND(PRODUCT(D49:G49),2) -> 12.81
A51: =A41& ".03" -> 01.04.01.02.03 | B51: RELLENO COMPACTADO CON MATERIAL PROPIO SELECCIONADO | C51: m3 | I51: =+SUM(H52) -> 2.57
B52: Ver plano de movimiento de tierras - CTL-PMT-02 | D52: 1 | G52: Volumen | H52: 2.57
A54: =A41& ".04" -> 01.04.01.02.04 | B54: ACARREO Y ELIMINACION DE MATERIAL EXCEDENTE Dmax=30 m | C54: m3 | I54: =+SUM(H55:H56) -> 13.08
B55: Excavacion - Esponjamiento 20% | D55: 1 | F55: 1.2 | G55: =+I43 -> 13.37 | H55: =+ROUND(PRODUCT(D55:G55),2) -> 16.04
B56: Relleno - Compactacion 85% | D56: -1 | F56: 1.15 | G56: =+I51 -> 2.57 | H56: =+ROUND(PRODUCT(D56:G56),2) -> -2.96
A58: =A$26 & ".02" -> 01.04.02 | B58: CÁMARA HUMEDA O ALMACENAMIENTO DE RESERVORIO
A59: =A$58& ".01" -> 01.04.02.01 | B59: OBRAS DE CONCRETO SIMPLE
A60: =A$59& ".01" -> 01.04.02.01.01 | B60: SOLADO f'c=100 Kg/cm2, e=10 cm | C60: m2 | I60: =+SUM(H61:H61) -> 7.84
B61: Base de cámara húmeda | D61: 1 | E61: 2.8 | F61: 2.8 | H61: =+PRODUCT(D61:G61) -> 7.84
A63: =A$58& ".02" -> 01.04.02.02 | B63: OBRAS DE CONCRETO ARMADO
A64: =A$63& ".01" -> 01.04.02.02.01 | B64: CONCRETO F'C=210 KG/CM2 PARA CIMENTACIÓN Y LOSA DE FONDO | C64: m3 | I64: =+SUM(H65:H79) -> 2.24
B65: Zapata seccion 1 | D65: 1 | E65: 11.2 | F65: 0.5 | G65: 0.25 | H65: =+PRODUCT(D65:G65) -> 1.4
B70: Zapata seccion 2
D71: 1 | E71: 11.2 | F71: 0.1 | G71: 0.15 | H71: =+PRODUCT(D71:G71) -> 0.168
B75: Losa de Fondo | D75: 1 | E75: 2.8 | F75: 1.6 | G75: 0.15 | H75: =+PRODUCT(D75:G75) -> 0.672
A81: =A$63& ".02" -> 01.04.02.02.02 | B81: CONCRETO f'c=210 kg/cm2 EN MUROS | C81: m3 | I81: =SUM(H82:H83) -> 1.9035
B82: Muros laterales | D82: 2 | E82: 2.5 | F82: 0.15 | G82: 1.35 | H82: =+PRODUCT(D82:G82) -> 1.0125
B83: Muros frontal y posterior | D83: 2 | E83: 2.2 | F83: 0.15 | G83: 1.35 | H83: =+PRODUCT(D83:G83) -> 0.891
A85: =A$63& ".03" -> 01.04.02.02.03 | B85: CONCRETO F'C=210 KG/CM2 PARA LOSA SUPERIOR | C85: m3 | I85: =SUM(H86:H88) -> 0.701
B86: Losa superior | D86: 1 | E86: 2.7 | F86: 2.7 | G86: 0.1 | H86: =+PRODUCT(D86:G86) -> 0.729
B87: Descuento de tapa | D87: -1 | E87: 0.6 | F87: 0.6 | G87: 0.1 | H87: =+PRODUCT(D87:G87) -> -0.036
B88: Borde de soporte de tapa | D88: 2 | E88: 0.8 | F88: 0.1 | G88: 0.05 | H88: =+PRODUCT(D88:G88) -> 0.008
A90: =A$63& ".04" -> 01.04.02.02.04 | B90: ENCOFRADO Y DESENCOFRADO PARA LOSA DE FONDO | C90: m2 | I90: =SUM(H91:H91) -> 2.8
B91: Borde de losa de Fondo | D91: 1 | E91: 11.2 | G91: 0.25 | H91: =+PRODUCT(D91:G91) -> 2.8
A93: =A$63& ".05" -> 01.04.02.02.05 | B93: ENCOFRADO Y DESENCOFRADO EN MUROS | C93: m2 | I93: =SUM(H94:H95) -> 25.38
B94: Interior de muros | D94: 4 | E94: 2.2 | G94: 1.35 | H94: =+PRODUCT(D94:G94) -> 11.88
B95: Exterior de muros | D95: 4 | E95: 2.5 | G95: 1.35 | H95: =+PRODUCT(D95:G95) -> 13.5
A97: =A$63& ".06" -> 01.04.02.02.06 | B97: ENCOFRADO Y DESENCOFRADO PARA LOSA SUPERIOR | C97: m2 | I97: =SUM(H98:H104) -> 7.12
B98: Parte interior de losa superior | D98: 1 | E98: 2.2 | F98: 2.2 | H98: =+PRODUCT(D98:G98) -> 4.84
B99: Parte interior del borde de la losa superior | D99: 2 | E99: 2.7 | F99: 0.1 | H99: =+PRODUCT(D99:G99) -> 0.54
D100: 2 | E100: 2.5 | F100: 0.1 | H100: =+PRODUCT(D100:G100) -> 0.5
B101: Descuento de tapa | D101: -1 | E101: 0.6 | F101: 0.6 | H101: =+PRODUCT(D101:G101) -> -0.36
B102: Borde interior de soporte de tapa | D102: 4 | E102: 0.6 | G102: 0.15 | H102: =+PRODUCT(D102:G102) -> 0.36
B103: Borde exterior de soporte de tapa | D103: 4 | E103: 0.8 | G103: 0.05 | H103: =+PRODUCT(D103:G103) -> 0.16
B104: Borde de losa superior | D104: 4 | E104: 2.7 | G104: 0.1 | H104: =+PRODUCT(D104:G104) -> 1.08
A106: =A$63& ".07" -> 01.04.02.02.07 | B106: ACERO CORRUGADO f'y=4200 kg/cm2 G-60 EN RESERVORIO | C106: kg | I106: =SUM(H107:H107) -> 331.52
B107: Acero en cámara húmeda | D107: 1 | H107: 331.52
A109: =A$58& ".03" -> 01.04.02.03 | B109: REVOQUES Y ENLUCIDOS
A110: =A$109& ".01" -> 01.04.02.03.01 | B110: TARRAJEO CON IMPERMEABILIZANTE MEZCLA 1:2; E=1.5 CM | C110: m2 | I110: =+SUM(H111:H115) -> 21.56
B111: Interior de muros | D111: 4 | E111: 2.2 | G111: 1.35 | H111: =+ROUND(PRODUCT(D111:G111),2) -> 11.88
B112: Base de cámara húmeda | D112: 1 | E112: 2.2 | F112: 2.2 | H112: =+ROUND(PRODUCT(D112:G112),2) -> 4.84
B113: Interior de losa superior | D113: 1 | E113: 2.2 | F113: 2.2 | H113: =+ROUND(PRODUCT(D113:G113),2) -> 4.84
B114: Descuento de tapa | D114: -1 | E114: 0.6 | F114: 0.6 | H114: =+ROUND(PRODUCT(D114:G114),2) -> -0.36
B115: Borde interior de soporte de tapa | D115: 4 | E115: 0.6 | G115: 0.15 | H115: =+ROUND(PRODUCT(D115:G115),2) -> 0.36
A117: =A$109& ".02" -> 01.04.02.03.02 | B117: TARRAJEO INTERIOR Y EXTERIOR MEZCLA 1:4 E=1.5 CM | C117: m2 | I117: =+SUM(H118:H126) -> 22.99
B118: Exterior de muros | D118: 4 | E118: 2.5 | G118: 1.35 | H118: =+ROUND(PRODUCT(D118:G118),2) -> 13.5
B119: Parte inferior de borde de losa superior | D119: 2 | E119: 2.7 | F119: 0.1 | H119: =+ROUND(PRODUCT(D119:G119),2) -> 0.54
D120: 2 | E120: 2.5 | F120: 0.1 | H120: =+ROUND(PRODUCT(D120:G120),2) -> 0.5
B121: Parte exterior de losa superior | D121: 1 | E121: 2.7 | F121: 2.7 | H121: =+ROUND(PRODUCT(D121:G121),2) -> 7.29
B122: Descuento de tapa | D122: -1 | E122: 0.6 | F122: 0.6 | H122: =+ROUND(PRODUCT(D122:G122),2) -> -0.36
B123: Borde exterior de soporte de tapa | D123: 4 | E123: 0.8 | G123: 0.05 | H123: =+ROUND(PRODUCT(D123:G123),2) -> 0.16
B124: Parte superior de soporte de tapa | D124: 2 | E124: 0.8 | F124: 0.1 | H124: =+ROUND(PRODUCT(D124:G124),2) -> 0.16
D125: 2 | E125: 0.6 | F125: 0.1 | H125: =+ROUND(PRODUCT(D125:G125),2) -> 0.12
B126: Borde exterior de losa | D126: 4 | E126: 2.7 | G126: 0.1 | H126: =+ROUND(PRODUCT(D126:G126),2) -> 1.08
A128: =A$109& ".03" -> 01.04.02.03.03 | B128: MORTERO PARA PENDIENTE DE FONDO C:A 1:5 | C128: m2 | I128: =+H129 -> 4.84
B129: Losa de fondo de cámara humeda | D129: 1 | E129: 2.2 | F129: 2.2 | H129: =+ROUND(PRODUCT(D129:G129),2) -> 4.84
A131: =A$58& ".04" -> 01.04.02.04 | B131: PINTURA
A132: =A$131& ".01" -> 01.04.02.04.01 | B132: PINTURA LATEX EN EXTERIORES (DOS MANOS) PARA ESTRUCTURAS | C132: m2 | I132: =SUM(H133:H140) -> 22.87
B133: Exterior de muros | D133: 4 | E133: 2.5 | F133: 1.35 | H133: =+ROUND(PRODUCT(D133:G133),2) -> 13.5
B134: Exterior de losa superior | D134: 1 | E134: 2.7 | F134: 2.7 | H134: =+ROUND(PRODUCT(D134:G134),2) -> 7.29
B135: Descuento de tapa | D135: -1 | E135: 0.6 | F135: 0.6 | H135: =+ROUND(PRODUCT(D135:G135),2) -> -0.36
B136: Borde exterior de soporte de tapa | D136: 4 | E136: 0.8 | G136: 0.05 | H136: =+ROUND(PRODUCT(D136:G136),2) -> 0.16
B137: Parte superior de soporte de tapa | D137: 2 | E137: 0.8 | F137: 0.1 | H137: =+ROUND(PRODUCT(D137:G137),2) -> 0.16
B138: Parte inferior de borde de losa superior | D138: 2 | E138: 2.7 | F138: 0.1 | H138: =+ROUND(PRODUCT(D138:G138),2) -> 0.54
D139: 2 | E139: 2.5 | F139: 0.1 | H139: =+ROUND(PRODUCT(D139:G139),2) -> 0.5
B140: Borde exterior de losa | D140: 4 | E140: 2.7 | G140: 0.1 | H140: =+ROUND(PRODUCT(D140:G140),2) -> 1.08
A142: =A$58& ".05" -> 01.04.02.05 | B142: ESTRUCTURA METÁLICA
A143: =A$142& ".01" -> 01.04.02.05.01 | B143: ESCALERA INTERIOR / PELDAÑOS DE POLIPROPILENO DE 12MM | C143: und | I143: =H144 -> 4
B144: Peldaños de escalera interior | D144: 4 | H144: =+ROUND(PRODUCT(D144:G144),2) -> 4
A146: =A$142& ".02" -> 01.04.02.05.02 | B146: ESCALERA EXTERIOR/ TIPO MARINERA ESCALINES DE F°G° Ø=3/4" | C146: und | I146: =H147 -> 1
B147: Escalera exterior tipo marinera | D147: 1 | H147: 1
A149: =A$142& ".03" -> 01.04.02.05.03 | B149: SUMINISTRO E INST. DE TAPA METALICA DE 0.60 x 0.60 m e=1/8" INC. ACCESORIOS + PINTURA | C149: und | I149: =H150 -> 1
D150: 1 | H150: =+ROUND(PRODUCT(D150:G150),2) -> 1
A152: =A$142& ".04" -> 01.04.02.05.04 | B152: SUMINISTRO E INST. DE ACCESORIOS DE TUBO DE VENTILACION F°G° Ø = 2" | C152: und | I152: =H153 -> 1
D153: 1 | H153: 1
A155: =A$58& ".06" -> 01.04.02.06 | B155: VARIOS
A156: =A$155& ".01" -> 01.04.02.06.01 | B156: SUMINISTRO E INSTALACION DE JUNTA WATER STOP NEOPRENO 6" | C156: m | I156: =+SUM(H157:H157) -> 10
D157: 1 | E157: perimetro | F157: 10 | H157: =F157 -> 10
...

Sheet 1.4 METR.ACERO 5M3
B2: METRADO DE ACERO DE REFUERZO
B3: PROYECTO | D3: "CREACION DEL SERVICIO DE AGUA POTABLE RURAL Y CREACION DEL SERVICIO DE ALCANTARILLADO U OTRAS FORMAS DE DISPOSICION SANITARIA DE EXCRETAS EN EL SECTOR NUEVA ESPERANZA DE LA CC.NN. BAJO PITOCUNA DISTRITO DE RIO NEGRO, PROVINCIA DE SATIPO, DEPARTAMENTO DE JUNIN" | P3: ESTRUCTURA :
P4: RESERVORIO APOYADO V=5M3
P5: CÁMARA HÚMEDA
B6: ITEM | C6: DESCRIPCION | D6: FORMA | J6: Ø (Pulg) | K6: LONG. (m) | L6: # BARRAS | M6: # ELEMEN. | N6: LARGO TOTAL | S6: OBSERV.
L7: ELEMENTO | M7: ELEMENTO | N7: 0.25 | O7: 0.375 | P7: 0.5 | Q7: 0.625 | R7: 0.75
C8: Acero losa de fondo - eye x-x
B10: 1 | E10: 0.1 | F10: 2.71 | I10: 0.1 | J10: 0.375 | K10: =SUM(D8:I12) -> 2.91 | L10: 16 | M10: 1 | N10: =IF(J10=1/4,L10*K10*M10,"-") -> - | O10: =IF(J10=3/8,K10*L10*M10,"-") -> 46.56 | P10: =IF(J10=1/2,L10*K10*M10,"-") -> - | Q10: =IF(J10=5/8,L10*K10*M10,"-") -> - | R10: =IF(J10=3/4,K10*L10,"-") -> -
C13: Acero losa de fondo - eye x-x
B14: 2 | F14: 0.3 | G14: 0.3 | J14: 0.375 | K14: =SUM(D13:I18) -> 2.2 | L14: 16 | M14: 1 | N14: =IF(J14=1/4,L14*K14*M14,"-") -> - | O14: =IF(J14=3/8,K14*L14*M14,"-") -> 35.2 | P14: =IF(J14=1/2,L14*K14*M14,"-") -> - | Q14: =IF(J14=5/8,L14*K14*M14,"-") -> - | R14: =IF(J14=3/4,K14*L14,"-") -> -
E15: 0.24 | H15: 0.24 | I15: 0.1
D16: 0.1
E17: 0.46 | H17: 0.46
C19: Acero losa de fondo - eye y-y
E21: 0.1 | F21: 2.71 | I21: 0.1
B22: 3 | J22: 0.375 | K22: =SUM(D19:I23) -> 2.91 | L22: 16 | M22: 1 | N22: =IF(J22=1/4,L22*K22*M22,"-") -> - | O22: =IF(J22=3/8,K22*L22*M22,"-") -> 46.56 | P22: =IF(J22=1/2,L22*K22*M22,"-") -> - | Q22: =IF(J22=5/8,L22*K22*M22,"-") -> - | R22: =IF(J22=3/4,K22*L22,"-") -> -
C24: Acero losa de fondo - eye y-y
F25: 0.3 | G25: 0.3
E26: 0.24 | H26: 0.24 | I26: 0.1
B27: 4 | D27: 0.1 | J27: 0.375 | K27: =SUM(D24:I29) -> 2.2 | L27: 16 | M27: 1 | N27: =IF(J27=1/4,L27*K27*M27,"-") -> - | O27: =IF(J27=3/8,K27*L27*M27,"-") -> 35.2 | P27: =IF(J27=1/2,L27*K27*M27,"-") -> - | Q27: =IF(J27=5/8,L27*K27*M27,"-") -> - | R27: =IF(J27=3/4,K27*L27,"-") -> -
E28: 0.46 | H28: 0.46
C30: Acero horizontal muro
F31: 2.47
D32: 0.15 | I32: 0.15
B33: 5 | E33: 0.15 | F33: 2.33 | H33: 0.15 | J33: 0.375 | K33: =SUM(D30:I34) -> 5.4 | L33: 8 | M33: 4 | N33: =IF(J33=1/4,L33*K33*M33,"-") -> - | O33: =IF(J33=3/8,K33*L33*M33,"-") -> 172.8 | P33: =IF(J33=1/2,L33*K33*M33,"-") -> - | Q33: =IF(J33=5/8,L33*K33*M33,"-") -> - | R33: =IF(J33=3/4,K33*L33,"-") -> -
C35: Acero vertical muro | E35: 0.12 | F35: 0.15
E38: 1.62 | F38: 1.62
B39: 6 | J39: 0.375 | K39: =SUM(D35:I42) -> 3.81 | L39: 12 | M39: 4 | N39: =IF(J39=1/4,L39*K39*M39,"-") -> - | O39: =IF(J39=3/8,K39*L39*M39,"-") -> 182.88 | P39: =IF(J39=1/2,L39*K39*M39,"-") -> - | Q39: =IF(J39=5/8,L39*K39*M39,"-") -> - | R39: =IF(J39=3/4,K39*L39,"-") -> -
E42: 0.15 | F42: 0.15
C43: Acero en losa superior en eje x-x
F44: 2.64
B45: 7 | J45: 0.375 | K45: =SUM(D43:I46) -> 2.64 | L45: 13 | M45: 1 | N45: =IF(J45=1/4,L45*K45*M45,"-") -> - | O45: =IF(J45=3/8,K45*L45*M45,"-") -> 34.32 | P45: =IF(J45=1/2,L45*K45*M45,"-") -> - | Q45: =IF(J45=5/8,L45*K45*M45,"-") -> - | R45: =IF(J45=3/4,K45*L45,"-") -> -
C47: Acero en losa superior en eje y-y
F48: 2.64
B49: 8 | J49: 0.375 | K49: =SUM(D47:I51) -> 2.64 | L49: 13 | M49: 1 | N49: =IF(J49=1/4,L49*K49*M49,"-") -> - | O49: =IF(J49=3/8,K49*L49*M49,"-") -> 34.32 | P49: =IF(J49=1/2,L49*K49*M49,"-") -> - | Q49: =IF(J49=5/8,L49*K49*M49,"-") -> - | R49: =IF(J49=3/4,K49*L49,"-") -> -
C52: Acero en horizontal en borde de soporte de tapa
F53: 0.74
B54: 9 | E54: 0.15 | F54: 0.15 | J54: 0.375 | K54: =SUM(D52:I56) -> 1.04 | L54: 4 | M54: 1 | N54: =IF(J54=1/4,L54*K54*M54,"-") -> - | O54: =IF(J54=3/8,K54*L54*M54,"-") -> 4.16 | P54: =IF(J54=1/2,L54*K54*M54,"-") -> - | Q54: =IF(J54=5/8,L54*K54*M54,"-") -> - | R54: =IF(J54=3/4,K54*L54,"-") -> -
J57: LONGITUD TOTAL (M) | N57: =SUM(N8:N29) -> 0 | O57: =SUM(O8:O56) -> 592 | P57: =SUM(P8:P29) -> 0 | Q57: =SUM(Q8:Q29) -> 0 | R57: =SUM(R8:R29) -> 0
J58: PESO x M.L (kg) | N58: 0.22 | O58: 0.56 | P58: 0.994 | Q58: 1.552 | R58: 2.235
J59: SUB TOTAL | N59: =N57*N58 -> 0 | O59: =O57*O58 -> 331.52 | P59: =P57*P58 -> 0 | Q59: =Q57*Q58 -> 0 | R59: =R57*R58 -> 0
J60: N° DE UNIDADES | M60: 1
J61: PESO TOTAL (KG) | M61: =SUM(N59:S59)*M60 -> 331.52
B64: METRADO DE ACERO DE REFUERZO
B65: PROYECTO | D65: "CREACION DEL SERVICIO DE AGUA POTABLE RURAL Y CREACION DEL SERVICIO DE ALCANTARILLADO U OTRAS FORMAS DE DISPOSICION SANITARIA DE EXCRETAS EN EL SECTOR NUEVA ESPERANZA DE LA CC.NN. BAJO PITOCUNA DISTRITO DE RIO NEGRO, PROVINCIA DE SATIPO, DEPARTAMENTO DE JUNIN" | P65: ESTRUCTURA :
P66: RESERVORIO APOYADO V=5M3
P67: CÁMARA DE VÁLVULAS
B68: ITEM | C68: DESCRIPCION | D68: FORMA | J68: Ø (Pulg) | K68: LONG. (m) | L68: # BARRAS | M68: # ELEMEN. | N68: LARGO TOTAL | S68: OBSERV.
L69: ELEMENTO | M69: ELEMENTO | N69: 0.25 | O69: 0.375 | P69: 0.5 | Q69: 0.625 | R69: 0.75
C70: Acero losa de fondo - eye x-x
B72: 1 | F72: 1.22 | J72: 0.375 | K72: =SUM(D70:I74) -> 1.22 | L72: 8 | M72: 1 | N72: =IF(J72=1/4,L72*K72*M72,"-") -> - | O72: =IF(J72=3/8,K72*L72*M72,"-") -> 9.76 | P72: =IF(J72=1/2,L72*K72*M72,"-") -> - | Q72: =IF(J72=5/8,L72*K72*M72,"-") -> - | R72: =IF(J72=3/4,K72*L72,"-") -> -
C75: Acero losa de fondo - eye y-y
B76: 2 | F76: 1.32 | J76: 0.375 | K76: =SUM(D75:I78) -> 1.32 | L76: 6 | M76: 1 | N76: =IF(J76=1/4,L76*K76*M76,"-") -> - | O76: =IF(J76=3/8,K76*L76*M76,"-") -> 7.92 | P76: =IF(J76=1/2,L76*K76*M76,"-") -> - | Q76: =IF(J76=5/8,L76*K76*M76,"-") -> - | R76: =IF(J76=3/4,K76*L76,"-") -> -
C79: Acero horizontal muro
B81: 3 | E81: 0.15 | F81: 1.34 | I81: 0.15 | J81: 0.375 | K81: =SUM(D79:I83) -> 1.64 | L81: 5 | M81: 4 | N81: =IF(J81=1/4,L81*K81*M81,"-") -> - | O81: =IF(J81=3/8,K81*L81*M81,"-") -> 32.8 | P81: =IF(J81=1/2,L81*K81*M81,"-") -> - | Q81: =IF(J81=5/8,L81*K81*M81,"-") -> - | R81: =IF(J81=3/4,K81*L81,"-") -> -
C84: Acero vertical muro
F85: 0.15
B86: 4 | F86: 1.03 | J86: 0.375 | K86: =SUM(D84:I89) -> 1.33 | L86: 20 | M86: 1 | N86: =IF(J86=1/4,L86*K86*M86,"-") -> - | O86: =IF(J86=3/8,K86*L86*M86,"-") -> 26.6 | P86: =IF(J86=1/2,L86*K86*M86,"-") -> - | Q86: =IF(J86=5/8,L86*K86*M86,"-") -> - | R86: =IF(J86=3/4,K86*L86,"-") -> -
F88: 0.15
C90: Acero losa superior eje y-y
F91: 0.15
F92: 1.32
B93: 5 | J93: 0.375 | K93: =SUM(D90:I95) -> 1.62 | L93: 7 | M93: 1 | N93: =IF(J93=1/4,L93*K93*M93,"-") -> - | O93: =IF(J93=3/8,K93*L93*M93,"-") -> 11.34 | P93: =IF(J93=1/2,L93*K93*M93,"-") -> - | Q93: =IF(J93=5/8,L93*K93*M93,"-") -> - | R93: =IF(J93=3/4,K93*L93,"-") -> -
F94: 0.15
C96: Acero losa superior eje x-x
F97: 1.32
B99: 6 | E99: 0.15 | G99: 0.15 | J99: 0.375 | K99: =SUM(D96:I101) -> 1.62 | L99: 8 | M99: 1 | N99: =IF(J99=1/4,L99*K99*M99,"-") -> - | O99: =IF(J99=3/8,K99*L99*M99,"-") -> 12.96 | P99: =IF(J99=1/2,L99*K99*M99,"-") -> - | Q99: =IF(J99=5/8,L99*K99*M99,"-") -> - | R99: =IF(J99=3/4,K99*L99,"-") -> -
J102: LONGITUD TOTAL (M) | N102: =SUM(N70:N89) -> 0 | O102: =SUM(O70:O101) -> 101.38 | P102: =SUM(P70:P89) -> 0 | Q102: =SUM(Q70:Q89) -> 0 | R102: =SUM(R70:R89) -> 0
J103: PESO x M.L (kg) | N103: 0.22 | O103: 0.56 | P103: 0.994 | Q103: 1.552 | R103: 2.235
J104: SUB TOTAL | N104: =N102*N103 -> 0 | O104: =O102*O103 -> 56.7728 | P104: =P102*P103 -> 0 | Q104: =Q102*Q103 -> 0 | R104: =R102*R103 -> 0
J105: N° DE UNIDADES | M105: 1
J106: PESO TOTAL (KG) | M106: =SUM(N104:S104)*M105 -> 56.7728
B109: METRADO DE ACERO DE REFUERZO
B110: PROYECTO | D110: "CREACION DEL SERVICIO DE AGUA POTABLE RURAL Y CREACION DEL SERVICIO DE ALCANTARILLADO U OTRAS FORMAS DE DISPOSICION SANITARIA DE EXCRETAS EN EL SECTOR NUEVA ESPERANZA DE LA CC.NN. BAJO PITOCUNA DISTRITO DE RIO NEGRO, PROVINCIA DE SATIPO, DEPARTAMENTO DE JUNIN" | P110: ESTRUCTURA :
P111: RESERVORIO APOYADO V=5M3
P112: CASETA DE CLORACIÓN
B113: ITEM | C113: DESCRIPCION | D113: FORMA | J113: Ø (Pulg) | K113: LONG. (m) | L113: # BARRAS | M113: # ELEMEN. | N113: LARGO TOTAL | S113: OBSERV.
L114: ELEMENTO | M114: ELEMENTO | N114: 0.25 | O114: 0.375 | P114: 0.5 | Q114: 0.625 | R114: 0.75
C115: Acero horizontal muro eje x-x
E116: 0.15 | F116: 0.73
B117: 1 | J117: 0.375 | K117: =SUM(D115:I119) -> 1.76 | L117: 4 | M117: 1 | N117: =IF(J117=1/4,L117*K117*M117,"-") -> - | O117: =IF(J117=3/8,K117*L117*M117,"-") -> 7.04 | P117: =IF(J117=1/2,L117*K117*M117,"-") -> - | Q117: =IF(J117=5/8,L117*K117*M117,"-") -> - | R117: =IF(J117=3/4,K117*L117,"-") -> -
E118: 0.15 | F118: 0.73
C120: Acero horizontal muro eje y-y
F121: 0.15
B122: 2 | F122: 1.04 | J122: 0.375 | K122: =SUM(D120:I125) -> 1.34 | L122: 4 | M122: 1 | N122: =IF(J122=1/4,L122*K122*M122,"-") -> - | O122: =IF(J122=3/8,K122*L122*M122,"-") -> 5.36 | P122: =IF(J122=1/2,L122*K122*M122,"-") -> - | Q122: =IF(J122=5/8,L122*K122*M122,"-") -> - | R122: =IF(J122=3/4,K122*L122,"-") -> -
F124: 0.15
C126: Acero vertical muro
F127: 0.15
B128: 3 | F128: 1.04 | J128: 0.375 | K128: =SUM(D126:I131) -> 1.34 | L128: 12 | M128: 1 | N128: =IF(J128=1/4,L128*K128*M128,"-") -> - | O128: =IF(J128=3/8,K128*L128*M128,"-") -> 16.08 | P128: =IF(J128=1/2,L128*K128*M128,"-") -> - | Q128: =IF(J128=5/8,L128*K128*M128,"-") -> - | R128: =IF(J128=3/4,K128*L128,"-") -> -
F130: 0.15
C132: Acero en losa superior eje x-x
F133: 0.73
B134: 4 | J134: 0.375 | K134: =SUM(D132:I137) -> 0.88 | L134: 6 | M134: 1 | N134: =IF(J134=1/4,L134*K134*M134,"-") -> - | O134: =IF(J134=3/8,K134*L134*M134,"-") -> 5.28 | P134: =IF(J134=1/2,L134*K134*M134,"-") -> - | Q134: =IF(J134=5/8,L134*K134*M134,"-") -> - | R134: =IF(J134=3/4,K134*L134,"-") -> -
E135: 0.15
C138: Acero losa superior eje y-y
F139: 0.15
F140: 1.04
B141: 5 | J141: 0.375 | K141: =SUM(D138:I143) -> 1.34 | L141: 4 | M141: 1 | N141: =IF(J141=1/4,L141*K141*M141,"-") -> - | O141: =IF(J141=3/8,K141*L141*M141,"-") -> 5.36 | P141: =IF(J141=1/2,L141*K141*M141,"-") -> - | Q141: =IF(J141=5/8,L141*K141*M141,"-") -> - | R141: =IF(J141=3/4,K141*L141,"-") -> -
F142: 0.15
J144: LONGITUD TOTAL (M) | N144: =SUM(N115:N137) -> 0 | O144: =SUM(O115:O143) -> 39.12 | P144: =SUM(P115:P137) -> 0 | Q144: =SUM(Q115:Q137) -> 0 | R144: =SUM(R115:R137) -> 0
...

Sheet 1.5 L-ADUCC.
A2: HOJA DE METRADOS DE AGUA POTABLE
A3: "CREACION DEL SERVICIO DE AGUA POTABLE RURAL Y CREACION DEL SERVICIO DE ALCANTARILLADO U OTRAS FORMAS DE DISPOSICION SANITARIA DE EXCRETAS EN EL SECTOR NUEVA ESPERANZA DE LA CC.NN. BAJO PITOCUNA DISTRITO DE RIO NEGRO, PROVINCIA DE SATIPO, DEPARTAMENTO DE JUNIN"
A4: LINEA DE ADUCCION
B6: Zanja Tipica | C6: =+C8&" x "&C7&" m" -> 0.5 x 0.7 m | D6: normal | E6: MANGUERA HDPE - 1 1/2"
B7: Altura | C7: 0.7 | D7: m
B8: Ancho | C8: 0.5 | D8: m
B9: Cama de Apoyo | C9: 0.1 | D9: m
B10: Capas de relleno con material propio | C10: =C7-C9 -> 0.6 | D10: m
A12: PARTIDA | B12: DESCRIPCION | C12: UNIDAD | D12: VECES | E12: LONGITUD | F12: ANCHO | G12: ALTURA | H12: SUB-TOTAL | I12: TOTAL
A13: =+"01.05" -> 01.05 | B13: =A4&" L= "&E17&"m" -> LINEA DE ADUCCION L= 185.94m | E13: =SUM(E14:E14) -> 185.94
B14: MANGUERA HDPE Ø 1 1/2" PN-10 TERRENO SUELTOS | C14: ML | D14: 1 | E14: 185.94
A16: =A$13 & ".01" -> 01.05.01 | B16: TRABAJOS PRELIMINARES
A17: =A$16 & ".01" -> 01.05.01.01 | B17: LIMPIEZA Y DESBROCE DE TERRENO MANUAL | C17: ML | D17: 1 | E17: =E13 -> 185.94 | H17: =+ROUND(PRODUCT(D17:G17),2) -> 185.94 | I17: =+H17 -> 185.94
A18: =A$16 & ".02" -> 01.05.01.02 | B18: TRAZO Y REPLANTEO PRELIMINAR EN LINEAS Y REDES | C18: ML | D18: 1 | E18: =E13 -> 185.94 | H18: =+ROUND(PRODUCT(D18:G18),2) -> 185.94 | I18: =+H18 -> 185.94
A19: =A$16 & ".03" -> 01.05.01.03 | B19: TRAZO Y REPLANTEO DURANTE EL PROCESO EN LINEAS Y REDES | C19: ML | D19: 1 | E19: =E13 -> 185.94 | H19: =+ROUND(PRODUCT(D19:G19),2) -> 185.94 | I19: =+H19 -> 185.94
A21: =A$13 & ".02" -> 01.05.02 | B21: MOVIMIENTO DE TIERRAS
A22: =$A$21 & ".01" -> 01.05.02.01 | B22: EXCAVACION MANUAL EN TERRENO SUELTO DE ZANJA DE 0.40 x 0.30 m P/MANGUERA HDPE | C22: ML | D22: 1 | E22: =E14 -> 185.94 | H22: =+ROUND(PRODUCT(D22:G22),2) -> 185.94 | I22: =+H22 -> 185.94
A23: =$A$21 & ".02" -> 01.05.02.02 | B23: RELLENO DE ZANJA, CON MAT. PROPIO, E=0.40m A=0.30m P/MANGUERA HDPE | C23: ML | D23: 1 | E23: =E13 -> 185.94 | H23: =+ROUND(PRODUCT(D23:G23),2) -> 185.94 | I23: =+H23 -> 185.94
A24: =$A$21 & ".03" -> 01.05.02.03 | B24: ACARREO Y ELIMINACION DE MAT. EXCEDENTE Dmax=30 m | C24: ML | D24: 1 | E24: 4.4 | H24: =+ROUND(PRODUCT(D24:G24),2) -> 4.4 | I24: =+H24 -> 4.4
A25: =A$13 & ".03" -> 01.05.03 | B25: SUMINISTRO E INSTALACION DE TUBERIAS
A26: =A25 & ".01" -> 01.05.03.01 | B26: SUMINISTRO E INSTALACION DE MANGUERA HDPE NTP - ISO 4427: 2008 PE 80, PN=10, ø=44.4mm | C26: ML | D26: 1 | E26: =SUM(E14:E14) -> 185.94 | H26: =+ROUND(PRODUCT(D26:G26),2) -> 185.94 | I26: =+H26 -> 185.94
A28: =A$13 & ".04" -> 01.05.04 | B28: SUMINISTRO E INSTALACION DE ACCESORIOS
A29: =A28 & ".01" -> 01.05.04.01 | B29: SUMINISTRO E INSTALACION DE UNION ENLACE P/MANG. HDPE, PN-10 ø=44.4mm | C29: UND | D29: 1 | H29: =+ROUND(PRODUCT(D29:G29),2) -> 1 | I29: =+H29 -> 1
A30: =A29 & ".02" -> 01.05.04.01.02 | B30: SUMINISTRO E INSTALACION DE UNION HDPE, PN=8" ø=43.4 MM | C30: UND | H30: =+ROUND(PRODUCT(D30:G30),2) -> 0 | I30: =+H30 -> 0
A32: =A$13 & ".05" -> 01.05.05 | B32: PRUEBA HIDRAULICA
A33: =A32 &".01" -> 01.05.05.01 | B33: PRUEBA HIDRAULICA Y DESINFECCION DE LA TUBERIA | C33: ML | D33: 1 | E33: =SUM(E14:E14) -> 185.94 | H33: =+ROUND(PRODUCT(D33:G33),2) -> 185.94 | I33: =+H33 -> 185.94

Sheet 1.6 RED DE DISTRIB.
B2: HOJA DE METRADOS DE AGUA POTABLE
B3: "CREACION DEL SERVICIO DE AGUA POTABLE RURAL Y CREACION DEL SERVICIO DE ALCANTARILLADO U OTRAS FORMAS DE DISPOSICION SANITARIA DE EXCRETAS EN EL SECTOR NUEVA ESPERANZA DE LA CC.NN. BAJO PITOCUNA DISTRITO DE RIO NEGRO, PROVINCIA DE SATIPO, DEPARTAMENTO DE JUNIN"
B4: RED DE DISTRIBUCION
C6: Zanja Tipica | D6: =+D8&" x "&D7&" m" -> 0.5 x 0.8 m | E6: Normal | F6: TUBERIA PVC - 3/4",1"
C7: Altura | D7: 0.8 | E7: m
C8: Ancho | D8: 0.5 | E8: m
C9: Cama de Apoyo | D9: 0.1 | E9: m
C10: 1ra Capas de compactacion | D10: 0.3 | E10: m
C11: 2ra Capas de compactacion | D11: 0.4 | E11: m
C13: Zanja Tipica | D13: =+D15&" x "&D14&" m" -> 0.5 x 1 m | E13: Normal | F13: TUBERIA PVC CARRETERA - 3/4",1"
C14: Altura | D14: 1 | E14: m
C15: Ancho | D15: 0.5 | E15: m
C16: Cama de Apoyo | D16: 0.1 | E16: m
C17: 1ra Capas de compactacion | D17: 0.3 | E17: m
C18: 2ra Capas de compactacion | D18: 0.6 | E18: m
B21: PARTIDA | C21: DESCRIPCION | D21: UNIDAD | E21: VECES | F21: LONGITUD | G21: ANCHO | H21: ALTURA | I21: SUB-TOTAL | J21: TOTAL
B22: =+"01.06" -> 01.06 | C22: =B4&" L= "&F54&"m" -> RED DE DISTRIBUCION L= 1066.66m | F22: =SUM(F23:F51) -> 1097.16
C23: Tubería PVC Ø 3/4" C-10 - TERRENO NORMAL EN CARRETERA | D23: ML | E23: 1 | F23: =SUM(E24:E27) -> 86.04
C24: T-10 | E24: 31.83
C25: T-12 | E25: 27.29
C26: T-13 | E26: 53.92
C27: MENOS T-13 PRUFUNDIZADA TUB 13 | E27: -27
C29: Tubería PVC Ø 1" C-10 - TERRENO NORMAL EN CARRETERA | D29: ML | E29: 1 | F29: =SUM(E30:E37) -> 258.29
C30: T-11-INICIO | E30: 7.75
C31: T-11-FINAL | E31: 4.7
C32: T-14 | E32: 44.4
C33: T-18 | E33: 64.18
C34: T-19 | E34: 43.6
C35: T-20 | E35: 23.21
C36: T-21 | E36: 29.37
C37: T-23 | E37: 41.08
C39: Tubería PVC Ø 3/4" C-10 - TERRENO NORMAL | D39: ML | E39: 1 | F39: =SUM(E40:E42) -> 305.94
C40: TOTAL | E40: 414.98
C41: TUBERIA EN CARRETERA | E41: =-F23 -> -86.04
C42: TUBERIA PROFUNDIZADA TUBERIA 15 | E42: -23
C44: Tubería PVC Ø 1" C-10 - TERRENO NORMAL | D44: ML | E44: 1 | F44: =SUM(E45:E49) -> 396.89
C45: TOTAL | E45: 682.18
C46: MENOS TUBERIA EN CARRETERA | E46: =-F29 -> -258.29
C47: MENOS TUBERIA DE CRUCE EN PUENTE MODULAR | E47: -24.5
C48: MENOS TUBERIA CRUCE EN ALCANTARILLA TMC 24" | E48: -6
C49: TUBERIA DE ALCANTARILLADO | E49: 3.5
C51: Tubería PVC Ø 3/4" C-10 - TERRENO NORMAL H=0.90 A 1.90m. Hprom=1.40m | D51: ML | E51: 1 | F51: 50
B53: =B$22 & ".01" -> 01.06.01 | C53: TRABAJOS PRELIMINARES
B54: =B$53 & ".01" -> 01.06.01.01 | C54: LIMPIEZA Y DESBROCE DE TERRENO MANUAL | D54: ML | E54: 1 | F54: =F22+E47+E48 -> 1066.66 | I54: =+ROUND(PRODUCT(E54:H54),2) -> 1066.66 | J54: =+I54 -> 1066.66
B55: =B$53 & ".02" -> 01.06.01.02 | C55: TRAZO Y REPLANTEO PRELIMINAR EN LINEAS Y REDES | D55: ML | E55: 1 | F55: =F54 -> 1066.66 | I55: =+ROUND(PRODUCT(E55:H55),2) -> 1066.66 | J55: =+I55 -> 1066.66
B56: =B$53 & ".03" -> 01.06.01.03 | C56: TRAZO Y REPLANTEO DURANTE EL PROCESO EN LINEAS Y REDES | D56: ML | E56: 1 | F56: =F54 -> 1066.66 | I56: =+ROUND(PRODUCT(E56:H56),2) -> 1066.66 | J56: =+I56 -> 1066.66
B58: =B$22 & ".02" -> 01.06.02 | C58: MOVIMIENTO DE TIERRAS
B59: =B$58 & ".01" -> 01.06.02.01 | C59: EXCAVACION DE ZANJA CON MAQUINARIA EN TERRENO NORMAL DE 0.50 x 1.10 m P/TUBERIA EN CARRETERA | D59: ML | E59: 1 | F59: =F23+F29 -> 344.33 | I59: =+ROUND(PRODUCT(E59:H59),2) -> 344.33 | J59: =+I59 -> 344.33
B60: =B$58 & ".02" -> 01.06.02.02 | C60: EXCAVACION MANUAL EN TERRENO NORMAL DE ZANJA DE 0.50 x 0.80 m P/TUBERIA | D60: ML | E60: 1 | F60: =F39+F44 -> 702.83 | I60: =+ROUND(PRODUCT(E60:H60),2) -> 702.83 | J60: =+I60 -> 702.83
B61: =B$58 & ".03" -> 01.06.02.03 | C61: EXCAVACION DE ZANJA CON MAQUINARIA EN TERRENO NORMAL DE 0.60 x 1.40 m P/TUBERIA PROFUNDIZADA | D61: ML | E61: 1 | F61: =F51 -> 50 | I61: =+ROUND(PRODUCT(E61:H61),2) -> 50 | J61: =+I61 -> 50
B62: =B$58 & ".04" -> 01.06.02.04 | C62: REFINE Y NIVELACION DE FONDO PARA ZANJA DE 0.50 x 1.10 m P/TUBERIA EN CARRETERA | D62: ML | E62: 1 | F62: =F59 -> 344.33 | I62: =+ROUND(PRODUCT(E62:H62),2) -> 344.33 | J62: =+I62 -> 344.33
B63: =B$58 & ".05" -> 01.06.02.05 | C63: REFINE Y NIVELACION DE FONDO PARA ZANJA DE 0.50 x 0.80 m P/TUBERIA | D63: ML | E63: 1 | F63: =F60 -> 702.83 | I63: =+ROUND(PRODUCT(E63:H63),2) -> 702.83 | J63: =+I63 -> 702.83
B64: =B$58 & ".06" -> 01.06.02.06 | C64: REFINE Y NIVELACION DE FONDO PARA ZANJA DE 0.60 x 1.40 m P/TUBERIA PROFUNDIZADA | D64: ML | E64: 1 | F64: =F61 -> 50 | I64: =+ROUND(PRODUCT(E64:H64),2) -> 50 | J64: =+I64 -> 50
B65: =B$58 & ".07" -> 01.06.02.07 | C65: CAMA DE APOYO PARA TUBERIA CON MAT. PROPIO ZARANDEADO E=0.10m, A=0.50 m | D65: ML | E65: 1 | F65: =F59+F60 -> 1047.16 | I65: =+ROUND(PRODUCT(E65:H65),2) -> 1047.16 | J65: =+I65 -> 1047.16
B66: =B$58 & ".08" -> 01.06.02.08 | C66: CAMA DE APOYO PARA TUBERIA CON MAT. PROPIO ZARANDEADO E=0.10m, A=0.60 m TUB. PROFUNDIZADA | D66: ML | E66: 1 | F66: =F61 -> 50 | I66: =+ROUND(PRODUCT(E66:H66),2) -> 50 | J66: =+I66 -> 50
B67: =B$58 & ".09" -> 01.06.02.09 | C67: PRIMER RELLENO COMPACTADO DE ZANJA, CON MAT. PROPIO ZARANDEADO, E=0.30m, A=0.50 m | D67: ML | E67: 1 | F67: =F59+F60 -> 1047.16 | I67: =+ROUND(PRODUCT(E67:H67),2) -> 1047.16 | J67: =+I67 -> 1047.16
B68: =B$58 & ".10" -> 01.06.02.10 | C68: PRIMER RELLENO COMPACTADO DE ZANJA, CON MAT. PROPIO ZARANDEADO, E=0.30m, A=0.60 m P/TUBERIA PROFUNDIZADA | D68: ML | E68: 1 | F68: =F61 -> 50 | I68: =+ROUND(PRODUCT(E68:H68),2) -> 50 | J68: =+I68 -> 50
B69: =B$58&".11" -> 01.06.02.11 | C69: SEGUNDO RELLENO COMPACTADO DE ZANJA CON MAT. PROPIO EN CARRETERA, E=0.70m, A=0.50 m | D69: ML | E69: 1 | F69: =F59 -> 344.33 | I69: =+ROUND(PRODUCT(E69:H69),2) -> 344.33 | J69: =+I69 -> 344.33
B70: =B$58 & ".12" -> 01.06.02.12 | C70: SEGUNDO RELLENO COMPACTADO DE ZANJA CON MAT. PROPIO EN TERRENO NORMAL, E=0.40m, A=0.50 m | D70: ML | E70: 1 | F70: =F60 -> 702.83 | I70: =+ROUND(PRODUCT(E70:H70),2) -> 702.83 | J70: =+I70 -> 702.83
B71: =B$58 & ".13" -> 01.06.02.13 | C71: SEGUNDO RELLENO COMPACTADO DE ZANJA CON MAT. PROPIO EN TERRENO NORMAL, E=1.00m, A=0.60 m TUB. PROFUNDIZADA | D71: ML | E71: 1 | F71: =F61 -> 50 | I71: =+ROUND(PRODUCT(E71:H71),2) -> 50 | J71: =+I71 -> 50
B72: =B$58 & ".14" -> 01.06.02.14 | C72: ACARREO Y ELIMINACION DE MAT. EXCEDENTE Dmax=30 m | D72: M3 | E72: 1 | F72: vol. | I72: =+SUM(I73:I75) -> 159.43 | J72: =+I72 -> 159.43
C73: Excavacion - Esponjamiento 25% terreno normal | E73: 1.25 | F73: =(I59*0.5*1.1)+(I60*0.5*0.8)+(I61*0.6*1.4) -> 512.5135 | I73: =+ROUND(PRODUCT(E73:H73),2) -> 640.64
C74: primer relleno | E74: =-1/0.95 -> -1.0526316 | F74: =(I67*0.3*0.5)+(I68*0.3*0.6) -> 166.074 | I74: =+ROUND(PRODUCT(E74:H74),2) -> -174.81
C75: segundo relleno | E75: =-1/0.95 -> -1.0526316 | F75: =(I69*0.7*0.5)+(I70*0.4*0.5)+(I71*1*0.6) -> 291.0815 | I75: =+ROUND(PRODUCT(E75:H75),2) -> -306.4
B76: =B$22 & ".03" -> 01.06.03 | C76: SUMINISTRO E INSTALACION DE TUBERIAS
B77: =B76 & ".01" -> 01.06.03.01 | C77: SUMINISTRO E INSTALACION DE TUBERÍA PVC NTP 399.002 Ø 3/4" C-10. | D77: ML | E77: 1 | F77: =F23+F39+F51 -> 441.98 | I77: =+ROUND(PRODUCT(E77:H77),2) -> 441.98 | J77: =+I77 -> 441.98
B78: =B76 & ".02" -> 01.06.03.02 | C78: SUMINISTRO E INSTALACION DE TUBERÍA PVC NTP 399.002 Ø 1" C-10. | D78: ML | E78: 1 | F78: =F29+F44+E47+E48 -> 624.68 | I78: =+ROUND(PRODUCT(E78:H78),2) -> 624.68 | J78: =+I78 -> 624.68
B79: =B$22 & ".04" -> 01.06.04 | C79: SUMINISTRO E INSTALACION DE ACCESORIOS
B80: =B79 & ".01" -> 01.06.04.01 | C80: SUMINISTRO E INSTALACION DE CODO 90° PVC C-10 Ø 1" | D80: UND | E80: 4 | I80: =+ROUND(PRODUCT(E80:H80),2) -> 4 | J80: =+I80 -> 4
B81: =B79 & ".02" -> 01.06.04.02 | C81: SUMINISTRO E INSTALACION DE CODO 90° PVC C-10 Ø 3/4" | D81: UND | E81: 2 | I81: =+ROUND(PRODUCT(E81:H81),2) -> 2 | J81: =+I81 -> 2
B82: =B79 & ".03" -> 01.06.04.03 | C82: SUMINISTRO E INSTALACION DE CODO 45° PVC C-10 Ø 1" | D82: UND | E82: 8 | I82: =+ROUND(PRODUCT(E82:H82),2) -> 8 | J82: =+I82 -> 8
B83: =$B$79 & ".04" -> 01.06.04.04 | C83: SUMINISTRO E INSTALACION DE CODO 45° PVC C-10 Ø 3/4" | D83: UND | E83: 5 | I83: =+ROUND(PRODUCT(E83:H83),2) -> 5 | J83: =+I83 -> 5
B84: =$B$79 & ".05" -> 01.06.04.05 | C84: SUMINISTRO E INSTALACION DE TEE PVC C-10 Ø 1" | D84: UND | E84: 8 | I84: =+ROUND(PRODUCT(E84:H84),2) -> 8 | J84: =+I84 -> 8
B85: =$B$79 & ".06" -> 01.06.04.06 | C85: SUMINISTRO E INSTALACION DE TEE PVC C-10 Ø 1 1/2" | D85: UND | E85: 1 | I85: =+ROUND(PRODUCT(E85:H85),2) -> 1 | J85: =+I85 -> 1
B86: =$B$79 & ".07" -> 01.06.04.07 | C86: SUMINISTRO E INSTALACION DE REDUCCION PVC C-10 Ø 1 1/2" A Ø 1" | D86: UND | E86: 2 | I86: =+ROUND(PRODUCT(E86:H86),2) -> 2 | J86: =+I86 -> 2
B87: =$B$79 & ".08" -> 01.06.04.08 | C87: SUMINISTRO E INSTALACION DE REDUCCION PVC C-10 Ø 1" A Ø 3/4" | D87: UND | E87: 7 | I87: =+ROUND(PRODUCT(E87:H87),2) -> 7 | J87: =+I87 -> 7
B88: =$B$79 & ".09" -> 01.06.04.09 | C88: SUMINISTRO E INSTALACION DE REDUCCION PVC C-10 Ø 1 1/2" A Ø 3/4" | D88: UND | E88: 2 | I88: =+ROUND(PRODUCT(E88:H88),2) -> 2 | J88: =+I88 -> 2
B89: =$B$79 & ".10" -> 01.06.04.10 | C89: SUMINISTRO E INSTALACION DE NIPLE PVC C-10 L=2", Ø 1 1/2" | D89: UND | E89: 2 | I89: =+ROUND(PRODUCT(E89:H89),2) -> 2 | J89: =+I89 -> 2
B90: =$B$79 & ".11" -> 01.06.04.11 | C90: SUMINISTRO E INSTALACION DE ADAPTADOR UNIVERSAL HDPE A PVC Ø 1 1/2" | D90: UND | E90: 1 | I90: =+ROUND(PRODUCT(E90:H90),2) -> 1 | J90: =+I90 -> 1
B91: =$B$79 & ".12" -> 01.06.04.12 | C91: SUMINISTRO E INSTALACION DE TAPONES PVC Ø 3/4" | D91: UND | E91: 5 | I91: =+ROUND(PRODUCT(E91:H91),2) -> 5 | J91: =+I91 -> 5
B92: =B$22 & ".05" -> 01.06.05 | C92: PRUEBA HIDRAULICA
B93: =B92 &".01" -> 01.06.05.01 | C93: PRUEBA HIDRÁULICA Y DESINFECCIÓN DE LA TUBERÍA | D93: ML | E93: 1 | F93: =F22 -> 1097.16 | I93: =+ROUND(PRODUCT(E93:H93),2) -> 1097.16 | J93: =+I93 -> 1097.16
C107: ADAPTADOR UNIVERSAL HDPE A PVC Ø 1"
C108: TAPONES Ø 3/4"

Sheet 1.7 VALV-AIRE
B1: HOJA DE METRADOS DE AGUA POTABLE
B2: "CREACION DEL SERVICIO DE AGUA POTABLE RURAL Y CREACION DEL SERVICIO DE ALCANTARILLADO U OTRAS FORMAS DE DISPOSICION SANITARIA DE EXCRETAS EN EL SECTOR NUEVA ESPERANZA DE LA CC.NN. BAJO PITOCUNA DISTRITO DE RIO NEGRO, PROVINCIA DE SATIPO, DEPARTAMENTO DE JUNIN"
B3: VALVULA DE AIRE
L10: N° | M10: ACCESORIOS | N10: UNIDAD
L11: 1 | M11: Valvula de aire | N11: 1
L12: 2 | M12: Niple PVC L=1" | N12: 4
L13: 3 | M13: Union universal PVC | N13: 2
L14: 4 | M14: Valvula compuerta Bronce | N14: 1 | O14: Ø = 3/4"
L15: 5 | M15: Reduccion PVC SP | N15: 1
L16: 6 | M16: Tee PVC SP | N16: 1
B18: PARTIDA | C18: DESCRIPCION | D18: UNIDAD | E18: VECES | F18: LONGITUD | G18: ANCHO | H18: ALTURA | I18: SUB-TOTAL | J18: TOTAL | L18: =+B3&O14& " x" -> VALVULA DE AIRE Ø = 3/4" x
B19: =+"01.07" -> 01.07 | C19: =+B3&" ("&E19&" und.)" -> VALVULA DE AIRE (1 und.) | E19: =E20+E21 -> 1
C20: =+$L$18&L20 -> VALVULA DE AIRE Ø = 3/4" x Ø = 3/4" | E20: 1 | L20: Ø = 3/4"
B22: =B$19 & ".01" -> 01.07.01 | C22: TRABAJOS PRELIMINARES | E22: =+$E$19 -> 1 | L22: Descripcion | M22: Medida | N22: Unidad
B23: =B$22 & ".01" -> 01.07.01.01 | C23: LIMPIEZA Y DESBROCE DE TERRENO MANUAL | D23: m2 | I23: =SUM(I24) -> 2.72 | J23: =+I23*$E$22 -> 2.72 | L23: Caja de Valvulas
C24: Caja de valvula | E24: 1 | F24: =+M51 -> 1.65 | G24: =+M50 -> 1.65 | I24: =+ROUND(PRODUCT(E24:G24),2) -> 2.72 | L24: Ancho | M24: 0.6 | N24: m
L25: Largo | M25: 0.6 | N25: m
B26: =B$22 & ".02" -> 01.07.01.02 | C26: TRAZO Y REPLANTEO PRELIMINAR PARA ESTRUCTURAS | D26: m2 | I26: =SUM(I27) -> 2.72 | J26: =+I26*$E$22 -> 2.72 | L26: Altura | M26: 0.75 | N26: m
C27: Caja de valvula | E27: 1 | F27: =+F24 -> 1.65 | G27: =+G24 -> 1.65 | I27: =+ROUND(PRODUCT(E27:G27),2) -> 2.72 | L27: Uña | M27: 0.1 | N27: m
L28: Espesor de muro | M28: 0.1 | N28: m
B29: =B$22 & ".03" -> 01.07.01.03 | C29: TRAZO Y REPLANTEO DURANTE EL PROCESO PARA ESTRUCTURAS | D29: m2 | I29: =SUM(I30) -> 2.72 | J29: =+I29*$E$22 -> 2.72
C30: Caja de valvula | E30: 1 | F30: =+F27 -> 1.65 | G30: =+G27 -> 1.65 | I30: =+ROUND(PRODUCT(E30:G30),2) -> 2.72
B32: =B$19 & ".02" -> 01.07.02 | C32: MOVIMIENTO DE TIERRAS | E32: =+$E$19 -> 1 | L32: Cimentacion
B33: =B$32 & ".01" -> 01.07.02.01 | C33: EXCAVACION MANUAL EN TERRENO NORMAL | D33: m3 | I33: =SUM(I34:I42) -> 1.9 | J33: =+I33*$E$32 -> 1.9 | L33: Ancho | M33: =+M24+2*M28+2*M27 -> 1 | N33: m
C34: Caja de valvula | E34: 1 | F34: Volumen | H34: =+G39/6*((2*G35+G37)*G36+(2*G37+G35)*G38) -> 1.84275 | I34: =+ROUND(PRODUCT(E34:H34),2) -> 1.84 | L34: Largo | M34: =+M25+2*M28+2*M27 -> 1 | N34: m
F35: a | G35: =+M50 -> 1.65 | L35: Espesor de losa | M35: 0.1 | N35: m
F36: b | G36: =+M51 -> 1.65 | L36: Solado | M36: 0.05 | N36: m
C37: Se considera 0.10m de | F37: a´ | G37: =+M46 -> 1.2 | L37: Uñas de cimentacion
C38: excavacion y talud 1:0.25 | F38: b´ | G38: =+M47 -> 1.2 | L38: Espesor | M38: 0.1 | N38: m
F39: h | G39: =+M53 -> 0.9 | L39: Profundidad | M39: 0.2 | N39: m
L40: Ancho | M40: 0.2 | N40: m
C41: Uña de cimentación | E41: 1 | F41: =+M42+M38 -> 0.235 | G41: =+M40+M38 -> 0.3 | H41: =+M39 -> 0.2 | I41: =+ROUND(PRODUCT(E41:H41),2) -> 0.01
C42: Solado | E42: 1 | F42: =+M34 -> 1 | G42: =+M33 -> 1 | H42: =+M36 -> 0.05 | I42: =+ROUND(PRODUCT(E42:H42),2) -> 0.05 | L42: Largo | M42: 0.135 | N42: m
L43: Excavacion
B44: =B$32 & ".02" -> 01.07.02.02 | C44: RELLENO CON MATERIAL PROPIO SELECCIONADO | D44: m3 | I44: =SUM(I45:I47) -> 1.26 | J44: =+I44*$E$32 -> 1.26 | L44: Fondo
C45: Volumen de excavacion | E45: 1 | H45: =+H34 -> 1.84275 | I45: =+ROUND(PRODUCT(E45:H45),2) -> 1.84 | L45: Excavacion | M45: 0.1 | N45: m
C46: Volumen de muros | E46: -1 | F46: =+M25+M28*2 -> 0.8 | G46: =+M24+2*M28 -> 0.8 | H46: =+M26 -> 0.75 | I46: =+ROUND(PRODUCT(E46:H46),2) -> -0.48 | L46: Ancho (a´) | M46: =+M33+2*M45 -> 1.2 | N46: m
C47: Volumen de losa | E47: -1 | F47: =+M34 -> 1 | G47: =+M33 -> 1 | H47: =+M35 -> 0.1 | I47: =+ROUND(PRODUCT(E47:H47),2) -> -0.1 | L47: Largo (b´) | M47: =+M34+2*M45 -> 1.2 | N47: m
L48: Superior
B49: =B$32 & ".03" -> 01.07.02.03 | C49: ACARREO Y ELIMINACION DE MAT. EXCEDENTE Dmax=30 m | D49: m3 | I49: =SUM(I50:I51) -> 0.88 | J49: =+I49*$E$32 -> 0.88 | L49: Excavacion | M49: =+M52*M53 -> 0.225 | N49: m
C50: Excavacion - Esponjamiento 20% | E50: 1 | F50: 1.2 | G50: Volumen | H50: =+I33 -> 1.9 | I50: =+ROUND(PRODUCT(E50:H50),2) -> 2.28 | L50: Ancho (a) | M50: =+M46+2*M49 -> 1.65 | N50: m
C51: Relleno - Compactacion | E51: -1 | F51: =1/(0.9) -> 1.1111111 | G51: Volumen | H51: =+I44 -> 1.26 | I51: =+ROUND(PRODUCT(E51:H51),2) -> -1.4 | L51: Largo (b) | M51: =+M47+2*M49 -> 1.65 | N51: m
L52: Talud | M52: 0.25 | N52: m
B53: =B$19 & ".03" -> 01.07.03 | C53: OBRAS DE CONCRETO SIMPLE | E53: =+$E$19 -> 1 | L53: Altura (h) | M53: 0.9 | N53: m
B54: =B$53& ".01" -> 01.07.03.01 | C54: SOLADO f'c=100 Kg/cm2, e=5 cm | D54: m2 | I54: =SUM(I55) -> 1 | J54: =+I54*$E$53 -> 1 | L54: Superficie Libre (sl) | M54: 0.05 | N54: m
C55: Base de caja de valvula | E55: 1 | F55: =+M34 -> 1 | G55: =+M33 -> 1 | I55: =+ROUND(PRODUCT(E55:H55),2) -> 1
B57: =B$53& ".02" -> 01.07.03.02 | C57: CONCRETO f'c=140 kg/cm2 EN DADOS | D57: m3 | I57: =SUM(I58) -> 0.005 | J57: =+I57*$E$53 -> 0.005
C58: Dado para soporte | E58: 1 | F58: 0.15 | G58: 0.15 | H58: 0.2 | I58: =+ROUND(PRODUCT(E58:H58),3) -> 0.005
B60: =B$19 & ".04" -> 01.07.04 | C60: OBRAS DE CONCRETO ARMADO | E60: =+$E$19 -> 1
B61: =B$60 & ".01" -> 01.07.04.01 | C61: CONCRETO f'c=175 kg/cm2 EN MUROS | D61: m3 | I61: =SUM(I62:I64) -> 0.223 | J61: =+I61*$E$60 -> 0.223
C62: Muro longitudinales | E62: 2 | F62: =+M25+2*M28 -> 0.8 | G62: =+M28 -> 0.1 | H62: =+$M$26 -> 0.75 | I62: =+ROUND(PRODUCT(E62:H62),2) -> 0.12
C63: Muros transversales | E63: 2 | F63: =+M24 -> 0.6 | G63: =+G62 -> 0.1 | H63: =+$M$26 -> 0.75 | I63: =+ROUND(PRODUCT(E63:H63),3) -> 0.09
C64: Uñas de cimentaión | E64: 1 | F64: =2*(M40+M42) -> 0.67 | G64: =+M38 -> 0.1 | H64: =+M39 -> 0.2 | I64: =+ROUND(PRODUCT(E64:H64),3) -> 0.013
B66: =B$60 & ".02" -> 01.07.04.02 | C66: CONCRETO f'c=175 kg/cm2 EN LOSA | D66: m3 | I66: =I67 -> 0.1 | J66: =+I66*$E$53 -> 0.1
C67: Losa de fondo | E67: 1 | F67: =+M34 -> 1 | G67: =+M33 -> 1 | H67: =+M35 -> 0.1 | I67: =+ROUND(PRODUCT(E67:H67),3) -> 0.1
B69: =B$60 & ".03" -> 01.07.04.03 | C69: ENCOFRADO Y DESENCOFRADO EN MUROS | D69: m2 | I69: =SUM(I70:I73) -> 4.2 | J69: =+I69*$E$53 -> 4.2
C70: Muro longitudinales cara exterior | E70: 2 | F70: =+M25+2*M28 -> 0.8 | H70: =+$M$26 -> 0.75 | I70: =+ROUND(PRODUCT(E70:H70),2) -> 1.2
C71: Muro transversal cara exterior | E71: 2 | G71: =+M24+2*M28 -> 0.8 | H71: =+$M$26 -> 0.75 | I71: =+ROUND(PRODUCT(E71:H71),2) -> 1.2
C72: Muro longitudinales cara interior | E72: 2 | F72: =+M25 -> 0.6 | H72: =+$M$26 -> 0.75 | I72: =+ROUND(PRODUCT(E72:H72),2) -> 0.9
C73: Muro transversal cara interior | E73: 2 | G73: =+M24 -> 0.6 | H73: =+$M$26 -> 0.75 | I73: =+ROUND(PRODUCT(E73:H73),2) -> 0.9
B75: =B$60 & ".04" -> 01.07.04.04 | C75: ENCOFRADO Y DESENCOFRADO EN LOSAS | D75: m2 | I75: =SUM(I76:I78) -> 0.4 | J75: =+I75*$E$53 -> 0.4
C76: Losa de fondo, longitudinal cara exterior | E76: 2 | F76: =+M34 -> 1 | H76: =+$M$35 -> 0.1 | I76: =+ROUND(PRODUCT(E76:H76),2) -> 0.2
C77: Losa de fondo, transversal cara exterior | E77: 2 | F77: =+M33 -> 1 | H77: =+$M$35 -> 0.1 | I77: =+ROUND(PRODUCT(E77:H77),2) -> 0.2
B79: =B$60 & ".05" -> 01.07.04.05 | C79: ACERO CORRUGADO fý=4200 kg/cm2 G-60 | D79: kg | E79: Ø | F79: NºVarillas | G79: Long. | H79: kg/m | I79: =SUM(I80:I85) -> 103.4363 | J79: =+I79*E19 -> 103.4363
C80: Losa de fondo
C81: Armadura inferior_Acero Transversal | E81: 0.375 | F81: 4 | G81: 1.07 | H81: =+VLOOKUP(E81,$E$116:$J$124,6,FALSE) -> 0.56 | I81: =+ROUND(PRODUCT(F81:H81),2)*5.01 -> 12.024
C82: Armadura superior_Acero Longitudinal | E82: 0.375 | F82: 4 | G82: 1.07 | H82: =+VLOOKUP(E82,$E$116:$J$124,6,FALSE) -> 0.56 | I82: =+ROUND(PRODUCT(F82:H82),2)*5.01 -> 12.024
C83: Muro | I83: =+ROUND(PRODUCT(F83:H83),2)*5.01 -> 0
C84: Armadura verticales Ø3/8"@0.20m | E84: 0.375 | F84: 16 | G84: 0.9564 | H84: =+VLOOKUP(E84,$E$116:$J$124,6,FALSE) -> 0.56 | I84: =+ROUND(PRODUCT(F84:H84),2)*5.01 -> 42.9357
C85: Armadura horizontal ext. Ø3/8@0.20m | E85: 0.375 | F85: 4 | G85: 3.24 | H85: =+VLOOKUP(E85,$E$116:$J$124,6,FALSE) -> 0.56 | I85: =+ROUND(PRODUCT(F85:H85),2)*5.01+0.08 -> 36.4526
B87: =B$19 & ".05" -> 01.07.05 | C87: REVOQUES, ENLUCIDOS Y MOLDURAS | E87: =+$E$19 -> 1
B88: =B$87 & ".01" -> 01.07.05.01 | C88: TARRAJEO INTERIOR C:A 1:4, e=1.5 cm | D88: m2 | I88: =SUM(I89:I91) -> 2.16 | J88: =+I88*$E$87 -> 2.16
C89: Muro longitudinales cara interior | E89: 2 | F89: =+M25 -> 0.6 | H89: =+$M$26 -> 0.75 | I89: =+ROUND(PRODUCT(E89:H89),2) -> 0.9
C90: Muro transversal cara interior | E90: 2 | G90: =+M24 -> 0.6 | H90: =+$M$26 -> 0.75 | I90: =+ROUND(PRODUCT(E90:H90),2) -> 0.9
C91: Losa de fondo cara interior | E91: 1 | F91: =+M25 -> 0.6 | G91: =+M24 -> 0.6 | I91: =+ROUND(PRODUCT(E91:G91),2) -> 0.36
B93: =B$19 & ".06" -> 01.07.06 | C93: INSTALACIONES HIDRAULICAS | E93: =+$E$19 -> 1
B94: =B$93 & ".01" -> 01.07.06.01 | C94: SUMINISTRO Y COLOC. DE ACCESORIOS EN VALVULA DE AIRE Ø=1 1/2" X Ø=1/2" - LINEA DE CONDUCCION HDPE | D94: und | E94: 9 | I94: =E93 -> 1 | J94: =+I94 -> 1
C95: Valvula de aire Ø = 1/2" automatica | D95: und | E95: =+$N$11 -> 1
C96: Niple PVC L=1" Ø = 1/2" | D96: und | E96: =+$N$12 -> 4
C97: Union universal PVC Ø = 1/2" | D97: und | E97: =+$N$13 -> 2
C98: Valvula compuerta Bronce Ø = 1/2" | D98: und | E98: =+$N$14 -> 1
C99: Reduccion PVC SP Ø = 2"x Ø = 1/2" | D99: und | E99: =+$N$15 -> 1
C100: Tee PVC SP Ø = 2" | D100: und | E100: =+$N$16 -> 1
C101: Unión enlace adaptador HDPE a PVC, PN-8 ø=54.2 MM | D101: und | E101: 2
C102: Niple F°G° L=0.2m Ø = 2", con rosca a un lado | D102: und | E102: 1
C103: Codo de 90° F°G°Ø = 2" con malla soldada | D103: und | E103: 1
C104: Cinta teflon | D104: und | E104: 5
C105: Pegamento para PVC 1/4 gln | D105: und | E105: 1
B107: =B$19 & ".07" -> 01.07.07 | C107: CARPINTERIA METALICA | E107: =+$E$19 -> 1
B108: =B$107 & ".01" -> 01.07.07.01 | C108: SUMINISTRO E INST. DE TAPA METALICA DE 0.60 x 0.60 m e=1/8" INC. ACCESORIOS + PINTURA | D108: und | E108: 1 | I108: =+ROUND(PRODUCT(E108:H108),3) -> 1 | J108: =+I108*$E$107 -> 1
E113: CARACTERISTICAS DE ACERO CORRUGADO
E114: Diametro | G114: Area (cm2) | H114: Diametro (cm) | I114: Perimetro (cm) | J114: Peso (kg/m)
E115: Pulg. | F115: mm
E116: 0.25 | F116: 6 | G116: =+PI()*H116*H116/4 -> 0.31669217 | H116: =2.54*1/4 -> 0.635 | I116: =+H116*PI() -> 1.9949113 | J116: 0.222
F117: 8 | G117: =+PI()*H117*H117/4 -> 0.50265482 | H117: 0.8 | J117: 0.4
E118: 0.375 | F118: - | G118: =+PI()*H118*H118/4 -> 0.71255739 | H118: =2.54*3/8 -> 0.9525 | I118: =+H118*PI() -> 2.992367 | J118: 0.56
F119: 12 | G119: =+PI()*H119*H119/4 -> 1.1309734 | H119: 1.2 | J119: 0.89
E120: 0.5 | F120: - | G120: =+PI()*H120*H120/4 -> 1.2667687 | H120: =1/2*2.54 -> 1.27 | I120: =+H120*PI() -> 3.9898227 | J120: 0.994
E121: 0.625 | F121: - | G121: =+PI()*H121*H121/4 -> 1.9793261 | H121: =5/8*2.54 -> 1.5875 | I121: =+H121*PI() -> 4.9872783 | J121: 1.552
E122: 0.75 | F122: - | G122: =+PI()*H122*H122/4 -> 2.8502296 | H122: =3/4*2.54 -> 1.905 | I122: =+H122*PI() -> 5.984734 | J122: 2.235
...

Sheet 1.8. VALV-PURGA T-1
B1: METRADOS DEL SISTEMA DE AGUA POTABLE
B2: "CREACION DEL SERVICIO DE AGUA POTABLE RURAL Y CREACION DEL SERVICIO DE ALCANTARILLADO U OTRAS FORMAS DE DISPOSICION SANITARIA DE EXCRETAS EN EL SECTOR NUEVA ESPERANZA DE LA CC.NN. BAJO PITOCUNA DISTRITO DE RIO NEGRO, PROVINCIA DE SATIPO, DEPARTAMENTO DE JUNIN"
B3: VALVULA DE PURGA TIPO 1
L4: N° | M4: ACCESORIOS | N4: UNIDAD
L5: 1 | M5: Valvula compuerta Bronce | N5: 1
L6: 2 | M6: Niple PVC L=2" | N6: 2
L7: 3 | M7: Union universal PVC | N7: 2
L8: 4 | M8: Adaptador UPR PVC | N8: 2
L9: 5 | M9: Niple PVC L=8" | N9: 3
L10: 6 | M10: Codo PVC SP x 45° | N10: 4
L11: 7 | M11: Niple PVC L=22" | N11: 1
L12: 8 | M12: Niple PVC L=7" | N12: 1
L13: 9 | M13: Tee PVC SP | N13: 1
L14: 10 | M14: Tapón macho F°G° | N14: 1
M15: Tuberia PVC C-10 | N15: 3
B18: PARTIDA | C18: DESCRIPCION | D18: UNIDAD | E18: VECES | F18: LONGITUD | G18: ANCHO | H18: ALTURA | I18: SUB-TOTAL | J18: TOTAL | L18: VALVULA DE PURGA TIPO 1 (8 und.)
B19: =+"01.08" -> 01.08 | C19: VALVULA DE PUGA (5 und) | E19: =+SUM(E20:E20) -> 2
C20: =+$B$3&L20 -> VALVULA DE PURGA TIPO 1 Ø = 1 1/2" | E20: 2 | L20: Ø = 1 1/2"
B21: =B$19 & ".01" -> 01.08.01 | C21: VALVULAS DE PURGA TIPO 1 (2 und)
B22: =B$19 & ".01.01" -> 01.08.01.01 | C22: TRABAJOS PRELIMINARES | E22: =+$E$19 -> 2 | L22: Descripcion | M22: Medida | N22: Unidad
B23: =B$22 & ".01" -> 01.08.01.01.01 | C23: LIMPIEZA Y DESBROCE DE TERRENO MANUAL | D23: m2 | I23: =SUM(I24:I25) -> 5.56 | J23: =+I23*$E$22 -> 11.12 | L23: Caja de Valvulas
C24: Caja de valvula | E24: 1 | F24: =+M45 -> 1.6 | G24: =+M44 -> 1.6 | I24: =+ROUND(PRODUCT(E24:G24),2) -> 2.56 | L24: Ancho | M24: 0.6 | N24: m
C25: Tuberia de limpieza | E25: 1 | F25: 3 | G25: 1 | I25: =+ROUND(PRODUCT(E25:H25),2) -> 3 | L25: Largo | M25: 0.6 | N25: m
L26: Altura | M26: 0.7 | N26: m
B27: =B$22 & ".02" -> 01.08.01.01.02 | C27: TRAZO Y REPLANTEO PRELIMINAR PARA ESTRUCTURAS | D27: m2 | I27: =SUM(I28:I29) -> 5.56 | J27: =+I27*$E$22 -> 11.12 | L27: Uña | M27: 0.1 | N27: m
C28: Caja de valvula | E28: 1 | F28: =+F24 -> 1.6 | G28: =+G24 -> 1.6 | I28: =+ROUND(PRODUCT(E28:G28),2) -> 2.56 | L28: Espesor de muro | M28: 0.1 | N28: m
C29: Tuberia de limpieza | E29: 1 | F29: =+F25 -> 3 | G29: =+G25 -> 1 | I29: =+ROUND(PRODUCT(E29:H29),2) -> 3 | L29: Cimentacion B
B31: =B$22 & ".03" -> 01.08.01.01.03 | C31: TRAZO Y REPLANTEO DURANTE EL PROCESO PARA ESTRUCTURAS | D31: m2 | I31: =SUM(I32:I33) -> 5.56 | J31: =+I31*$E$22 -> 11.12
C32: Caja de valvula | E32: 1 | F32: =+F28 -> 1.6 | G32: =+G28 -> 1.6 | I32: =+ROUND(PRODUCT(E32:G32),2) -> 2.56
C33: Tuberia de limpieza | E33: 1 | F33: =+F29 -> 3 | G33: =+G29 -> 1 | I33: =+ROUND(PRODUCT(E33:H33),2) -> 3
L34: Ancho | M34: =+M24+2*M28+2*M27 -> 1 | N34: m
B35: =B$19 & ".01.02" -> 01.08.01.02 | C35: MOVIMIENTO DE TIERRAS | E35: =+$E$19 -> 2 | L35: Largo | M35: =+M25+2*M28+2*M27 -> 1 | N35: m
B36: =B$35 & ".01" -> 01.08.01.02.01 | C36: EXCAVACION MANUAL EN TERRENO NORMAL | D36: m3 | I36: =SUM(I37:I44) -> 3.38 | J36: =+I36*$E$35 -> 6.76 | L36: Espesor de losa | M36: 0.1 | N36: m
C37: Caja de valvula | E37: 1 | F37: Volumen | H37: =+G42/6*((2*G38+G40)*G39+(2*G40+G38)*G41) -> 1.5786667 | I37: =+ROUND(PRODUCT(E37:H37),2) -> 1.58 | L37: Excavacion
F38: a | G38: =+M44 -> 1.6 | L38: Fondo
F39: b | G39: =+M45 -> 1.6 | L39: Excavacion | M39: 0.1 | N39: m
C40: Se considera 0.10m de | F40: a´ | G40: =+M40 -> 1.2 | L40: Ancho (a´) | M40: =+M34+2*M39 -> 1.2 | N40: m
C41: excavacion y talud 1:0.25 | F41: b´ | G41: =+M41 -> 1.2 | L41: Largo (b´) | M41: =+M35+2*M39 -> 1.2 | N41: m
F42: h | G42: =+M47 -> 0.8 | L42: Superior
L43: Excavacion | M43: =+M46*M47 -> 0.2 | N43: m
C44: Zanja para tuberia de limpieza | E44: 1 | F44: =+F25 -> 3 | G44: =+G29 -> 1 | H44: 0.6 | I44: =+ROUND(PRODUCT(E44:H44),2) -> 1.8 | L44: Ancho (a) | M44: =+M40+2*M43 -> 1.6 | N44: m
L45: Largo (b) | M45: =+M41+2*M43 -> 1.6 | N45: m
B46: =B$35 & ".02" -> 01.08.01.02.02 | C46: RELLENO CON MATERIAL PROPIO SELECCIONADO | D46: m3 | I46: =SUM(I47:I49) -> 1.03 | J46: =+I46*$E$35 -> 2.06 | L46: Talud | M46: 0.25 | N46: m
C47: Volumen de excavacion | E47: 1 | H47: =+H37 -> 1.5786667 | I47: =+ROUND(PRODUCT(E47:H47),2) -> 1.58 | L47: Altura (h) | M47: 0.8 | N47: m
C48: Volumen de muros | E48: -1 | F48: =+M25+2*M28 -> 0.8 | G48: =+M24+2*M28 -> 0.8 | H48: =+M26 -> 0.7 | I48: =+ROUND(PRODUCT(E48:H48),2) -> -0.45 | L48: Superficie Libre (sl) | M48: 0.05 | N48: m
C49: Volumen de losa | E49: -1 | F49: =+M35 -> 1 | G49: =+M34 -> 1 | H49: =+M36 -> 0.1 | I49: =+ROUND(PRODUCT(E49:H49),2) -> -0.1 | L49: Filtro de piedra | M49: 0.2 | N49: m
B51: =B$35 & ".03" -> 01.08.01.02.03 | C51: ACARREO Y ELIMINACION DE MAT. EXCEDENTE Dmax=30 m | D51: m3 | I51: =SUM(I52:I53) -> 2.92 | J51: =+I51*$E$35 -> 5.84
C52: Excavacion - Esponjamiento 20% | E52: 1 | F52: 1.2 | G52: Volumen | H52: =+I36 -> 3.38 | I52: =+ROUND(PRODUCT(E52:H52),2) -> 4.06
C53: Relleno | E53: -1 | F53: =1/(0.9) -> 1.1111111 | G53: Volumen | H53: =+I46 -> 1.03 | I53: =+ROUND(PRODUCT(E53:H53),2) -> -1.14
B55: =B$19 & ".01.03" -> 01.08.01.03 | C55: OBRAS DE CONCRETO SIMPLE | E55: =+$E$19 -> 2
B56: =B$55 & ".01" -> 01.08.01.03.01 | C56: CONCRETO f'c=140 kg/cm2 EN DADOS | D56: m3 | I56: =SUM(I57) -> 0.012 | J56: =+I56*$E$55 -> 0.024
C57: Dado Movil | E57: 1 | F57: 0.3 | G57: 0.2 | H57: 0.2 | I57: =+ROUND(PRODUCT(E57:H57),3) -> 0.012
B59: =B$19 & ".01.04" -> 01.08.01.04 | C59: OBRAS DE CONCRETO ARMADO
B60: =B$59 & ".01" -> 01.08.01.04.01 | C60: CONCRETO f'c=175 kg/cm2 EN MUROS | D60: m3 | I60: =SUM(I61:I62) -> 0.196 | J60: =+I60*E55 -> 0.392
C61: Muro longitudinales | E61: 2 | F61: =+M24+2*M28 -> 0.8 | G61: =+M28 -> 0.1 | H61: =+$M$26 -> 0.7 | I61: =+ROUND(PRODUCT(E61:H61),3) -> 0.112
C62: Muros transversales | E62: 2 | F62: =+M24 -> 0.6 | G62: =+M28 -> 0.1 | H62: =+$M$26 -> 0.7 | I62: =+ROUND(PRODUCT(E62:H62),3) -> 0.084
B64: =B$59 & ".02" -> 01.08.01.04.02 | C64: CONCRETO f'c=175 kg/cm2 EN LOSA | D64: m3 | I64: =SUM(I65:I66) -> 0.064 | J64: =+I64*E55 -> 0.128
C65: Losa de fondo | E65: 1 | F65: =+M35 -> 1 | G65: =+M34 -> 1 | H65: =+$M$36 -> 0.1 | I65: =+ROUND(PRODUCT(E65:H65),3) -> 0.1
C66: Descuento de Grava | E66: -1 | F66: =+M25 -> 0.6 | G66: =+M24 -> 0.6 | H66: =+$M$36 -> 0.1 | I66: =+ROUND(PRODUCT(E66:H66),3) -> -0.036
B68: =B$59 & ".03" -> 01.08.01.04.03 | C68: ENCOFRADO Y DESENCOFRADO EN DADOS | D68: m2 | I68: =SUM(I69:I70) -> 0.2 | J68: =+I68*$E$55 -> 0.4
C69: Dado Movil (laterles) | E69: 2 | F69: 0.2 | H69: 0.2 | I69: =+ROUND(PRODUCT(E69:H69),3) -> 0.08
C70: Dado Movil (posterior y frontal) | E70: 2 | F70: 0.3 | G70: 0.2 | I70: =+ROUND(PRODUCT(E70:H70),3) -> 0.12
B72: =B$59 & ".04" -> 01.08.01.04.04 | C72: ENCOFRADO Y DESENCOFRADO EN MUROS | D72: m2 | I72: =SUM(I73:I76) -> 3.92 | J72: =+I72*$E$55 -> 7.84
C73: Muro longitudinales cara exterior | E73: 2 | F73: =+M25+2*M28 -> 0.8 | H73: =+$M$26 -> 0.7 | I73: =+ROUND(PRODUCT(E73:H73),3) -> 1.12
C74: Muro transversal cara exterior | E74: 2 | G74: =+M24+2*M28 -> 0.8 | H74: =+$M$26 -> 0.7 | I74: =+ROUND(PRODUCT(E74:H74),3) -> 1.12
C75: Muro longitudinales cara interior | E75: 2 | F75: =+$M$25 -> 0.6 | H75: =+$M$26 -> 0.7 | I75: =+ROUND(PRODUCT(E75:H75),3) -> 0.84
C76: Muro transversal cara interior | E76: 2 | G76: =+$M$24 -> 0.6 | H76: =+$M$26 -> 0.7 | I76: =+ROUND(PRODUCT(E76:H76),3) -> 0.84
B78: =B$59 & ".05" -> 01.08.01.04.05 | C78: ENCOFRADO Y DESENCOFRADO EN LOSAS | D78: m2 | I78: =SUM(I79:I82) -> 0.64 | J78: =+I78*$E$55 -> 1.28
C79: Losa de fondo, longitudinal cara exterior | E79: 2 | F79: =+$M$35 -> 1 | H79: =+$M$36 -> 0.1 | I79: =+ROUND(PRODUCT(E79:H79),3) -> 0.2
C80: Losa de fondo, transversal cara exterior | E80: 2 | G80: =+$M$34 -> 1 | H80: =+$M$36 -> 0.1 | I80: =+ROUND(PRODUCT(E80:H80),3) -> 0.2
C81: Losa de fondo, longitudinal cara interior | E81: 2 | F81: =+$M$25 -> 0.6 | H81: =+$M$36 -> 0.1 | I81: =+ROUND(PRODUCT(E81:H81),3) -> 0.12
C82: Losa de fondo, transversal cara interior | E82: 2 | G82: =+$M$24 -> 0.6 | H82: =+$M$36 -> 0.1 | I82: =+ROUND(PRODUCT(E82:H82),3) -> 0.12
B84: =B$59 & ".06" -> 01.08.01.04.06 | C84: ACERO CORRUGADO f'y=4200 kg/cm2 G-60 | D84: kg | I84: =SUM(I85:I85) -> 25.7152 | J84: =+I84*$E$55 -> 51.4304
C85: Ver planilla de metrado de acero | E85: 1 | I85: ='1.8.1 M.ACERO T-01'!N228 -> 25.7152
B87: =B$19 & ".01.05" -> 01.08.01.05 | C87: REVOQUES Y ENLUCIDOS Y MOLDURAS | E87: =+$E$19 -> 2
B88: =B$87 & ".01" -> 01.08.01.05.01 | C88: TARRAJEO INTERIOR MEZCLA C:A 1:4, e=1.5 cm | D88: m2 | I88: =SUM(I89:I92) -> 1.92 | J88: =+I88*$E$87 -> 3.84
C89: Muro longitudinales cara interior | E89: 2 | F89: =+$M$25 -> 0.6 | H89: =+$M$26 -> 0.7 | I89: =+ROUND(PRODUCT(E89:H89),2) -> 0.84
C90: Muro transversal cara interior | E90: 2 | G90: =+$M$24 -> 0.6 | H90: =+$M$26 -> 0.7 | I90: =+ROUND(PRODUCT(E90:H90),2) -> 0.84
C91: Losa de fondo, longitudinal cara interior | E91: 2 | F91: =+$M$25 -> 0.6 | H91: =+$M$36 -> 0.1 | I91: =+ROUND(PRODUCT(E91:H91),2) -> 0.12
C92: Losa de fondo, transversal cara interior | E92: 2 | G92: =+$M$24 -> 0.6 | H92: =+$M$36 -> 0.1 | I92: =+ROUND(PRODUCT(E92:H92),2) -> 0.12
B94: =B$19 & ".01.06" -> 01.08.01.06 | C94: ASENTADO DE PIEDRA | E94: =+$E$19 -> 2
B95: =B$94 & ".01" -> 01.08.01.06.01 | C95: EMPEDRADO, ASENTADO Y EMBOQUILLADO C/CONCRETO f´c=140 kg/cm2, e=15 cm | D95: m2 | I95: =SUM(I96) -> 0.5 | J95: =+I95*$E$94 -> 1
C96: Proteccion de dado de anclaje | E96: 1 | F96: 1 | G96: 0.5 | I96: =+ROUND(PRODUCT(E96:H96),2) -> 0.5
B98: =B$19 & ".01.07" -> 01.08.01.07 | C98: FILTROS | E98: =+$E$19 -> 2
B99: =B$98 & ".01" -> 01.08.01.07.01 | C99: PIEDRA CHANCADA DE 1/2" | D99: m3 | I99: =SUM(I100) -> 0.072 | J99: =+I99*$E$98 -> 0.144
E100: 1 | F100: =+M25 -> 0.6 | G100: =+M24 -> 0.6 | H100: =+M49 -> 0.2 | I100: =+ROUND(PRODUCT(E100:H100),3) -> 0.072
B102: =B$19 & ".01.08" -> 01.08.01.08 | C102: INSTALACIONES SANITARIAS
B104: =B$102 & ".01" -> 01.08.01.08.01 | C104: ="SUMINISTRO Y COLOC. DE ACCESORIOS EN VALVULA DE PURGA "&L20 -> SUMINISTRO Y COLOC. DE ACCESORIOS EN VALVULA DE PURGA Ø = 1 1/2" | D104: und | E104: =E19 -> 2 | I104: =+ROUND(PRODUCT(E104:H104),3) -> 2 | J104: =+I104 -> 2
C105: =+M5&L20 -> Valvula compuerta Bronce Ø = 1 1/2" | D105: und | E105: =+N5 -> 1
C106: =+M6&L20 -> Niple PVC L=2" Ø = 1 1/2" | D106: und | E106: =+N6 -> 2
C107: =+M7&L20 -> Union universal PVC Ø = 1 1/2" | D107: und | E107: =+N7 -> 2
C108: =+M8&L20 -> Adaptador UPR PVC Ø = 1 1/2" | D108: und | E108: =+N8 -> 2
C109: =+M9&L20 -> Niple PVC L=8" Ø = 1 1/2" | D109: und | E109: =+N9 -> 3
C110: =+M10&L20 -> Codo PVC SP x 45° Ø = 1 1/2" | D110: und | E110: =+N10 -> 4
C111: =+M11&L20 -> Niple PVC L=22" Ø = 1 1/2" | D111: und | E111: =+N11 -> 1
C112: =+M12&L20 -> Niple PVC L=7" Ø = 1 1/2" | D112: und | E112: =+N12 -> 1
C113: =+M13&L20 -> Tee PVC SP Ø = 1 1/2" | D113: und | E113: =+N13 -> 1
C114: =+M14&L20 -> Tapón macho F°G° Ø = 1 1/2" | D114: und | E114: =+N14 -> 1
C115: =+M15&L20 -> Tuberia PVC C-10 Ø = 1 1/2" | D115: m | E115: =+N15 -> 3
C116: Union enlace adaptador HDPE a PVC Ø = 2" | D116: und | E116: 2
...

Sheet 1.8.1 M.ACERO T-01
A2: METRADOS Del SISTEMA DE AGUA POTABLE
A3: "CREACION DEL SERVICIO DE AGUA POTABLE RURAL Y CREACION DEL SERVICIO DE ALCANTARILLADO U OTRAS FORMAS DE DISPOSICION SANITARIA DE EXCRETAS EN EL SECTOR NUEVA ESPERANZA DE LA CC.NN. BAJO PITOCUNA DISTRITO DE RIO NEGRO, PROVINCIA DE SATIPO, DEPARTAMENTO DE JUNIN"
A4: METRADO DE CAMARA ROMPE PRESION T 06
A6: =+'[26]Captación Dique'!B140 -> 01.03.04.03 | D6: =+'[26]Captación Dique'!C140 -> ACERO f'y=4200 kg/cm2
A8: DESCRIPCION | D8: ELEMENTO | J8: Ø (Pulg.) | K8: CANTIDAD | L8: N° DE ELEMENTOS | M8: LONG. DEL ELEMENTO (m) | N8: LONGITUD (m)
N9: 1/4" | O9: 3/8" | P9: 1/2" | Q9: 5/8" | R9: 3/4" | S9: 1"
A10: CAMARA HUMEDA | B10: Muro y Losa | C10: Acero Vertical
F12: 0.95 | J12: 3/8" | K12: 4 | L12: 4 | M12: =+F12+G14 -> 1.15 | N12: =IF(+$J12=N$9,+$K12*$L12*$M12,0) -> 0 | O12: =IF(+$J12=O$9,+$K12*$L12*$M12,0) -> 18.4 | P12: =IF(+$J12=P$9,+$K12*$L12*$M12,0) -> 0 | Q12: =IF(+$J12=Q$9,+$K12*$L12*$M12,0) -> 0 | R12: =IF(+$J12=R$9,+$K12*$L12*$M12,0) -> 0 | S12: =IF(+$J12=S$9,+$K12*$L12*$M12,0) -> 0
G14: 0.2
C15: Acero Horizontal | F15: 0.2
E16: 0.2 | F16: 0.7
F17: 0.7 | H17: 0.7 | J17: 3/8" | K17: 1 | L17: 4 | M17: =+F19+H17+E16+F15+F16+F17 -> 3.2 | N17: =IF(+$J17=N$9,+$K17*$L17*$M17,0) -> 0 | O17: =IF(+$J17=O$9,+$K17*$L17*$M17,0) -> 12.8 | P17: =IF(+$J17=P$9,+$K17*$L17*$M17,0) -> 0 | Q17: =IF(+$J17=Q$9,+$K17*$L17*$M17,0) -> 0 | R17: =IF(+$J17=R$9,+$K17*$L17*$M17,0) -> 0 | S17: =IF(+$J17=S$9,+$K17*$L17*$M17,0) -> 0
F19: 0.7
C20: Losa - Acero Longitudinal y Transversal
F22: 0.92 | J22: 3/8" | K22: 4 | L22: 4 | M22: =+F22 -> 0.92 | N22: =IF(+$J22=N$9,+$K22*$L22*$M22,0) -> 0 | O22: =IF(+$J22=O$9,+$K22*$L22*$M22,0) -> 14.72 | P22: =IF(+$J22=P$9,+$K22*$L22*$M22,0) -> 0 | Q22: =IF(+$J22=Q$9,+$K22*$L22*$M22,0) -> 0 | R22: =IF(+$J22=R$9,+$K22*$L22*$M22,0) -> 0 | S22: =IF(+$J22=S$9,+$K22*$L22*$M22,0) -> 0
C25: Losa - Acero Transversal
F27: 4.44 | J27: 3/8" | K27: 0 | L27: 3 | M27: =+F27+H26+E26 -> 4.44 | N27: =IF(+$J27=N$9,+$K27*$L27*$M27,0) -> 0 | O27: =IF(+$J27=O$9,+$K27*$L27*$M27,0) -> 0 | P27: =IF(+$J27=P$9,+$K27*$L27*$M27,0) -> 0 | Q27: =IF(+$J27=Q$9,+$K27*$L27*$M27,0) -> 0 | R27: =IF(+$J27=R$9,+$K27*$L27*$M27,0) -> 0 | S27: =IF(+$J27=S$9,+$K27*$L27*$M27,0) -> 0
C30: Zapata - Acero Longitudinal
F32: 2.98 | J32: 3/8" | K32: 0 | L32: 4 | M32: =+F32 -> 2.98 | N32: =IF(+$J32=N$9,+$K32*$L32*$M32,0) -> 0 | O32: =IF(+$J32=O$9,+$K32*$L32*$M32,0) -> 0 | P32: =IF(+$J32=P$9,+$K32*$L32*$M32,0) -> 0 | Q32: =IF(+$J32=Q$9,+$K32*$L32*$M32,0) -> 0 | R32: =IF(+$J32=R$9,+$K32*$L32*$M32,0) -> 0 | S32: =IF(+$J32=S$9,+$K32*$L32*$M32,0) -> 0
C35: Zapata - Acero Transversal
F37: 4.44 | J37: 3/8" | K37: 0 | L37: 3 | M37: =+F37 -> 4.44 | N37: =IF(+$J37=N$9,+$K37*$L37*$M37,0) -> 0 | O37: =IF(+$J37=O$9,+$K37*$L37*$M37,0) -> 0 | P37: =IF(+$J37=P$9,+$K37*$L37*$M37,0) -> 0 | Q37: =IF(+$J37=Q$9,+$K37*$L37*$M37,0) -> 0 | R37: =IF(+$J37=R$9,+$K37*$L37*$M37,0) -> 0 | S37: =IF(+$J37=S$9,+$K37*$L37*$M37,0) -> 0
B40: Muro segundario | C40: Acero Vertical (interior y exterior)
F42: 1.23 | J42: 1/2" | K42: 0 | L42: 4 | M42: =+F42+G44 -> 1.33 | N42: =IF(+$J42=N$9,+$K42*$L42*$M42,0) -> 0 | O42: =IF(+$J42=O$9,+$K42*$L42*$M42,0) -> 0 | P42: =IF(+$J42=P$9,+$K42*$L42*$M42,0) -> 0 | Q42: =IF(+$J42=Q$9,+$K42*$L42*$M42,0) -> 0 | R42: =IF(+$J42=R$9,+$K42*$L42*$M42,0) -> 0 | S42: =IF(+$J42=S$9,+$K42*$L42*$M42,0) -> 0
G44: 0.1
C45: Acero Horizontal
J47: 3/8" | K47: 0 | L47: 7 | M47: =+F48 -> 0.839 | N47: =IF(+$J47=N$9,+$K47*$L47*$M47,0) -> 0 | O47: =IF(+$J47=O$9,+$K47*$L47*$M47,0) -> 0 | P47: =IF(+$J47=P$9,+$K47*$L47*$M47,0) -> 0 | Q47: =IF(+$J47=Q$9,+$K47*$L47*$M47,0) -> 0 | R47: =IF(+$J47=R$9,+$K47*$L47*$M47,0) -> 0 | S47: =IF(+$J47=S$9,+$K47*$L47*$M47,0) -> 0
F48: 0.839
C50: Zapata - Acero Longitudinal
J52: 1/2" | K52: 0 | L52: 6 | M52: =+F53 -> 0.839 | N52: =IF(+$J52=N$9,+$K52*$L52*$M52,0) -> 0 | O52: =IF(+$J52=O$9,+$K52*$L52*$M52,0) -> 0 | P52: =IF(+$J52=P$9,+$K52*$L52*$M52,0) -> 0 | Q52: =IF(+$J52=Q$9,+$K52*$L52*$M52,0) -> 0 | R52: =IF(+$J52=R$9,+$K52*$L52*$M52,0) -> 0 | S52: =IF(+$J52=S$9,+$K52*$L52*$M52,0) -> 0
F53: =+F48 -> 0.839
C55: Zapata - Acero Transversal
F57: 0.91 | J57: 1/2" | K57: 0 | L57: =+L42 -> 4 | M57: =+F57 -> 0.91 | N57: =IF(+$J57=N$9,+$K57*$L57*$M57,0) -> 0 | O57: =IF(+$J57=O$9,+$K57*$L57*$M57,0) -> 0 | P57: =IF(+$J57=P$9,+$K57*$L57*$M57,0) -> 0 | Q57: =IF(+$J57=Q$9,+$K57*$L57*$M57,0) -> 0 | R57: =IF(+$J57=R$9,+$K57*$L57*$M57,0) -> 0 | S57: =IF(+$J57=S$9,+$K57*$L57*$M57,0) -> 0
G60: 0.137
F62: 1.101 | J62: 1/2" | K62: 0 | L62: 7 | M62: =+F62+F64+G60 -> 1.488 | N62: =IF(+$J62=N$9,+$K62*$L62*$M62,0) -> 0 | O62: =IF(+$J62=O$9,+$K62*$L62*$M62,0) -> 0 | P62: =IF(+$J62=P$9,+$K62*$L62*$M62,0) -> 0 | Q62: =IF(+$J62=Q$9,+$K62*$L62*$M62,0) -> 0 | R62: =IF(+$J62=R$9,+$K62*$L62*$M62,0) -> 0 | S62: =IF(+$J62=S$9,+$K62*$L62*$M62,0) -> 0
F64: 0.25
C66: Acero Horizontal
F67: 1.26 | J67: 1/2" | K67: 0 | L67: 11 | M67: =+F67 -> 1.26 | N67: =IF(+$J67=N$9,+$K67*$L67*$M67,0) -> 0 | O67: =IF(+$J67=O$9,+$K67*$L67*$M67,0) -> 0 | P67: =IF(+$J67=P$9,+$K67*$L67*$M67,0) -> 0 | Q67: =IF(+$J67=Q$9,+$K67*$L67*$M67,0) -> 0 | R67: =IF(+$J67=R$9,+$K67*$L67*$M67,0) -> 0 | S67: =IF(+$J67=S$9,+$K67*$L67*$M67,0) -> 0
C70: Acero Vertical (Frontal) | G70: 0.2
F72: =+F67 -> 1.26 | J72: 1/2" | K72: 0 | L72: 7 | M72: =+F72+G70+G74 -> 1.96 | N72: =IF(+$J72=N$9,+$K72*$L72*$M72,0) -> 0 | O72: =IF(+$J72=O$9,+$K72*$L72*$M72,0) -> 0 | P72: =IF(+$J72=P$9,+$K72*$L72*$M72,0) -> 0 | Q72: =IF(+$J72=Q$9,+$K72*$L72*$M72,0) -> 0 | R72: =IF(+$J72=R$9,+$K72*$L72*$M72,0) -> 0 | S72: =IF(+$J72=S$9,+$K72*$L72*$M72,0) -> 0
G74: 0.5
C75: Losa sobre compuerta de cierre - Acero Longitudinal
F77: 0.695 | J77: 1/2" | K77: 0 | L77: 4 | M77: =+F77 -> 0.695 | N77: =IF(+$J77=N$9,+$K77*$L77*$M77,0) -> 0 | O77: =IF(+$J77=O$9,+$K77*$L77*$M77,0) -> 0 | P77: =IF(+$J77=P$9,+$K77*$L77*$M77,0) -> 0 | Q77: =IF(+$J77=Q$9,+$K77*$L77*$M77,0) -> 0 | R77: =IF(+$J77=R$9,+$K77*$L77*$M77,0) -> 0 | S77: =IF(+$J77=S$9,+$K77*$L77*$M77,0) -> 0
C80: Losa sobre compuerta de cierre - Acero Transversal
F82: 0.76 | J82: 1/2" | K82: 0 | L82: 5 | M82: =+F82 -> 0.76 | N82: =IF(+$J82=N$9,+$K82*$L82*$M82,0) -> 0 | O82: =IF(+$J82=O$9,+$K82*$L82*$M82,0) -> 0 | P82: =IF(+$J82=P$9,+$K82*$L82*$M82,0) -> 0 | Q82: =IF(+$J82=Q$9,+$K82*$L82*$M82,0) -> 0 | R82: =IF(+$J82=R$9,+$K82*$L82*$M82,0) -> 0 | S82: =IF(+$J82=S$9,+$K82*$L82*$M82,0) -> 0
G85: 0.2
F87: 0.2 | J87: 3/8" | K87: 0 | L87: 4 | M87: =+F87+G89+G85 -> 0.4 | N87: =IF(+$J87=N$9,+$K87*$L87*$M87,0) -> 0 | O87: =IF(+$J87=O$9,+$K87*$L87*$M87,0) -> 0 | P87: =IF(+$J87=P$9,+$K87*$L87*$M87,0) -> 0 | Q87: =IF(+$J87=Q$9,+$K87*$L87*$M87,0) -> 0 | R87: =IF(+$J87=R$9,+$K87*$L87*$M87,0) -> 0 | S87: =IF(+$J87=S$9,+$K87*$L87*$M87,0) -> 0
C90: Bloque de canal de descarga Acero Horizontal
F92: 0.1 | J92: 3/8" | K92: 0 | L92: 2 | M92: =+F92 -> 0.1 | N92: =IF(+$J92=N$9,+$K92*$L92*$M92,0) -> 0 | O92: =IF(+$J92=O$9,+$K92*$L92*$M92,0) -> 0 | P92: =IF(+$J92=P$9,+$K92*$L92*$M92,0) -> 0 | Q92: =IF(+$J92=Q$9,+$K92*$L92*$M92,0) -> 0 | R92: =IF(+$J92=R$9,+$K92*$L92*$M92,0) -> 0 | S92: =IF(+$J92=S$9,+$K92*$L92*$M92,0) -> 0
C95: Dientes - Acero Longitudinal
G97: 0.43 | J97: 3/8" | K97: 0 | L97: 2 | M97: =+G97+F99 -> 0.53 | N97: =IF(+$J97=N$9,+$K97*$L97*$M97,0) -> 0 | O97: =IF(+$J97=O$9,+$K97*$L97*$M97,0) -> 0 | P97: =IF(+$J97=P$9,+$K97*$L97*$M97,0) -> 0 | Q97: =IF(+$J97=Q$9,+$K97*$L97*$M97,0) -> 0 | R97: =IF(+$J97=R$9,+$K97*$L97*$M97,0) -> 0 | S97: =IF(+$J97=S$9,+$K97*$L97*$M97,0) -> 0
F99: 0.1
C100: Dientes - Acero Vertical
G102: 0.29 | J102: 3/8" | K102: 0 | L102: 2 | M102: =+G102+G104 -> 0.39 | N102: =IF(+$J102=N$9,+$K102*$L102*$M102,0) -> 0 | O102: =IF(+$J102=O$9,+$K102*$L102*$M102,0) -> 0 | P102: =IF(+$J102=P$9,+$K102*$L102*$M102,0) -> 0 | Q102: =IF(+$J102=Q$9,+$K102*$L102*$M102,0) -> 0 | R102: =IF(+$J102=R$9,+$K102*$L102*$M102,0) -> 0 | S102: =IF(+$J102=S$9,+$K102*$L102*$M102,0) -> 0
G104: 0.1
C105: Dientes - Acero Longitudinal
G107: 0.8 | J107: 3/8" | K107: 0 | L107: 2 | M107: =+G107+F109 -> 0.8 | N107: =IF(+$J107=N$9,+$K107*$L107*$M107,0) -> 0 | O107: =IF(+$J107=O$9,+$K107*$L107*$M107,0) -> 0 | P107: =IF(+$J107=P$9,+$K107*$L107*$M107,0) -> 0 | Q107: =IF(+$J107=Q$9,+$K107*$L107*$M107,0) -> 0 | R107: =IF(+$J107=R$9,+$K107*$L107*$M107,0) -> 0 | S107: =IF(+$J107=S$9,+$K107*$L107*$M107,0) -> 0
C110: Umbral terminal - Acero Transversal | F110: 0.223
G112: 0.155 | J112: 3/8" | K112: 0 | L112: 11 | M112: =+G112+G114+F110 -> 0.732 | N112: =IF(+$J112=N$9,+$K112*$L112*$M112,0) -> 0 | O112: =IF(+$J112=O$9,+$K112*$L112*$M112,0) -> 0 | P112: =IF(+$J112=P$9,+$K112*$L112*$M112,0) -> 0 | Q112: =IF(+$J112=Q$9,+$K112*$L112*$M112,0) -> 0 | R112: =IF(+$J112=R$9,+$K112*$L112*$M112,0) -> 0 | S112: =IF(+$J112=S$9,+$K112*$L112*$M112,0) -> 0
G114: 0.354
C115: Umbral terminal - Acero Longitudinal
G117: 2.3 | J117: 3/8" | K117: 0 | L117: 2 | M117: =+G117+F119+F115 -> 2.3 | N117: =IF(+$J117=N$9,+$K117*$L117*$M117,0) -> 0 | O117: =IF(+$J117=O$9,+$K117*$L117*$M117,0) -> 0 | P117: =IF(+$J117=P$9,+$K117*$L117*$M117,0) -> 0 | Q117: =IF(+$J117=Q$9,+$K117*$L117*$M117,0) -> 0 | R117: =IF(+$J117=R$9,+$K117*$L117*$M117,0) -> 0 | S117: =IF(+$J117=S$9,+$K117*$L117*$M117,0) -> 0
C120: Umbral terminal - Acero Vertical
G122: 0.285 | J122: 1/2" | K122: 0 | L122: 2 | M122: =+G122 -> 0.285 | N122: =IF(+$J122=N$9,+$K122*$L122*$M122,0) -> 0 | O122: =IF(+$J122=O$9,+$K122*$L122*$M122,0) -> 0 | P122: =IF(+$J122=P$9,+$K122*$L122*$M122,0) -> 0 | Q122: =IF(+$J122=Q$9,+$K122*$L122*$M122,0) -> 0 | R122: =IF(+$J122=R$9,+$K122*$L122*$M122,0) -> 0 | S122: =IF(+$J122=S$9,+$K122*$L122*$M122,0) -> 0
G124: 0.1
A125: Losa | B125: Losa de Fondo | C125: Acero Longitudinal
F126: 4.266
E127: 0.5 | H127: 0.5 | J127: 3/8" | K127: 0 | L127: 10 | M127: =F126+H127+E127 -> 5.266 | N127: =IF(+$J127=N$9,+$K127*$L127*$M127,0) -> 0 | O127: =IF(+$J127=O$9,+$K127*$L127*$M127,0) -> 0 | P127: =IF(+$J127=P$9,+$K127*$L127*$M127,0) -> 0 | Q127: =IF(+$J127=Q$9,+$K127*$L127*$M127,0) -> 0 | R127: =IF(+$J127=R$9,+$K127*$L127*$M127,0) -> 0 | S127: =IF(+$J127=S$9,+$K127*$L127*$M127,0) -> 0
C130: Acero Vertical | G130: 0.25
J132: 3/8" | K132: 0 | L132: 22 | M132: =F133+G130+G134 -> 2.909 | N132: =IF(+$J132=N$9,+$K132*$L132*$M132,0) -> 0 | O132: =IF(+$J132=O$9,+$K132*$L132*$M132,0) -> 0 | P132: =IF(+$J132=P$9,+$K132*$L132*$M132,0) -> 0 | Q132: =IF(+$J132=Q$9,+$K132*$L132*$M132,0) -> 0 | R132: =IF(+$J132=R$9,+$K132*$L132*$M132,0) -> 0 | S132: =IF(+$J132=S$9,+$K132*$L132*$M132,0) -> 0
F133: 2.409
G134: 0.25
B135: Uña de losa | C135: Acero Vertical
G137: 0.475 | J137: 1/2" | K137: 0 | L137: 10 | M137: =G137 -> 0.475 | N137: =IF(+$J137=N$9,+$K137*$L137*$M137,0) -> 0 | O137: =IF(+$J137=O$9,+$K137*$L137*$M137,0) -> 0 | P137: =IF(+$J137=P$9,+$K137*$L137*$M137,0) -> 0 | Q137: =IF(+$J137=Q$9,+$K137*$L137*$M137,0) -> 0 | R137: =IF(+$J137=R$9,+$K137*$L137*$M137,0) -> 0 | S137: =IF(+$J137=S$9,+$K137*$L137*$M137,0) -> 0
C140: Acero Transversal
F142: 2.34 | J142: 1/2" | K142: 0 | L142: 3 | M142: =F142 -> 2.34 | N142: =IF(+$J142=N$9,+$K142*$L142*$M142,0) -> 0 | O142: =IF(+$J142=O$9,+$K142*$L142*$M142,0) -> 0 | P142: =IF(+$J142=P$9,+$K142*$L142*$M142,0) -> 0 | Q142: =IF(+$J142=Q$9,+$K142*$L142*$M142,0) -> 0 | R142: =IF(+$J142=R$9,+$K142*$L142*$M142,0) -> 0 | S142: =IF(+$J142=S$9,+$K142*$L142*$M142,0) -> 0
A145: Camara humeda y caja de valvulas | B145: Losa de fondo | C145: Acero Longitudinal - Camara humeda
H146: =+E148 -> 0.085
J147: 3/8" | K147: 0 | L147: 9 | M147: =+E148+F148+H146 -> 1.32 | N147: =IF(+$J147=N$9,+$K147*$L147*$M147,0) -> 0 | O147: =IF(+$J147=O$9,+$K147*$L147*$M147,0) -> 0 | P147: =IF(+$J147=P$9,+$K147*$L147*$M147,0) -> 0 | Q147: =IF(+$J147=Q$9,+$K147*$L147*$M147,0) -> 0 | R147: =IF(+$J147=R$9,+$K147*$L147*$M147,0) -> 0 | S147: =IF(+$J147=S$9,+$K147*$L147*$M147,0) -> 0
E148: 0.085 | F148: 1.15
C150: Acero Transversal - Camara humeda | G150: 0.1
G152: 1.64 | J152: 3/8" | K152: 0 | L152: 6 | M152: =+G150+F154+G152 -> 1.84 | N152: =IF(+$J152=N$9,+$K152*$L152*$M152,0) -> 0 | O152: =IF(+$J152=O$9,+$K152*$L152*$M152,0) -> 0 | P152: =IF(+$J152=P$9,+$K152*$L152*$M152,0) -> 0 | Q152: =IF(+$J152=Q$9,+$K152*$L152*$M152,0) -> 0 | R152: =IF(+$J152=R$9,+$K152*$L152*$M152,0) -> 0 | S152: =IF(+$J152=S$9,+$K152*$L152*$M152,0) -> 0
F154: 0.1
C155: Acero Longitudinal - Camara seca
E156: 0.1 | H156: =+E156 -> 0.1
J157: 3/8" | K157: 0 | L157: 9 | M157: =+E156+F158+H156 -> 1.72
F158: 1.52 | N158: =IF(+$J158=N$9,+$K158*$L158*$M158,0) -> 0 | O158: =IF(+$J158=O$9,+$K158*$L158*$M158,0) -> 0 | P158: =IF(+$J158=P$9,+$K158*$L158*$M158,0) -> 0 | Q158: =IF(+$J158=Q$9,+$K158*$L158*$M158,0) -> 0 | R158: =IF(+$J158=R$9,+$K158*$L158*$M158,0) -> 0 | S158: =IF(+$J158=S$9,+$K158*$L158*$M158,0) -> 0
C160: Acero Transversal - Camara seca | G160: =F164 -> 0.1
G162: 1.64 | J162: 3/8" | K162: 0 | L162: 6 | M162: =+G162+F164+G160 -> 1.84 | N162: =IF(+$J162=N$9,+$K162*$L162*$M162,0) -> 0 | O162: =IF(+$J162=O$9,+$K162*$L162*$M162,0) -> 0 | P162: =IF(+$J162=P$9,+$K162*$L162*$M162,0) -> 0 | Q162: =IF(+$J162=Q$9,+$K162*$L162*$M162,0) -> 0 | R162: =IF(+$J162=R$9,+$K162*$L162*$M162,0) -> 0 | S162: =IF(+$J162=S$9,+$K162*$L162*$M162,0) -> 0
F164: 0.1
B165: Muro | C165: Vertedero - Horizontal
E167: 0.1 | H167: 0.1 | J167: 3/8" | K167: 0 | L167: 2 | M167: =+E167+F168 -> 1.2 | N167: =IF(+$J167=N$9,+$K167*$L167*$M167,0) -> 0 | O167: =IF(+$J167=O$9,+$K167*$L167*$M167,0) -> 0 | P167: =IF(+$J167=P$9,+$K167*$L167*$M167,0) -> 0 | Q167: =IF(+$J167=Q$9,+$K167*$L167*$M167,0) -> 0 | R167: =IF(+$J167=R$9,+$K167*$L167*$M167,0) -> 0 | S167: =IF(+$J167=S$9,+$K167*$L167*$M167,0) -> 0
F168: 1.1
C170: Vertedero - Vertical
G172: 0.66 | J172: 3/8" | K172: 0 | L172: 6 | M172: =+F174+G172 -> 0.91 | N172: =IF(+$J172=N$9,+$K172*$L172*$M172,0) -> 0 | O172: =IF(+$J172=O$9,+$K172*$L172*$M172,0) -> 0 | P172: =IF(+$J172=P$9,+$K172*$L172*$M172,0) -> 0 | Q172: =IF(+$J172=Q$9,+$K172*$L172*$M172,0) -> 0 | R172: =IF(+$J172=R$9,+$K172*$L172*$M172,0) -> 0 | S172: =IF(+$J172=S$9,+$K172*$L172*$M172,0) -> 0
F174: 0.25
C175: Acero Vertical - Camara humeda - lateral
E177: 1.15 | J177: 3/8" | K177: 0 | L177: 8 | M177: =+E177+F179+F175 -> 1.4 | N177: =IF(+$J177=N$9,+$K177*$L177*$M177,0) -> 0 | O177: =IF(+$J177=O$9,+$K177*$L177*$M177,0) -> 0 | P177: =IF(+$J177=P$9,+$K177*$L177*$M177,0) -> 0 | Q177: =IF(+$J177=Q$9,+$K177*$L177*$M177,0) -> 0 | R177: =IF(+$J177=R$9,+$K177*$L177*$M177,0) -> 0 | S177: =IF(+$J177=S$9,+$K177*$L177*$M177,0) -> 0
F179: 0.25
C180: Acero Horizontal - camara humeda - lateral | F180: =F184 -> 0.25
J182: 3/8" | K182: 0 | L182: 6 | M182: =+G183+F184+F180 -> 2.047 | N182: =IF(+$J182=N$9,+$K182*$L182*$M182,0) -> 0 | O182: =IF(+$J182=O$9,+$K182*$L182*$M182,0) -> 0 | P182: =IF(+$J182=P$9,+$K182*$L182*$M182,0) -> 0 | Q182: =IF(+$J182=Q$9,+$K182*$L182*$M182,0) -> 0 | R182: =IF(+$J182=R$9,+$K182*$L182*$M182,0) -> 0 | S182: =IF(+$J182=S$9,+$K182*$L182*$M182,0) -> 0
...

Sheet 1.8.2 VALV-PURGA T-2
B1: PLANILLA DE METRADOS Del SISTEMA DE AGUA POTABLE
B2: "CREACION DEL SERVICIO DE AGUA POTABLE RURAL Y CREACION DEL SERVICIO DE ALCANTARILLADO U OTRAS FORMAS DE DISPOSICION SANITARIA DE EXCRETAS EN EL SECTOR NUEVA ESPERANZA DE LA CC.NN. BAJO PITOCUNA DISTRITO DE RIO NEGRO, PROVINCIA DE SATIPO, DEPARTAMENTO DE JUNIN"
B3: VALVULA DE PURGA TIPO 2
L4: N° | M4: ACCESORIOS | N4: UNIDAD
L5: 1 | M5: Valvula compuerta Bronce | N5: 1
L6: 2 | M6: Niple PVC L=2" | N6: 2
L7: 3 | M7: Union universal PVC | N7: 2
L8: 4 | M8: Adaptador UPR PVC | N8: 2
L9: 5 | M9: Niple PVC L=8" | N9: 3
L10: 6 | M10: Codo PVC SP x 45° | N10: 4
L11: 7 | M11: Niple PVC L=22" | N11: 1
L12: 8 | M12: Niple PVC L=7" | N12: 1
L13: 9 | M13: Tee PVC SP | N13: 1
L14: 10 | M14: Tapón macho F°G° | N14: 1
M15: Tuberia PVC C-10 | N15: 3
B18: PARTIDA | C18: DESCRIPCION | D18: UNIDAD | E18: VECES | F18: LONGITUD | G18: ANCHO | H18: ALTURA | I18: SUB-TOTAL | J18: TOTAL
B19: =+"01.08.02" -> 01.08.02 | C19: =+B3&" ("&E19&" und.)" -> VALVULA DE PURGA TIPO 2 (3 und.) | E19: =+SUM(E20:E20) -> 3
C20: =+$B$3&L20 -> VALVULA DE PURGA TIPO 2 Ø = 1" | E20: 3 | L20: Ø = 1"
B22: =B$19 & ".01" -> 01.08.02.01 | C22: TRABAJOS PRELIMINARES | E22: =+$E$19 -> 3 | L22: Descripcion | M22: Medida | N22: Unidad
B23: =B$22 & ".01" -> 01.08.02.01.01 | C23: LIMPIEZA Y DESBROCE DE TERRENO MANUAL | D23: m2 | I23: =SUM(I24:I25) -> 5.56 | J23: =+I23*$E$22 -> 16.68 | L23: Caja de Valvulas
C24: Caja de valvula | E24: 1 | F24: =+M45 -> 1.6 | G24: =+M44 -> 1.6 | I24: =+ROUND(PRODUCT(E24:G24),2) -> 2.56 | L24: Ancho | M24: 0.6 | N24: m
C25: Tuberia de limpieza | E25: 1 | F25: 3 | G25: 1 | I25: =+ROUND(PRODUCT(E25:H25),2) -> 3 | L25: Largo | M25: 0.6 | N25: m
L26: Altura | M26: 0.7 | N26: m
B27: =B$22 & ".02" -> 01.08.02.01.02 | C27: TRAZO Y REPLANTEO PRELIMINAR PARA ESTRUCTURAS | D27: m2 | I27: =SUM(I28:I29) -> 5.56 | J27: =+I27*$E$22 -> 16.68 | L27: Uña | M27: 0.1 | N27: m
C28: Caja de valvula | E28: 1 | F28: =+F24 -> 1.6 | G28: =+G24 -> 1.6 | I28: =+ROUND(PRODUCT(E28:G28),2) -> 2.56 | L28: Espesor de muro | M28: 0.1 | N28: m
C29: Tuberia de limpieza | E29: 1 | F29: =+F25 -> 3 | G29: =+G25 -> 1 | I29: =+ROUND(PRODUCT(E29:H29),2) -> 3 | L29: Cimentacion B
B31: =B$22 & ".03" -> 01.08.02.01.03 | C31: TRAZO Y REPLANTEO DURANTE EL PROCESO PARA ESTRUCTURAS | D31: m2 | I31: =SUM(I32:I33) -> 5.56 | J31: =+I31*$E$22 -> 16.68
C32: Caja de valvula | E32: 1 | F32: =+F28 -> 1.6 | G32: =+G28 -> 1.6 | I32: =+ROUND(PRODUCT(E32:G32),2) -> 2.56
C33: Tuberia de limpieza | E33: 1 | F33: =+F29 -> 3 | G33: =+G29 -> 1 | I33: =+ROUND(PRODUCT(E33:H33),2) -> 3
L34: Ancho | M34: =+M24+2*M28+2*M27 -> 1 | N34: m
B35: =B$19 & ".02" -> 01.08.02.02 | C35: MOVIMIENTO DE TIERRAS | E35: =+$E$19 -> 3 | L35: Largo | M35: =+M25+2*M28+2*M27 -> 1 | N35: m
B36: =B$35 & ".01" -> 01.08.02.02.01 | C36: EXCAVACION MANUAL EN TERRENO NORMAL | D36: m3 | I36: =SUM(I37:I44) -> 3.38 | J36: =+I36*$E$35 -> 10.14 | L36: Espesor de losa | M36: 0.1 | N36: m
C37: Caja de valvula | E37: 1 | F37: Volumen | H37: =+G42/6*((2*G38+G40)*G39+(2*G40+G38)*G41) -> 1.5786667 | I37: =+ROUND(PRODUCT(E37:H37),2) -> 1.58 | L37: Excavacion
F38: a | G38: =+M44 -> 1.6 | L38: Fondo
F39: b | G39: =+M45 -> 1.6 | L39: Excavacion | M39: 0.1 | N39: m
C40: Se considera 0.10m de | F40: a´ | G40: =+M40 -> 1.2 | L40: Ancho (a´) | M40: =+M34+2*M39 -> 1.2 | N40: m
C41: excavacion y talud 1:0.25 | F41: b´ | G41: =+M41 -> 1.2 | L41: Largo (b´) | M41: =+M35+2*M39 -> 1.2 | N41: m
F42: h | G42: =+M47 -> 0.8 | L42: Superior
L43: Excavacion | M43: =+M46*M47 -> 0.2 | N43: m
C44: Zanja para tuberia de limpieza | E44: 1 | F44: =+F25 -> 3 | G44: =+G29 -> 1 | H44: 0.6 | I44: =+ROUND(PRODUCT(E44:H44),2) -> 1.8 | L44: Ancho (a) | M44: =+M40+2*M43 -> 1.6 | N44: m
L45: Largo (b) | M45: =+M41+2*M43 -> 1.6 | N45: m
B46: =B$35 & ".02" -> 01.08.02.02.02 | C46: RELLENO COMPACTADO CON MATERIAL PROPIO SELECCIONADO | D46: m3 | I46: =SUM(I47:I49) -> 1.03 | J46: =+I46*$E$35 -> 3.09 | L46: Talud | M46: 0.25 | N46: m
C47: Volumen de excavacion | E47: 1 | H47: =+H37 -> 1.5786667 | I47: =+ROUND(PRODUCT(E47:H47),2) -> 1.58 | L47: Altura (h) | M47: 0.8 | N47: m
C48: Volumen de muros | E48: -1 | F48: =+M25+2*M28 -> 0.8 | G48: =+M24+2*M28 -> 0.8 | H48: =+M26 -> 0.7 | I48: =+ROUND(PRODUCT(E48:H48),2) -> -0.45 | L48: Superficie Libre (sl) | M48: 0.05 | N48: m
C49: Volumen de losa | E49: -1 | F49: =+M35 -> 1 | G49: =+M34 -> 1 | H49: =+M36 -> 0.1 | I49: =+ROUND(PRODUCT(E49:H49),2) -> -0.1 | L49: Filtro de piedra | M49: 0.2 | N49: m
B51: =B$35 & ".03" -> 01.08.02.02.03 | C51: ACARREO Y ELIMINACION DE MAT. EXCEDENTE Dmax=30 m | D51: m3 | I51: =SUM(I52:I53) -> 2.92 | J51: =+I51*$E$35 -> 8.76
C52: Excavacion - Esponjamiento 20% | E52: 1 | F52: 1.2 | G52: Volumen | H52: =+I36 -> 3.38 | I52: =+ROUND(PRODUCT(E52:H52),2) -> 4.06
C53: Relleno - Compactacion 90% | E53: -1 | F53: =1/(0.9) -> 1.1111111 | G53: Volumen | H53: =+I46 -> 1.03 | I53: =+ROUND(PRODUCT(E53:H53),2) -> -1.14
B55: =B$19 & ".03" -> 01.08.02.03 | C55: OBRAS DE CONCRETO SIMPLE | E55: =+$E$19 -> 3
B56: =B$55 & ".01" -> 01.08.02.03.01 | C56: CONCRETO f'c=140 kg/cm2 EN DADOS | D56: m3 | I56: =SUM(I57) -> 0.012 | J56: =+I56*$E$55 -> 0.036
C57: Dado Movil | E57: 1 | F57: 0.3 | G57: 0.2 | H57: 0.2 | I57: =+ROUND(PRODUCT(E57:H57),3) -> 0.012
B59: =B$19 & ".04" -> 01.08.02.04 | C59: OBRAS DE CONCRETO ARMADO
B60: =B$59 & ".01" -> 01.08.02.04.01 | C60: CONCRETO f'c=175 kg/cm2 EN MUROS | D60: m3 | I60: =SUM(I61:I62) -> 0.196 | J60: =+I60*E55 -> 0.588
C61: Muro longitudinales | E61: 2 | F61: =+M24+2*M28 -> 0.8 | G61: =+M28 -> 0.1 | H61: =+$M$26 -> 0.7 | I61: =+ROUND(PRODUCT(E61:H61),3) -> 0.112
C62: Muros transversales | E62: 2 | F62: =+M24 -> 0.6 | G62: =+M28 -> 0.1 | H62: =+$M$26 -> 0.7 | I62: =+ROUND(PRODUCT(E62:H62),3) -> 0.084
B64: =B$59 & ".02" -> 01.08.02.04.02 | C64: CONCRETO f'c=175 kg/cm2 EN LOSA | D64: m3 | I64: =SUM(I65:I66) -> 0.064 | J64: =+I64*E55 -> 0.192
C65: Losa de fondo | E65: 1 | F65: =+M35 -> 1 | G65: =+M34 -> 1 | H65: =+$M$36 -> 0.1 | I65: =+ROUND(PRODUCT(E65:H65),3) -> 0.1
C66: Descuento de Grava | E66: -1 | F66: =+M25 -> 0.6 | G66: =+M24 -> 0.6 | H66: =+$M$36 -> 0.1 | I66: =+ROUND(PRODUCT(E66:H66),3) -> -0.036
B68: =B$59 & ".03" -> 01.08.02.04.03 | C68: ENCOFRADO Y DESENCOFRADO EN DADOS | D68: m2 | I68: =SUM(I69:I70) -> 0.2 | J68: =+I68*$E$55 -> 0.6
C69: Dado Movil (laterles) | E69: 2 | F69: 0.2 | H69: 0.2 | I69: =+ROUND(PRODUCT(E69:H69),3) -> 0.08
C70: Dado Movil (posterior y frontal) | E70: 2 | F70: 0.3 | G70: 0.2 | I70: =+ROUND(PRODUCT(E70:H70),3) -> 0.12
B72: =B$59 & ".04" -> 01.08.02.04.04 | C72: ENCOFRADO Y DESENCOFRADO EN MUROS | D72: m2 | I72: =SUM(I73:I76) -> 3.92 | J72: =+I72*$E$55 -> 11.76
C73: Muro longitudinales cara exterior | E73: 2 | F73: =+M25+2*M28 -> 0.8 | H73: =+$M$26 -> 0.7 | I73: =+ROUND(PRODUCT(E73:H73),3) -> 1.12
C74: Muro transversal cara exterior | E74: 2 | G74: =+M24+2*M28 -> 0.8 | H74: =+$M$26 -> 0.7 | I74: =+ROUND(PRODUCT(E74:H74),3) -> 1.12
C75: Muro longitudinales cara interior | E75: 2 | F75: =+$M$25 -> 0.6 | H75: =+$M$26 -> 0.7 | I75: =+ROUND(PRODUCT(E75:H75),3) -> 0.84
C76: Muro transversal cara interior | E76: 2 | G76: =+$M$24 -> 0.6 | H76: =+$M$26 -> 0.7 | I76: =+ROUND(PRODUCT(E76:H76),3) -> 0.84
B78: =B$59 & ".05" -> 01.08.02.04.05 | C78: ENCOFRADO Y DESENCOFRADO EN LOSAS | D78: m2 | I78: =SUM(I79:I82) -> 0.64 | J78: =+I78*$E$55 -> 1.92
C79: Losa de fondo, longitudinal cara exterior | E79: 2 | F79: =+$M$35 -> 1 | H79: =+$M$36 -> 0.1 | I79: =+ROUND(PRODUCT(E79:H79),3) -> 0.2
C80: Losa de fondo, transversal cara exterior | E80: 2 | G80: =+$M$34 -> 1 | H80: =+$M$36 -> 0.1 | I80: =+ROUND(PRODUCT(E80:H80),3) -> 0.2
C81: Losa de fondo, longitudinal cara interior | E81: 2 | F81: =+$M$25 -> 0.6 | H81: =+$M$36 -> 0.1 | I81: =+ROUND(PRODUCT(E81:H81),3) -> 0.12
C82: Losa de fondo, transversal cara interior | E82: 2 | G82: =+$M$24 -> 0.6 | H82: =+$M$36 -> 0.1 | I82: =+ROUND(PRODUCT(E82:H82),3) -> 0.12
B84: =B$59 & ".06" -> 01.08.02.04.06 | C84: ACERO CORRUGADO f'y=4200 kg/cm2 G-60 | D84: kg | I84: =SUM(I85:I85) -> 25.7152 | J84: =+I84*$E$55 -> 77.1456
C85: Ver planilla de metrado de acero | E85: 1 | I85: ='1.8 M-ACERO T-02'!N228 -> 25.7152
B87: =B$19 & ".05" -> 01.08.02.05 | C87: REVOQUES Y ENLUCIDOS Y MOLDURAS | E87: =+$E$19 -> 3
B88: =B$87 & ".01" -> 01.08.02.05.01 | C88: TARRAJEO INTERIOR MEZCLA C:A 1:4, e=1.5 cm | D88: m2 | I88: =SUM(I89:I92) -> 1.92 | J88: =+I88*$E$87 -> 5.76
C89: Muro longitudinales cara interior | E89: 2 | F89: =+$M$25 -> 0.6 | H89: =+$M$26 -> 0.7 | I89: =+ROUND(PRODUCT(E89:H89),2) -> 0.84
C90: Muro transversal cara interior | E90: 2 | G90: =+$M$24 -> 0.6 | H90: =+$M$26 -> 0.7 | I90: =+ROUND(PRODUCT(E90:H90),2) -> 0.84
C91: Losa de fondo, longitudinal cara interior | E91: 2 | F91: =+$M$25 -> 0.6 | H91: =+$M$36 -> 0.1 | I91: =+ROUND(PRODUCT(E91:H91),2) -> 0.12
C92: Losa de fondo, transversal cara interior | E92: 2 | G92: =+$M$24 -> 0.6 | H92: =+$M$36 -> 0.1 | I92: =+ROUND(PRODUCT(E92:H92),2) -> 0.12
B94: =B$19 & ".06" -> 01.08.02.06 | C94: ASENTADO DE PIEDRA | E94: =+$E$19 -> 3
B95: =B$94 & ".01" -> 01.08.02.06.01 | C95: EMPEDRADO, ASENTADO Y EMBOQUILLADO C/CONCRETO f´c=140 kg/cm2, e=15 cm | D95: m2 | I95: =SUM(I96) -> 0.25 | J95: =+I95*$E$94 -> 0.75
C96: Proteccion de dado de anclaje | E96: 1 | F96: 0.5 | G96: 0.5 | I96: =+ROUND(PRODUCT(E96:H96),2) -> 0.25
B98: =B$19 & ".07" -> 01.08.02.07 | C98: FILTROS | E98: =+$E$19 -> 3
B99: =B$98 & ".01" -> 01.08.02.07.01 | C99: PIEDRA CHANCADA DE 1/2" | D99: m3 | I99: =SUM(I100) -> 0.072 | J99: =+I99*$E$98 -> 0.216
E100: 1 | F100: =+M25 -> 0.6 | G100: =+M24 -> 0.6 | H100: =+M49 -> 0.2 | I100: =+ROUND(PRODUCT(E100:H100),3) -> 0.072
B102: =B$19 & ".08" -> 01.08.02.08 | C102: INSTALACIONES SANITARIAS
B103: =B$102 & ".01" -> 01.08.02.08.01 | C103: SUMINISTRO Y COLOC. DE ACCESORIOS EN VALVULA DE PURGA TIPO 2 Ø = 1" | D103: und | E103: =E98 -> 3 | I103: =+ROUND(PRODUCT(E103:H103),3) -> 3 | J103: =I103 -> 3
C104: Valvula compuerta Bronce Ø = 1" | D104: und | E104: 1
C105: Niple PVC L=2" Ø = 1" | D105: und | E105: 2
C106: Union universal PVC Ø = 1" | D106: und | E106: 2
C107: Adaptador UPR PVC Ø = 1" | D107: und | E107: 2
C108: Niple PVC L=8" Ø = 1" | D108: und | E108: 3
C109: Codo PVC SP x 45° Ø = 1" | D109: und | E109: 4
C110: Niple PVC L=22" Ø = 1" | D110: und | E110: 1
C111: Niple PVC L=7" Ø = 1" | D111: und | E111: 1
C112: Tee PVC SP Ø = 1" | D112: und | E112: 1
C113: Tapón macho PVC Ø = 1" | D113: und | E113: 1
C114: Cinta teflon | D114: und | E114: 5
C115: Pegamento para PVC | D115: und | E115: 1
B117: =B$19 & ".09" -> 01.08.02.09 | C117: CARPINTERIA METALICA | E117: =+$E$19 -> 3
...

Sheet 1.8 M-ACERO T-02
A2: METRADOS Del SISTEMA DE AGUA POTABLE
A3: "CREACION DEL SERVICIO DE AGUA POTABLE RURAL Y CREACION DEL SERVICIO DE ALCANTARILLADO U OTRAS FORMAS DE DISPOSICION SANITARIA DE EXCRETAS EN EL SECTOR NUEVA ESPERANZA DE LA CC.NN. BAJO PITOCUNA DISTRITO DE RIO NEGRO, PROVINCIA DE SATIPO, DEPARTAMENTO DE JUNIN"
A4: VALVULA DE PURGA TIPO 2
A6: =+'[26]Captación Dique'!B140 -> 01.03.04.03 | D6: =+'[26]Captación Dique'!C140 -> ACERO f'y=4200 kg/cm2
A8: DESCRIPCION | D8: ELEMENTO | J8: Ø (Pulg.) | K8: CANTIDAD | L8: N° DE ELEMENTOS | M8: LONG. DEL ELEMENTO (m) | N8: LONGITUD (m)
N9: 1/4" | O9: 3/8" | P9: 1/2" | Q9: 5/8" | R9: 3/4" | S9: 1"
A10: CAMARA HUMEDA | B10: Muro y Losa | C10: Acero Vertical
F12: 0.95 | J12: 3/8" | K12: 4 | L12: 4 | M12: =+F12+G14 -> 1.15 | N12: =IF(+$J12=N$9,+$K12*$L12*$M12,0) -> 0 | O12: =IF(+$J12=O$9,+$K12*$L12*$M12,0) -> 18.4 | P12: =IF(+$J12=P$9,+$K12*$L12*$M12,0) -> 0 | Q12: =IF(+$J12=Q$9,+$K12*$L12*$M12,0) -> 0 | R12: =IF(+$J12=R$9,+$K12*$L12*$M12,0) -> 0 | S12: =IF(+$J12=S$9,+$K12*$L12*$M12,0) -> 0
G14: 0.2
C15: Acero Horizontal | F15: 0.2
E16: 0.2 | F16: 0.7
F17: 0.7 | H17: 0.7 | J17: 3/8" | K17: 1 | L17: 4 | M17: =+F19+H17+E16+F15+F16+F17 -> 3.2 | N17: =IF(+$J17=N$9,+$K17*$L17*$M17,0) -> 0 | O17: =IF(+$J17=O$9,+$K17*$L17*$M17,0) -> 12.8 | P17: =IF(+$J17=P$9,+$K17*$L17*$M17,0) -> 0 | Q17: =IF(+$J17=Q$9,+$K17*$L17*$M17,0) -> 0 | R17: =IF(+$J17=R$9,+$K17*$L17*$M17,0) -> 0 | S17: =IF(+$J17=S$9,+$K17*$L17*$M17,0) -> 0
F19: 0.7
C20: Losa - Acero Longitudinal y Transversal
F22: 0.92 | J22: 3/8" | K22: 4 | L22: 4 | M22: =+F22 -> 0.92 | N22: =IF(+$J22=N$9,+$K22*$L22*$M22,0) -> 0 | O22: =IF(+$J22=O$9,+$K22*$L22*$M22,0) -> 14.72 | P22: =IF(+$J22=P$9,+$K22*$L22*$M22,0) -> 0 | Q22: =IF(+$J22=Q$9,+$K22*$L22*$M22,0) -> 0 | R22: =IF(+$J22=R$9,+$K22*$L22*$M22,0) -> 0 | S22: =IF(+$J22=S$9,+$K22*$L22*$M22,0) -> 0
C25: Losa - Acero Transversal
F27: 4.44 | J27: 3/8" | K27: 0 | L27: 3 | M27: =+F27+H26+E26 -> 4.44 | N27: =IF(+$J27=N$9,+$K27*$L27*$M27,0) -> 0 | O27: =IF(+$J27=O$9,+$K27*$L27*$M27,0) -> 0 | P27: =IF(+$J27=P$9,+$K27*$L27*$M27,0) -> 0 | Q27: =IF(+$J27=Q$9,+$K27*$L27*$M27,0) -> 0 | R27: =IF(+$J27=R$9,+$K27*$L27*$M27,0) -> 0 | S27: =IF(+$J27=S$9,+$K27*$L27*$M27,0) -> 0
C30: Zapata - Acero Longitudinal
F32: 2.98 | J32: 3/8" | K32: 0 | L32: 4 | M32: =+F32 -> 2.98 | N32: =IF(+$J32=N$9,+$K32*$L32*$M32,0) -> 0 | O32: =IF(+$J32=O$9,+$K32*$L32*$M32,0) -> 0 | P32: =IF(+$J32=P$9,+$K32*$L32*$M32,0) -> 0 | Q32: =IF(+$J32=Q$9,+$K32*$L32*$M32,0) -> 0 | R32: =IF(+$J32=R$9,+$K32*$L32*$M32,0) -> 0 | S32: =IF(+$J32=S$9,+$K32*$L32*$M32,0) -> 0
C35: Zapata - Acero Transversal
F37: 4.44 | J37: 3/8" | K37: 0 | L37: 3 | M37: =+F37 -> 4.44 | N37: =IF(+$J37=N$9,+$K37*$L37*$M37,0) -> 0 | O37: =IF(+$J37=O$9,+$K37*$L37*$M37,0) -> 0 | P37: =IF(+$J37=P$9,+$K37*$L37*$M37,0) -> 0 | Q37: =IF(+$J37=Q$9,+$K37*$L37*$M37,0) -> 0 | R37: =IF(+$J37=R$9,+$K37*$L37*$M37,0) -> 0 | S37: =IF(+$J37=S$9,+$K37*$L37*$M37,0) -> 0
B40: Muro segundario | C40: Acero Vertical (interior y exterior)
F42: 1.23 | J42: 1/2" | K42: 0 | L42: 4 | M42: =+F42+G44 -> 1.33 | N42: =IF(+$J42=N$9,+$K42*$L42*$M42,0) -> 0 | O42: =IF(+$J42=O$9,+$K42*$L42*$M42,0) -> 0 | P42: =IF(+$J42=P$9,+$K42*$L42*$M42,0) -> 0 | Q42: =IF(+$J42=Q$9,+$K42*$L42*$M42,0) -> 0 | R42: =IF(+$J42=R$9,+$K42*$L42*$M42,0) -> 0 | S42: =IF(+$J42=S$9,+$K42*$L42*$M42,0) -> 0
G44: 0.1
C45: Acero Horizontal
J47: 3/8" | K47: 0 | L47: 7 | M47: =+F48 -> 0.839 | N47: =IF(+$J47=N$9,+$K47*$L47*$M47,0) -> 0 | O47: =IF(+$J47=O$9,+$K47*$L47*$M47,0) -> 0 | P47: =IF(+$J47=P$9,+$K47*$L47*$M47,0) -> 0 | Q47: =IF(+$J47=Q$9,+$K47*$L47*$M47,0) -> 0 | R47: =IF(+$J47=R$9,+$K47*$L47*$M47,0) -> 0 | S47: =IF(+$J47=S$9,+$K47*$L47*$M47,0) -> 0
F48: 0.839
C50: Zapata - Acero Longitudinal
J52: 1/2" | K52: 0 | L52: 6 | M52: =+F53 -> 0.839 | N52: =IF(+$J52=N$9,+$K52*$L52*$M52,0) -> 0 | O52: =IF(+$J52=O$9,+$K52*$L52*$M52,0) -> 0 | P52: =IF(+$J52=P$9,+$K52*$L52*$M52,0) -> 0 | Q52: =IF(+$J52=Q$9,+$K52*$L52*$M52,0) -> 0 | R52: =IF(+$J52=R$9,+$K52*$L52*$M52,0) -> 0 | S52: =IF(+$J52=S$9,+$K52*$L52*$M52,0) -> 0
F53: =+F48 -> 0.839
C55: Zapata - Acero Transversal
F57: 0.91 | J57: 1/2" | K57: 0 | L57: =+L42 -> 4 | M57: =+F57 -> 0.91 | N57: =IF(+$J57=N$9,+$K57*$L57*$M57,0) -> 0 | O57: =IF(+$J57=O$9,+$K57*$L57*$M57,0) -> 0 | P57: =IF(+$J57=P$9,+$K57*$L57*$M57,0) -> 0 | Q57: =IF(+$J57=Q$9,+$K57*$L57*$M57,0) -> 0 | R57: =IF(+$J57=R$9,+$K57*$L57*$M57,0) -> 0 | S57: =IF(+$J57=S$9,+$K57*$L57*$M57,0) -> 0
G60: 0.137
F62: 1.101 | J62: 1/2" | K62: 0 | L62: 7 | M62: =+F62+F64+G60 -> 1.488 | N62: =IF(+$J62=N$9,+$K62*$L62*$M62,0) -> 0 | O62: =IF(+$J62=O$9,+$K62*$L62*$M62,0) -> 0 | P62: =IF(+$J62=P$9,+$K62*$L62*$M62,0) -> 0 | Q62: =IF(+$J62=Q$9,+$K62*$L62*$M62,0) -> 0 | R62: =IF(+$J62=R$9,+$K62*$L62*$M62,0) -> 0 | S62: =IF(+$J62=S$9,+$K62*$L62*$M62,0) -> 0
F64: 0.25
C66: Acero Horizontal
F67: 1.26 | J67: 1/2" | K67: 0 | L67: 11 | M67: =+F67 -> 1.26 | N67: =IF(+$J67=N$9,+$K67*$L67*$M67,0) -> 0 | O67: =IF(+$J67=O$9,+$K67*$L67*$M67,0) -> 0 | P67: =IF(+$J67=P$9,+$K67*$L67*$M67,0) -> 0 | Q67: =IF(+$J67=Q$9,+$K67*$L67*$M67,0) -> 0 | R67: =IF(+$J67=R$9,+$K67*$L67*$M67,0) -> 0 | S67: =IF(+$J67=S$9,+$K67*$L67*$M67,0) -> 0
C70: Acero Vertical (Frontal) | G70: 0.2
F72: =+F67 -> 1.26 | J72: 1/2" | K72: 0 | L72: 7 | M72: =+F72+G70+G74 -> 1.96 | N72: =IF(+$J72=N$9,+$K72*$L72*$M72,0) -> 0 | O72: =IF(+$J72=O$9,+$K72*$L72*$M72,0) -> 0 | P72: =IF(+$J72=P$9,+$K72*$L72*$M72,0) -> 0 | Q72: =IF(+$J72=Q$9,+$K72*$L72*$M72,0) -> 0 | R72: =IF(+$J72=R$9,+$K72*$L72*$M72,0) -> 0 | S72: =IF(+$J72=S$9,+$K72*$L72*$M72,0) -> 0
G74: 0.5
C75: Losa sobre compuerta de cierre - Acero Longitudinal
F77: 0.695 | J77: 1/2" | K77: 0 | L77: 4 | M77: =+F77 -> 0.695 | N77: =IF(+$J77=N$9,+$K77*$L77*$M77,0) -> 0 | O77: =IF(+$J77=O$9,+$K77*$L77*$M77,0) -> 0 | P77: =IF(+$J77=P$9,+$K77*$L77*$M77,0) -> 0 | Q77: =IF(+$J77=Q$9,+$K77*$L77*$M77,0) -> 0 | R77: =IF(+$J77=R$9,+$K77*$L77*$M77,0) -> 0 | S77: =IF(+$J77=S$9,+$K77*$L77*$M77,0) -> 0
C80: Losa sobre compuerta de cierre - Acero Transversal
F82: 0.76 | J82: 1/2" | K82: 0 | L82: 5 | M82: =+F82 -> 0.76 | N82: =IF(+$J82=N$9,+$K82*$L82*$M82,0) -> 0 | O82: =IF(+$J82=O$9,+$K82*$L82*$M82,0) -> 0 | P82: =IF(+$J82=P$9,+$K82*$L82*$M82,0) -> 0 | Q82: =IF(+$J82=Q$9,+$K82*$L82*$M82,0) -> 0 | R82: =IF(+$J82=R$9,+$K82*$L82*$M82,0) -> 0 | S82: =IF(+$J82=S$9,+$K82*$L82*$M82,0) -> 0
G85: 0.2
F87: 0.2 | J87: 3/8" | K87: 0 | L87: 4 | M87: =+F87+G89+G85 -> 0.4 | N87: =IF(+$J87=N$9,+$K87*$L87*$M87,0) -> 0 | O87: =IF(+$J87=O$9,+$K87*$L87*$M87,0) -> 0 | P87: =IF(+$J87=P$9,+$K87*$L87*$M87,0) -> 0 | Q87: =IF(+$J87=Q$9,+$K87*$L87*$M87,0) -> 0 | R87: =IF(+$J87=R$9,+$K87*$L87*$M87,0) -> 0 | S87: =IF(+$J87=S$9,+$K87*$L87*$M87,0) -> 0
C90: Bloque de canal de descarga Acero Horizontal
F92: 0.1 | J92: 3/8" | K92: 0 | L92: 2 | M92: =+F92 -> 0.1 | N92: =IF(+$J92=N$9,+$K92*$L92*$M92,0) -> 0 | O92: =IF(+$J92=O$9,+$K92*$L92*$M92,0) -> 0 | P92: =IF(+$J92=P$9,+$K92*$L92*$M92,0) -> 0 | Q92: =IF(+$J92=Q$9,+$K92*$L92*$M92,0) -> 0 | R92: =IF(+$J92=R$9,+$K92*$L92*$M92,0) -> 0 | S92: =IF(+$J92=S$9,+$K92*$L92*$M92,0) -> 0
C95: Dientes - Acero Longitudinal
G97: 0.43 | J97: 3/8" | K97: 0 | L97: 2 | M97: =+G97+F99 -> 0.53 | N97: =IF(+$J97=N$9,+$K97*$L97*$M97,0) -> 0 | O97: =IF(+$J97=O$9,+$K97*$L97*$M97,0) -> 0 | P97: =IF(+$J97=P$9,+$K97*$L97*$M97,0) -> 0 | Q97: =IF(+$J97=Q$9,+$K97*$L97*$M97,0) -> 0 | R97: =IF(+$J97=R$9,+$K97*$L97*$M97,0) -> 0 | S97: =IF(+$J97=S$9,+$K97*$L97*$M97,0) -> 0
F99: 0.1
C100: Dientes - Acero Vertical
G102: 0.29 | J102: 3/8" | K102: 0 | L102: 2 | M102: =+G102+G104 -> 0.39 | N102: =IF(+$J102=N$9,+$K102*$L102*$M102,0) -> 0 | O102: =IF(+$J102=O$9,+$K102*$L102*$M102,0) -> 0 | P102: =IF(+$J102=P$9,+$K102*$L102*$M102,0) -> 0 | Q102: =IF(+$J102=Q$9,+$K102*$L102*$M102,0) -> 0 | R102: =IF(+$J102=R$9,+$K102*$L102*$M102,0) -> 0 | S102: =IF(+$J102=S$9,+$K102*$L102*$M102,0) -> 0
G104: 0.1
C105: Dientes - Acero Longitudinal
G107: 0.8 | J107: 3/8" | K107: 0 | L107: 2 | M107: =+G107+F109 -> 0.8 | N107: =IF(+$J107=N$9,+$K107*$L107*$M107,0) -> 0 | O107: =IF(+$J107=O$9,+$K107*$L107*$M107,0) -> 0 | P107: =IF(+$J107=P$9,+$K107*$L107*$M107,0) -> 0 | Q107: =IF(+$J107=Q$9,+$K107*$L107*$M107,0) -> 0 | R107: =IF(+$J107=R$9,+$K107*$L107*$M107,0) -> 0 | S107: =IF(+$J107=S$9,+$K107*$L107*$M107,0) -> 0
C110: Umbral terminal - Acero Transversal | F110: 0.223
G112: 0.155 | J112: 3/8" | K112: 0 | L112: 11 | M112: =+G112+G114+F110 -> 0.732 | N112: =IF(+$J112=N$9,+$K112*$L112*$M112,0) -> 0 | O112: =IF(+$J112=O$9,+$K112*$L112*$M112,0) -> 0 | P112: =IF(+$J112=P$9,+$K112*$L112*$M112,0) -> 0 | Q112: =IF(+$J112=Q$9,+$K112*$L112*$M112,0) -> 0 | R112: =IF(+$J112=R$9,+$K112*$L112*$M112,0) -> 0 | S112: =IF(+$J112=S$9,+$K112*$L112*$M112,0) -> 0
G114: 0.354
C115: Umbral terminal - Acero Longitudinal
G117: 2.3 | J117: 3/8" | K117: 0 | L117: 2 | M117: =+G117+F119+F115 -> 2.3 | N117: =IF(+$J117=N$9,+$K117*$L117*$M117,0) -> 0 | O117: =IF(+$J117=O$9,+$K117*$L117*$M117,0) -> 0 | P117: =IF(+$J117=P$9,+$K117*$L117*$M117,0) -> 0 | Q117: =IF(+$J117=Q$9,+$K117*$L117*$M117,0) -> 0 | R117: =IF(+$J117=R$9,+$K117*$L117*$M117,0) -> 0 | S117: =IF(+$J117=S$9,+$K117*$L117*$M117,0) -> 0
C120: Umbral terminal - Acero Vertical
G122: 0.285 | J122: 1/2" | K122: 0 | L122: 2 | M122: =+G122 -> 0.285 | N122: =IF(+$J122=N$9,+$K122*$L122*$M122,0) -> 0 | O122: =IF(+$J122=O$9,+$K122*$L122*$M122,0) -> 0 | P122: =IF(+$J122=P$9,+$K122*$L122*$M122,0) -> 0 | Q122: =IF(+$J122=Q$9,+$K122*$L122*$M122,0) -> 0 | R122: =IF(+$J122=R$9,+$K122*$L122*$M122,0) -> 0 | S122: =IF(+$J122=S$9,+$K122*$L122*$M122,0) -> 0
G124: 0.1
A125: Losa | B125: Losa de Fondo | C125: Acero Longitudinal
F126: 4.266
E127: 0.5 | H127: 0.5 | J127: 3/8" | K127: 0 | L127: 10 | M127: =F126+H127+E127 -> 5.266 | N127: =IF(+$J127=N$9,+$K127*$L127*$M127,0) -> 0 | O127: =IF(+$J127=O$9,+$K127*$L127*$M127,0) -> 0 | P127: =IF(+$J127=P$9,+$K127*$L127*$M127,0) -> 0 | Q127: =IF(+$J127=Q$9,+$K127*$L127*$M127,0) -> 0 | R127: =IF(+$J127=R$9,+$K127*$L127*$M127,0) -> 0 | S127: =IF(+$J127=S$9,+$K127*$L127*$M127,0) -> 0
C130: Acero Vertical | G130: 0.25
J132: 3/8" | K132: 0 | L132: 22 | M132: =F133+G130+G134 -> 2.909 | N132: =IF(+$J132=N$9,+$K132*$L132*$M132,0) -> 0 | O132: =IF(+$J132=O$9,+$K132*$L132*$M132,0) -> 0 | P132: =IF(+$J132=P$9,+$K132*$L132*$M132,0) -> 0 | Q132: =IF(+$J132=Q$9,+$K132*$L132*$M132,0) -> 0 | R132: =IF(+$J132=R$9,+$K132*$L132*$M132,0) -> 0 | S132: =IF(+$J132=S$9,+$K132*$L132*$M132,0) -> 0
F133: 2.409
G134: 0.25
B135: Uña de losa | C135: Acero Vertical
G137: 0.475 | J137: 1/2" | K137: 0 | L137: 10 | M137: =G137 -> 0.475 | N137: =IF(+$J137=N$9,+$K137*$L137*$M137,0) -> 0 | O137: =IF(+$J137=O$9,+$K137*$L137*$M137,0) -> 0 | P137: =IF(+$J137=P$9,+$K137*$L137*$M137,0) -> 0 | Q137: =IF(+$J137=Q$9,+$K137*$L137*$M137,0) -> 0 | R137: =IF(+$J137=R$9,+$K137*$L137*$M137,0) -> 0 | S137: =IF(+$J137=S$9,+$K137*$L137*$M137,0) -> 0
C140: Acero Transversal
F142: 2.34 | J142: 1/2" | K142: 0 | L142: 3 | M142: =F142 -> 2.34 | N142: =IF(+$J142=N$9,+$K142*$L142*$M142,0) -> 0 | O142: =IF(+$J142=O$9,+$K142*$L142*$M142,0) -> 0 | P142: =IF(+$J142=P$9,+$K142*$L142*$M142,0) -> 0 | Q142: =IF(+$J142=Q$9,+$K142*$L142*$M142,0) -> 0 | R142: =IF(+$J142=R$9,+$K142*$L142*$M142,0) -> 0 | S142: =IF(+$J142=S$9,+$K142*$L142*$M142,0) -> 0
A145: Camara humeda y caja de valvulas | B145: Losa de fondo | C145: Acero Longitudinal - Camara humeda
H146: =+E148 -> 0.085
J147: 3/8" | K147: 0 | L147: 9 | M147: =+E148+F148+H146 -> 1.32 | N147: =IF(+$J147=N$9,+$K147*$L147*$M147,0) -> 0 | O147: =IF(+$J147=O$9,+$K147*$L147*$M147,0) -> 0 | P147: =IF(+$J147=P$9,+$K147*$L147*$M147,0) -> 0 | Q147: =IF(+$J147=Q$9,+$K147*$L147*$M147,0) -> 0 | R147: =IF(+$J147=R$9,+$K147*$L147*$M147,0) -> 0 | S147: =IF(+$J147=S$9,+$K147*$L147*$M147,0) -> 0
E148: 0.085 | F148: 1.15
C150: Acero Transversal - Camara humeda | G150: 0.1
G152: 1.64 | J152: 3/8" | K152: 0 | L152: 6 | M152: =+G150+F154+G152 -> 1.84 | N152: =IF(+$J152=N$9,+$K152*$L152*$M152,0) -> 0 | O152: =IF(+$J152=O$9,+$K152*$L152*$M152,0) -> 0 | P152: =IF(+$J152=P$9,+$K152*$L152*$M152,0) -> 0 | Q152: =IF(+$J152=Q$9,+$K152*$L152*$M152,0) -> 0 | R152: =IF(+$J152=R$9,+$K152*$L152*$M152,0) -> 0 | S152: =IF(+$J152=S$9,+$K152*$L152*$M152,0) -> 0
F154: 0.1
C155: Acero Longitudinal - Camara seca
E156: 0.1 | H156: =+E156 -> 0.1
J157: 3/8" | K157: 0 | L157: 9 | M157: =+E156+F158+H156 -> 1.72
F158: 1.52 | N158: =IF(+$J158=N$9,+$K158*$L158*$M158,0) -> 0 | O158: =IF(+$J158=O$9,+$K158*$L158*$M158,0) -> 0 | P158: =IF(+$J158=P$9,+$K158*$L158*$M158,0) -> 0 | Q158: =IF(+$J158=Q$9,+$K158*$L158*$M158,0) -> 0 | R158: =IF(+$J158=R$9,+$K158*$L158*$M158,0) -> 0 | S158: =IF(+$J158=S$9,+$K158*$L158*$M158,0) -> 0
C160: Acero Transversal - Camara seca | G160: =F164 -> 0.1
G162: 1.64 | J162: 3/8" | K162: 0 | L162: 6 | M162: =+G162+F164+G160 -> 1.84 | N162: =IF(+$J162=N$9,+$K162*$L162*$M162,0) -> 0 | O162: =IF(+$J162=O$9,+$K162*$L162*$M162,0) -> 0 | P162: =IF(+$J162=P$9,+$K162*$L162*$M162,0) -> 0 | Q162: =IF(+$J162=Q$9,+$K162*$L162*$M162,0) -> 0 | R162: =IF(+$J162=R$9,+$K162*$L162*$M162,0) -> 0 | S162: =IF(+$J162=S$9,+$K162*$L162*$M162,0) -> 0
F164: 0.1
B165: Muro | C165: Vertedero - Horizontal
E167: 0.1 | H167: 0.1 | J167: 3/8" | K167: 0 | L167: 2 | M167: =+E167+F168 -> 1.2 | N167: =IF(+$J167=N$9,+$K167*$L167*$M167,0) -> 0 | O167: =IF(+$J167=O$9,+$K167*$L167*$M167,0) -> 0 | P167: =IF(+$J167=P$9,+$K167*$L167*$M167,0) -> 0 | Q167: =IF(+$J167=Q$9,+$K167*$L167*$M167,0) -> 0 | R167: =IF(+$J167=R$9,+$K167*$L167*$M167,0) -> 0 | S167: =IF(+$J167=S$9,+$K167*$L167*$M167,0) -> 0
F168: 1.1
C170: Vertedero - Vertical
G172: 0.66 | J172: 3/8" | K172: 0 | L172: 6 | M172: =+F174+G172 -> 0.91 | N172: =IF(+$J172=N$9,+$K172*$L172*$M172,0) -> 0 | O172: =IF(+$J172=O$9,+$K172*$L172*$M172,0) -> 0 | P172: =IF(+$J172=P$9,+$K172*$L172*$M172,0) -> 0 | Q172: =IF(+$J172=Q$9,+$K172*$L172*$M172,0) -> 0 | R172: =IF(+$J172=R$9,+$K172*$L172*$M172,0) -> 0 | S172: =IF(+$J172=S$9,+$K172*$L172*$M172,0) -> 0
F174: 0.25
C175: Acero Vertical - Camara humeda - lateral
E177: 1.15 | J177: 3/8" | K177: 0 | L177: 8 | M177: =+E177+F179+F175 -> 1.4 | N177: =IF(+$J177=N$9,+$K177*$L177*$M177,0) -> 0 | O177: =IF(+$J177=O$9,+$K177*$L177*$M177,0) -> 0 | P177: =IF(+$J177=P$9,+$K177*$L177*$M177,0) -> 0 | Q177: =IF(+$J177=Q$9,+$K177*$L177*$M177,0) -> 0 | R177: =IF(+$J177=R$9,+$K177*$L177*$M177,0) -> 0 | S177: =IF(+$J177=S$9,+$K177*$L177*$M177,0) -> 0
F179: 0.25
C180: Acero Horizontal - camara humeda - lateral | F180: =F184 -> 0.25
J182: 3/8" | K182: 0 | L182: 6 | M182: =+G183+F184+F180 -> 2.047 | N182: =IF(+$J182=N$9,+$K182*$L182*$M182,0) -> 0 | O182: =IF(+$J182=O$9,+$K182*$L182*$M182,0) -> 0 | P182: =IF(+$J182=P$9,+$K182*$L182*$M182,0) -> 0 | Q182: =IF(+$J182=Q$9,+$K182*$L182*$M182,0) -> 0 | R182: =IF(+$J182=R$9,+$K182*$L182*$M182,0) -> 0 | S182: =IF(+$J182=S$9,+$K182*$L182*$M182,0) -> 0
...

Sheet 1.9 VALV-CONTROL
B1: PLANILLA DE METRADOS DE AGUA POTABLE
B2: "CREACION DEL SERVICIO DE AGUA POTABLE RURAL Y CREACION DEL SERVICIO DE ALCANTARILLADO U OTRAS FORMAS DE DISPOSICION SANITARIA DE EXCRETAS EN EL SECTOR NUEVA ESPERANZA DE LA CC.NN. BAJO PITOCUNA DISTRITO DE RIO NEGRO, PROVINCIA DE SATIPO, DEPARTAMENTO DE JUNIN"
B3: VALVULA DE CONTROL
L4: N° | M4: ACCESORIOS | N4: UNIDAD
L5: 1 | M5: Valvula compuerta Bronce | N5: 1
L6: 2 | M6: Niple PVC L=2" | N6: 2
L7: 3 | M7: Union universal PVC | N7: 2
L8: 4 | M8: Adaptador UPR PVC | N8: 2
L9: 5 | M9: Codo PVC SP x 45° | N9: 4
L10: 6 | M10: Niple PVC L=8" | N10: 2
L11: 7 | M11: Niple PVC L=7" | N11: 2
L17: VALVULA DE CONTROL (21 und.)
B18: PARTIDA | C18: DESCRIPCION | D18: UNIDAD | E18: VECES | F18: LONGITUD | G18: ANCHO | H18: ALTURA | I18: SUB-TOTAL | J18: TOTAL
B19: ="01.09" -> 01.09 | C19: =+B3&" ("&E19&" und.)" -> VALVULA DE CONTROL (6 und.) | E19: =+SUM(E20:E21) -> 6
C20: =+$B$3&L20 -> VALVULA DE CONTROL Ø = 1" | E20: 5 | L20: Ø = 1"
C21: =+$B$3&L21 -> VALVULA DE CONTROL Ø = 3/4" | E21: 1 | L21: Ø = 3/4"
B23: =B$19 & ".01" -> 01.09.01 | C23: TRABAJOS PRELIMINARES | E23: =+$E$19 -> 6 | L23: Descripcion | M23: Medida | N23: Unidad
B24: =B$23 & ".01" -> 01.09.01.01 | C24: LIMPIEZA Y DESBROCE DE TERRENO MANUAL | D24: m2 | I24: =SUM(I25) -> 2.33 | J24: =+I24*$E$23 -> 13.98 | L24: Caja de Valvulas
C25: Caja de valvula | E25: 1 | F25: =+M43 -> 1.525 | G25: =+M42 -> 1.525 | I25: =+ROUND(PRODUCT(E25:G25),2) -> 2.33 | L25: Ancho | M25: 0.6 | N25: m
L26: Largo | M26: 0.6 | N26: m
B27: =B$23 & ".02" -> 01.09.01.02 | C27: TRAZO Y REPLANTEO PRELIMINAR PARA ESTRUCTURAS | D27: m2 | I27: =SUM(I28) -> 2.33 | J27: =+I27*$E$23 -> 13.98 | L27: Altura | M27: 0.7 | N27: m
C28: Caja de valvula | E28: 1 | F28: =+F25 -> 1.525 | G28: =+G25 -> 1.525 | I28: =+ROUND(PRODUCT(E28:G28),2) -> 2.33 | L28: Uña | M28: 0.1 | N28: m
B30: =B$23 & ".03" -> 01.09.01.03 | C30: TRAZO Y REPLANTEO DURANTE EL PROCESO PARA ESTRUCTURAS | D30: m2 | I30: =SUM(I31) -> 2.33 | J30: =+I30*$E$23 -> 13.98 | L30: Espesor de muro | M30: 0.1 | N30: m
C31: Caja de valvula | E31: 1 | F31: =+F25 -> 1.525 | G31: =+G25 -> 1.525 | I31: =+ROUND(PRODUCT(E31:G31),2) -> 2.33 | L31: Cimentacion B
L32: Largo | M32: =+M26+2*M30+2*M28 -> 1 | N32: m
B33: =B$19 & ".02" -> 01.09.02 | C33: MOVIMIENTO DE TIERRAS | E33: =+$E$19 -> 6 | L33: Ancho | M33: =+M25+2*M30+2*M28 -> 1 | N33: m
B34: =B$33 & ".01" -> 01.09.02.01 | C34: EXCAVACION MANUAL EN TERRENO NORMAL | D34: m3 | I34: =SUM(I35) -> 1.21 | J34: =+I34*$E$33 -> 7.26 | L34: Espesor de losa | M34: 0.1 | N34: m
C35: Caja de valvula | E35: 1 | F35: Volumen | H35: =+G40/6*((2*G36+G38)*G37+(2*G38+G36)*G39) -> 1.2123854 | I35: =+ROUND(PRODUCT(E35:H35),2) -> 1.21 | L35: Excavacion
F36: a | G36: =+M42 -> 1.525 | L36: Fondo
F37: b | G37: =+M43 -> 1.525 | L37: Excavacion | M37: 0.1 | N37: m
C38: Se considera 0.10m de | F38: a´ | G38: =+M38 -> 1.2 | L38: Ancho (a´) | M38: =+M33+2*M37 -> 1.2 | N38: m
C39: excavacion y talud 1:0.25 | F39: b´ | G39: =+M39 -> 1.2 | L39: Largo (b´) | M39: =+M32+2*M37 -> 1.2 | N39: m
F40: h | G40: =+M45 -> 0.65 | L40: Superior
L41: Excavacion | M41: =+M44*M45 -> 0.1625 | N41: m
L42: Ancho (a) | M42: =+M38+2*M41 -> 1.525 | N42: m
B43: =B$33 & ".02" -> 01.09.02.02 | C43: RELLENO COMPACTADO CON MATERIAL PROPIO SELECCIONADO | D43: m3 | I43: =SUM(I44:I46) -> 0.66 | J43: =+I43*$E$33 -> 3.96 | L43: Largo (b) | M43: =+M39+2*M41 -> 1.525 | N43: m
C44: Volumen de excavacion | E44: 1 | H44: =+H35 -> 1.2123854 | I44: =+ROUND(PRODUCT(E44:H44),2) -> 1.21 | L44: Talud | M44: 0.25 | N44: m
C45: Volumen de muros | E45: -1 | F45: =+M26+2*M30 -> 0.8 | G45: =+M25+2*M30 -> 0.8 | H45: =+M27 -> 0.7 | I45: =+ROUND(PRODUCT(E45:H45),2) -> -0.45 | L45: Altura (h) | M45: =+M27-M46 -> 0.65 | N45: m
C46: Volumen de losa | E46: -1 | F46: =+M33 -> 1 | G46: =+M32 -> 1 | H46: =+M34 -> 0.1 | I46: =+ROUND(PRODUCT(E46:H46),2) -> -0.1 | L46: Superficie Libre (sl) | M46: 0.05 | N46: m
L47: Filtro de piedra | M47: 0.2 | N47: m
B48: =B$33 & ".03" -> 01.09.02.03 | C48: ACARREO Y ELIMINACION DE MAT. EXCEDENTE Dmax=30 m | D48: m3 | I48: =SUM(I49:I50) -> 0.55 | J48: =+I48*$E$33 -> 3.3
C49: Excavacion - Esponjamiento 20% | E49: 1 | I49: =I34-I43 -> 0.55
B51: =B$19 & ".03" -> 01.09.03 | C51: OBRAS DE CONCRETO ARMADO | E51: =+$E$19 -> 6
B52: =B$51 & ".01" -> 01.09.03.01 | C52: CONCRETO f'c=175 kg/cm2 EN MUROS | D52: m3 | I52: =SUM(I53:I54) -> 0.196 | J52: =+I52*$E$51 -> 1.176
C53: Muro longitudinales | E53: 2 | F53: =+M25+2*M30 -> 0.8 | G53: =+M30 -> 0.1 | H53: =+$M$27 -> 0.7 | I53: =+ROUND(PRODUCT(E53:H53),3) -> 0.112
C54: Muros transversales | E54: 2 | F54: =+M25 -> 0.6 | G54: =+M30 -> 0.1 | H54: =+$M$27 -> 0.7 | I54: =+ROUND(PRODUCT(E54:H54),3) -> 0.084
B56: =B$51 & ".02" -> 01.09.03.02 | C56: CONCRETO f'c=175 kg/cm2 EN LOSA | D56: m3 | I56: =SUM(I57:I58) -> 0.064 | J56: =+I56*$E$51 -> 0.384
C57: Losa de fondo | E57: 1 | F57: 1 | G57: 1 | H57: 0.1 | I57: =+ROUND(PRODUCT(E57:H57),3) -> 0.1
C58: Descuento de Grava | E58: -1 | F58: 0.6 | G58: 0.6 | H58: 0.1 | I58: =+ROUND(PRODUCT(E58:H58),3) -> -0.036
B60: =B$51 & ".03" -> 01.09.03.03 | C60: ENCOFRADO Y DESENCOFRADO EN MUROS | D60: m2 | I60: =SUM(I61:I64) -> 3.92 | J60: =+I60*$E$51 -> 23.52
C61: Muro longitudinales cara exterior | E61: 2 | F61: =+$M$26+2*$M$30 -> 0.8 | H61: =+$M$27 -> 0.7 | I61: =+ROUND(PRODUCT(E61:H61),2) -> 1.12
C62: Muro transversal cara exterior | E62: 2 | G62: =+$M$25+2*$M$30 -> 0.8 | H62: =+$M$27 -> 0.7 | I62: =+ROUND(PRODUCT(E62:H62),2) -> 1.12
C63: Muro longitudinales cara interior | E63: 2 | F63: =+$M$26 -> 0.6 | H63: =+$M$27 -> 0.7 | I63: =+ROUND(PRODUCT(E63:H63),2) -> 0.84
C64: Muro transversal cara interior | E64: 2 | G64: =+$M$25 -> 0.6 | H64: =+$M$27 -> 0.7 | I64: =+ROUND(PRODUCT(E64:H64),2) -> 0.84
B66: =B$51 & ".04" -> 01.09.03.04 | C66: ENCOFRADO Y DESENCOFRADO EN LOSAS | D66: m2 | I66: =SUM(I67:I70) -> 0.64 | J66: =+I66*$E$51 -> 3.84
C67: Losa de fondo, longitudinal cara exterior | E67: 2 | F67: =+$M$33 -> 1 | H67: =+$M$34 -> 0.1 | I67: =+ROUND(PRODUCT(E67:H67),2) -> 0.2
C68: Losa de fondo, transversal cara exterior | E68: 2 | G68: =+$M$32 -> 1 | H68: =+$M$34 -> 0.1 | I68: =+ROUND(PRODUCT(E68:H68),2) -> 0.2
C69: Losa de fondo, longitudinal cara interior | E69: 2 | F69: =+$M$26 -> 0.6 | H69: =+$M$34 -> 0.1 | I69: =+ROUND(PRODUCT(E69:H69),2) -> 0.12
C70: Losa de fondo, transversal cara interior | E70: 2 | G70: =+$M$25 -> 0.6 | H70: =+$M$34 -> 0.1 | I70: =+ROUND(PRODUCT(E70:H70),2) -> 0.12
B72: =B$51 & ".05" -> 01.09.03.05 | C72: ACERO CORRUGADO f'y=4200 kg/cm2 G-60 | D72: kg | I72: =SUM(I73:I73) -> 25.7152 | J72: =+I72*$E$19 -> 154.2912
C73: Ver planilla de metrado de acero | E73: 1 | I73: ='1.9 M-Acero'!O231 -> 25.7152
B75: =B$19 & ".04" -> 01.09.04 | C75: REVOQUES Y ENLUCIDOS | E75: =+$E$19 -> 6
B76: =B$75 & ".01" -> 01.09.04.01 | C76: TARRAJEO INTERIOR MEZCLA C:A 1:4, e=1.5 cm | D76: m2 | I76: =SUM(I77:I80) -> 1.92 | J76: =+I76*$E$75 -> 11.52
C77: Muro longitudinales cara interior | E77: 2 | F77: =+$M$26 -> 0.6 | H77: =+$M$27 -> 0.7 | I77: =+ROUND(PRODUCT(E77:H77),2) -> 0.84
C78: Muro transversal cara interior | E78: 2 | G78: =+$M$25 -> 0.6 | H78: =+$M$27 -> 0.7 | I78: =+ROUND(PRODUCT(E78:H78),2) -> 0.84
C79: Losa de fondo, longitudinal cara interior | E79: 2 | F79: =+$M$26 -> 0.6 | H79: =+$M$34 -> 0.1 | I79: =+ROUND(PRODUCT(E79:H79),2) -> 0.12
C80: Losa de fondo, transversal cara interior | E80: 2 | G80: =+$M$25 -> 0.6 | H80: =+$M$34 -> 0.1 | I80: =+ROUND(PRODUCT(E80:H80),2) -> 0.12
B82: =B$19 & ".05" -> 01.09.05 | C82: FILTROS | E82: =+$E$19 -> 6
B83: =B$82 & ".01" -> 01.09.05.01 | C83: PIEDRA CHANCADA DE 1/2" | D83: m3 | I83: =SUM(I84) -> 0.072 | J83: =+I83*$E$82 -> 0.432
E84: 1 | F84: =+M25 -> 0.6 | G84: =+M26 -> 0.6 | H84: =+M47 -> 0.2 | I84: =+ROUND(PRODUCT(E84:H84),3) -> 0.072
B86: =B$19 & ".06" -> 01.09.06 | C86: INSTALACIONES SANITARIAS | E86: =+$E$20 -> 5
B87: =B$86 & ".01" -> 01.09.06.01 | C87: ="SUMINISTRO Y COLOC. DE ACCESORIOS EN VALVULA DE CONTROL "&L20 -> SUMINISTRO Y COLOC. DE ACCESORIOS EN VALVULA DE CONTROL Ø = 1" | D87: und | E87: =+E20 -> 5 | I87: =+ROUND(PRODUCT(E87:H87),3) -> 5 | J87: =+I87 -> 5
C88: =+M5&$L$20 -> Valvula compuerta Bronce Ø = 1" | D88: und | E88: =+N5 -> 1
C89: =+M6&$L$20 -> Niple PVC L=2" Ø = 1" | D89: und | E89: =+N6 -> 2
C90: =+M7&$L$20 -> Union universal PVC Ø = 1" | D90: und | E90: =+N7 -> 2
C91: =+M8&$L$20 -> Adaptador UPR PVC Ø = 1" | D91: und | E91: =+N8 -> 2
C92: =+M9&$L$20 -> Codo PVC SP x 45° Ø = 1" | D92: und | E92: 4
C93: =+M10&$L$20 -> Niple PVC L=8" Ø = 1" | D93: und | E93: 2
C94: =+M11&$L$20 -> Niple PVC L=7" Ø = 1" | D94: und | E94: =+N11 -> 2
B96: =B$86 & ".02" -> 01.09.06.02 | C96: ="SUMINISTRO Y COLOC. DE ACCESORIOS EN VALVULA DE CONTROL "&L21 -> SUMINISTRO Y COLOC. DE ACCESORIOS EN VALVULA DE CONTROL Ø = 3/4" | D96: und | E96: =+E21 -> 1 | I96: =+ROUND(PRODUCT(E96:H96),3) -> 1 | J96: =+I96 -> 1
C97: =+M5&$L$21 -> Valvula compuerta Bronce Ø = 3/4" | D97: und | E97: =+N5 -> 1
C98: =+M6&$L$21 -> Niple PVC L=2" Ø = 3/4" | D98: und | E98: =+N6 -> 2
C99: =+M7&$L$21 -> Union universal PVC Ø = 3/4" | D99: und | E99: =+N7 -> 2
C100: =+M8&$L$21 -> Adaptador UPR PVC Ø = 3/4" | D100: und | E100: =+N8 -> 2
C101: =+M9&$L$21 -> Codo PVC SP x 45° Ø = 3/4" | D101: und | E101: =+N9 -> 4
C102: =+M10&$L$21 -> Niple PVC L=8" Ø = 3/4" | D102: und | E102: =+N10 -> 2
C103: =+M11&$L$21 -> Niple PVC L=7" Ø = 3/4" | D103: und | E103: =+N11 -> 2
B105: =B$19 & ".07" -> 01.09.07 | C105: CARPINTERIA METALICA | E105: =+$E$19 -> 6
B106: =B$105 & ".01" -> 01.09.07.01 | C106: SUMINISTRO E INST. DE TAPA METALICA DE 0.60 x 0.60 m e=1/8" INC. ACCESORIOS + PINTURA | D106: und | E106: 1 | I106: =+ROUND(PRODUCT(E106:H106),3) -> 1 | J106: =+I106*$E$105 -> 6
E110: CARACTERISTICAS DE ACERO CORRUGADO
E111: Diametro | G111: Area (cm2) | H111: Diametro (cm) | I111: Perimetro (cm) | J111: Peso (kg/m)
E112: Pulg. | F112: mm
E113: 0.25 | F113: 6 | G113: =+PI()*H113*H113/4 -> 0.31669217 | H113: =2.54*1/4 -> 0.635 | I113: =+H113*PI() -> 1.9949113 | J113: 0.222
F114: 8 | G114: =+PI()*H114*H114/4 -> 0.50265482 | H114: 0.8 | J114: 0.4
E115: 0.375 | F115: - | G115: =+PI()*H115*H115/4 -> 0.71255739 | H115: =2.54*3/8 -> 0.9525 | I115: =+H115*PI() -> 2.992367 | J115: 0.56
F116: 12 | G116: =+PI()*H116*H116/4 -> 1.1309734 | H116: 1.2 | J116: 0.89
E117: 0.5 | F117: - | G117: =+PI()*H117*H117/4 -> 1.2667687 | H117: =1/2*2.54 -> 1.27 | I117: =+H117*PI() -> 3.9898227 | J117: 0.994
E118: 0.625 | F118: - | G118: =+PI()*H118*H118/4 -> 1.9793261 | H118: =5/8*2.54 -> 1.5875 | I118: =+H118*PI() -> 4.9872783 | J118: 1.552
E119: 0.75 | F119: - | G119: =+PI()*H119*H119/4 -> 2.8502296 | H119: =3/4*2.54 -> 1.905 | I119: =+H119*PI() -> 5.984734 | J119: 2.235
E120: 1 | F120: - | G120: =+PI()*H120*H120/4 -> 5.0670748 | H120: 2.54 | I120: =+H120*PI() -> 7.9796453 | J120: 3.973
...

Sheet 1.9 M-Acero
B3: HOJA DE METRADOS DE AGUA POTABLE
B4: "CREACION DEL SERVICIO DE AGUA POTABLE RURAL Y CREACION DEL SERVICIO DE ALCANTARILLADO U OTRAS FORMAS DE DISPOSICION SANITARIA DE EXCRETAS EN EL SECTOR NUEVA ESPERANZA DE LA CC.NN. BAJO PITOCUNA DISTRITO DE RIO NEGRO, PROVINCIA DE SATIPO, DEPARTAMENTO DE JUNIN
B7: METRADO DE VALVULA DE CONTROL
B9: =+'[26]Captación Dique'!B141 -> 0 | E9: =+'[26]Captación Dique'!C141 -> Ver Planilla de Metrados de Acero
B11: DESCRIPCION | E11: ELEMENTO | K11: Ø (Pulg.) | L11: CANTIDAD | M11: N° DE ELEMENTOS | N11: LONG. DEL ELEMENTO (m) | O11: LONGITUD (m)
O12: 1/4" | P12: 3/8" | Q12: 1/2" | R12: 5/8" | S12: 3/4" | T12: 1"
B13: CAMARA HUMEDA | C13: Muro y Losa | D13: Acero Vertical
G15: 0.95 | K15: 3/8" | L15: 4 | M15: 4 | N15: =+G15+H17 -> 1.15 | O15: =IF(+$K15=O$11,+$L15*$M15*$N15,0) -> 0 | P15: =IF(+$K15=P$12,+$L15*$M15*$N15,0) -> 18.4 | Q15: =IF(+$K15=Q$11,+$L15*$M15*$N15,0) -> 0 | R15: =IF(+$K15=R$11,+$L15*$M15*$N15,0) -> 0 | S15: =IF(+$K15=S$11,+$L15*$M15*$N15,0) -> 0 | T15: =IF(+$K15=T$11,+$L15*$M15*$N15,0) -> 0
H17: 0.2
D18: Acero Horizontal | G18: 0.2
F19: 0.2 | G19: 0.7
G20: 0.7 | I20: 0.7 | K20: 3/8" | L20: 1 | M20: 4 | N20: =+G22+I20+F19+G18+G19+G20 -> 3.2 | O20: =IF(+$K20=O$11,+$L20*$M20*$N20,0) -> 0 | P20: =IF(+$K20=P$12,+$L20*$M20*$N20,0) -> 12.8 | Q20: =IF(+$K20=Q$11,+$L20*$M20*$N20,0) -> 0 | R20: =IF(+$K20=R$11,+$L20*$M20*$N20,0) -> 0 | S20: =IF(+$K20=S$11,+$L20*$M20*$N20,0) -> 0 | T20: =IF(+$K20=T$11,+$L20*$M20*$N20,0) -> 0
G22: 0.7
D23: Losa - Acero Longitudinal y Transversal
G25: 0.92 | K25: 3/8" | L25: 4 | M25: 4 | N25: =+G25 -> 0.92 | O25: =IF(+$K25=O$11,+$L25*$M25*$N25,0) -> 0 | P25: =IF(+$K25=P$12,+$L25*$M25*$N25,0) -> 14.72 | Q25: =IF(+$K25=Q$11,+$L25*$M25*$N25,0) -> 0 | R25: =IF(+$K25=R$11,+$L25*$M25*$N25,0) -> 0 | S25: =IF(+$K25=S$11,+$L25*$M25*$N25,0) -> 0 | T25: =IF(+$K25=T$11,+$L25*$M25*$N25,0) -> 0
D28: Losa - Acero Transversal
G30: 4.44 | K30: 3/8" | L30: 0 | M30: 3 | N30: =+G30+I29+F29 -> 4.44 | O30: =IF(+$K30=O$11,+$L30*$M30*$N30,0) -> 0 | P30: =IF(+$K30=P$11,+$L30*$M30*$N30,0) -> 0 | Q30: =IF(+$K30=Q$11,+$L30*$M30*$N30,0) -> 0 | R30: =IF(+$K30=R$11,+$L30*$M30*$N30,0) -> 0 | S30: =IF(+$K30=S$11,+$L30*$M30*$N30,0) -> 0 | T30: =IF(+$K30=T$11,+$L30*$M30*$N30,0) -> 0
D33: Zapata - Acero Longitudinal
G35: 2.98 | K35: 3/8" | L35: 0 | M35: 4 | N35: =+G35 -> 2.98 | O35: =IF(+$K35=O$11,+$L35*$M35*$N35,0) -> 0 | P35: =IF(+$K35=P$11,+$L35*$M35*$N35,0) -> 0 | Q35: =IF(+$K35=Q$11,+$L35*$M35*$N35,0) -> 0 | R35: =IF(+$K35=R$11,+$L35*$M35*$N35,0) -> 0 | S35: =IF(+$K35=S$11,+$L35*$M35*$N35,0) -> 0 | T35: =IF(+$K35=T$11,+$L35*$M35*$N35,0) -> 0
D38: Zapata - Acero Transversal
G40: 4.44 | K40: 3/8" | L40: 0 | M40: 3 | N40: =+G40 -> 4.44 | O40: =IF(+$K40=O$11,+$L40*$M40*$N40,0) -> 0 | P40: =IF(+$K40=P$11,+$L40*$M40*$N40,0) -> 0 | Q40: =IF(+$K40=Q$11,+$L40*$M40*$N40,0) -> 0 | R40: =IF(+$K40=R$11,+$L40*$M40*$N40,0) -> 0 | S40: =IF(+$K40=S$11,+$L40*$M40*$N40,0) -> 0 | T40: =IF(+$K40=T$11,+$L40*$M40*$N40,0) -> 0
C43: Muro segundario | D43: Acero Vertical (interior y exterior)
G45: 1.23 | K45: 1/2" | L45: 0 | M45: 4 | N45: =+G45+H47 -> 1.33 | O45: =IF(+$K45=O$11,+$L45*$M45*$N45,0) -> 0 | P45: =IF(+$K45=P$11,+$L45*$M45*$N45,0) -> 0 | Q45: =IF(+$K45=Q$11,+$L45*$M45*$N45,0) -> 0 | R45: =IF(+$K45=R$11,+$L45*$M45*$N45,0) -> 0 | S45: =IF(+$K45=S$11,+$L45*$M45*$N45,0) -> 0 | T45: =IF(+$K45=T$11,+$L45*$M45*$N45,0) -> 0
H47: 0.1
D48: Acero Horizontal
K50: 3/8" | L50: 0 | M50: 7 | N50: =+G51 -> 0.839 | O50: =IF(+$K50=O$11,+$L50*$M50*$N50,0) -> 0 | P50: =IF(+$K50=P$11,+$L50*$M50*$N50,0) -> 0 | Q50: =IF(+$K50=Q$11,+$L50*$M50*$N50,0) -> 0 | R50: =IF(+$K50=R$11,+$L50*$M50*$N50,0) -> 0 | S50: =IF(+$K50=S$11,+$L50*$M50*$N50,0) -> 0 | T50: =IF(+$K50=T$11,+$L50*$M50*$N50,0) -> 0
G51: 0.839
D53: Zapata - Acero Longitudinal
K55: 1/2" | L55: 0 | M55: 6 | N55: =+G56 -> 0.839 | O55: =IF(+$K55=O$11,+$L55*$M55*$N55,0) -> 0 | P55: =IF(+$K55=P$11,+$L55*$M55*$N55,0) -> 0 | Q55: =IF(+$K55=Q$11,+$L55*$M55*$N55,0) -> 0 | R55: =IF(+$K55=R$11,+$L55*$M55*$N55,0) -> 0 | S55: =IF(+$K55=S$11,+$L55*$M55*$N55,0) -> 0 | T55: =IF(+$K55=T$11,+$L55*$M55*$N55,0) -> 0
G56: =+G51 -> 0.839
D58: Zapata - Acero Transversal
G60: 0.91 | K60: 1/2" | L60: 0 | M60: =+M45 -> 4 | N60: =+G60 -> 0.91 | O60: =IF(+$K60=O$11,+$L60*$M60*$N60,0) -> 0 | P60: =IF(+$K60=P$11,+$L60*$M60*$N60,0) -> 0 | Q60: =IF(+$K60=Q$11,+$L60*$M60*$N60,0) -> 0 | R60: =IF(+$K60=R$11,+$L60*$M60*$N60,0) -> 0 | S60: =IF(+$K60=S$11,+$L60*$M60*$N60,0) -> 0 | T60: =IF(+$K60=T$11,+$L60*$M60*$N60,0) -> 0
H63: 0.137
G65: 1.101 | K65: 1/2" | L65: 0 | M65: 7 | N65: =+G65+G67+H63 -> 1.488 | O65: =IF(+$K65=O$11,+$L65*$M65*$N65,0) -> 0 | P65: =IF(+$K65=P$11,+$L65*$M65*$N65,0) -> 0 | Q65: =IF(+$K65=Q$11,+$L65*$M65*$N65,0) -> 0 | R65: =IF(+$K65=R$11,+$L65*$M65*$N65,0) -> 0 | S65: =IF(+$K65=S$11,+$L65*$M65*$N65,0) -> 0 | T65: =IF(+$K65=T$11,+$L65*$M65*$N65,0) -> 0
G67: 0.25
D69: Acero Horizontal
G70: 1.26 | K70: 1/2" | L70: 0 | M70: 11 | N70: =+G70 -> 1.26 | O70: =IF(+$K70=O$11,+$L70*$M70*$N70,0) -> 0 | P70: =IF(+$K70=P$11,+$L70*$M70*$N70,0) -> 0 | Q70: =IF(+$K70=Q$11,+$L70*$M70*$N70,0) -> 0 | R70: =IF(+$K70=R$11,+$L70*$M70*$N70,0) -> 0 | S70: =IF(+$K70=S$11,+$L70*$M70*$N70,0) -> 0 | T70: =IF(+$K70=T$11,+$L70*$M70*$N70,0) -> 0
D73: Acero Vertical (Frontal) | H73: 0.2
G75: =+G70 -> 1.26 | K75: 1/2" | L75: 0 | M75: 7 | N75: =+G75+H73+H77 -> 1.96 | O75: =IF(+$K75=O$11,+$L75*$M75*$N75,0) -> 0 | P75: =IF(+$K75=P$11,+$L75*$M75*$N75,0) -> 0 | Q75: =IF(+$K75=Q$11,+$L75*$M75*$N75,0) -> 0 | R75: =IF(+$K75=R$11,+$L75*$M75*$N75,0) -> 0 | S75: =IF(+$K75=S$11,+$L75*$M75*$N75,0) -> 0 | T75: =IF(+$K75=T$11,+$L75*$M75*$N75,0) -> 0
H77: 0.5
D78: Losa sobre compuerta de cierre - Acero Longitudinal
G80: 0.695 | K80: 1/2" | L80: 0 | M80: 4 | N80: =+G80 -> 0.695 | O80: =IF(+$K80=O$11,+$L80*$M80*$N80,0) -> 0 | P80: =IF(+$K80=P$11,+$L80*$M80*$N80,0) -> 0 | Q80: =IF(+$K80=Q$11,+$L80*$M80*$N80,0) -> 0 | R80: =IF(+$K80=R$11,+$L80*$M80*$N80,0) -> 0 | S80: =IF(+$K80=S$11,+$L80*$M80*$N80,0) -> 0 | T80: =IF(+$K80=T$11,+$L80*$M80*$N80,0) -> 0
D83: Losa sobre compuerta de cierre - Acero Transversal
G85: 0.76 | K85: 1/2" | L85: 0 | M85: 5 | N85: =+G85 -> 0.76 | O85: =IF(+$K85=O$11,+$L85*$M85*$N85,0) -> 0 | P85: =IF(+$K85=P$11,+$L85*$M85*$N85,0) -> 0 | Q85: =IF(+$K85=Q$11,+$L85*$M85*$N85,0) -> 0 | R85: =IF(+$K85=R$11,+$L85*$M85*$N85,0) -> 0 | S85: =IF(+$K85=S$11,+$L85*$M85*$N85,0) -> 0 | T85: =IF(+$K85=T$11,+$L85*$M85*$N85,0) -> 0
H88: 0.2
G90: 0.2 | K90: 3/8" | L90: 0 | M90: 4 | N90: =+G90+H92+H88 -> 0.4 | O90: =IF(+$K90=O$11,+$L90*$M90*$N90,0) -> 0 | P90: =IF(+$K90=P$11,+$L90*$M90*$N90,0) -> 0 | Q90: =IF(+$K90=Q$11,+$L90*$M90*$N90,0) -> 0 | R90: =IF(+$K90=R$11,+$L90*$M90*$N90,0) -> 0 | S90: =IF(+$K90=S$11,+$L90*$M90*$N90,0) -> 0 | T90: =IF(+$K90=T$11,+$L90*$M90*$N90,0) -> 0
D93: Bloque de canal de descarga Acero Horizontal
G95: 0.1 | K95: 3/8" | L95: 0 | M95: 2 | N95: =+G95 -> 0.1 | O95: =IF(+$K95=O$11,+$L95*$M95*$N95,0) -> 0 | P95: =IF(+$K95=P$11,+$L95*$M95*$N95,0) -> 0 | Q95: =IF(+$K95=Q$11,+$L95*$M95*$N95,0) -> 0 | R95: =IF(+$K95=R$11,+$L95*$M95*$N95,0) -> 0 | S95: =IF(+$K95=S$11,+$L95*$M95*$N95,0) -> 0 | T95: =IF(+$K95=T$11,+$L95*$M95*$N95,0) -> 0
D98: Dientes - Acero Longitudinal
H100: 0.43 | K100: 3/8" | L100: 0 | M100: 2 | N100: =+H100+G102 -> 0.53 | O100: =IF(+$K100=O$11,+$L100*$M100*$N100,0) -> 0 | P100: =IF(+$K100=P$11,+$L100*$M100*$N100,0) -> 0 | Q100: =IF(+$K100=Q$11,+$L100*$M100*$N100,0) -> 0 | R100: =IF(+$K100=R$11,+$L100*$M100*$N100,0) -> 0 | S100: =IF(+$K100=S$11,+$L100*$M100*$N100,0) -> 0 | T100: =IF(+$K100=T$11,+$L100*$M100*$N100,0) -> 0
G102: 0.1
D103: Dientes - Acero Vertical
H105: 0.29 | K105: 3/8" | L105: 0 | M105: 2 | N105: =+H105+H107 -> 0.39 | O105: =IF(+$K105=O$11,+$L105*$M105*$N105,0) -> 0 | P105: =IF(+$K105=P$11,+$L105*$M105*$N105,0) -> 0 | Q105: =IF(+$K105=Q$11,+$L105*$M105*$N105,0) -> 0 | R105: =IF(+$K105=R$11,+$L105*$M105*$N105,0) -> 0 | S105: =IF(+$K105=S$11,+$L105*$M105*$N105,0) -> 0 | T105: =IF(+$K105=T$11,+$L105*$M105*$N105,0) -> 0
H107: 0.1
D108: Dientes - Acero Longitudinal
H110: 0.8 | K110: 3/8" | L110: 0 | M110: 2 | N110: =+H110+G112 -> 0.8 | O110: =IF(+$K110=O$11,+$L110*$M110*$N110,0) -> 0 | P110: =IF(+$K110=P$11,+$L110*$M110*$N110,0) -> 0 | Q110: =IF(+$K110=Q$11,+$L110*$M110*$N110,0) -> 0 | R110: =IF(+$K110=R$11,+$L110*$M110*$N110,0) -> 0 | S110: =IF(+$K110=S$11,+$L110*$M110*$N110,0) -> 0 | T110: =IF(+$K110=T$11,+$L110*$M110*$N110,0) -> 0
D113: Umbral terminal - Acero Transversal | G113: 0.223
H115: 0.155 | K115: 3/8" | L115: 0 | M115: 11 | N115: =+H115+H117+G113 -> 0.732 | O115: =IF(+$K115=O$11,+$L115*$M115*$N115,0) -> 0 | P115: =IF(+$K115=P$11,+$L115*$M115*$N115,0) -> 0 | Q115: =IF(+$K115=Q$11,+$L115*$M115*$N115,0) -> 0 | R115: =IF(+$K115=R$11,+$L115*$M115*$N115,0) -> 0 | S115: =IF(+$K115=S$11,+$L115*$M115*$N115,0) -> 0 | T115: =IF(+$K115=T$11,+$L115*$M115*$N115,0) -> 0
H117: 0.354
D118: Umbral terminal - Acero Longitudinal
H120: 2.3 | K120: 3/8" | L120: 0 | M120: 2 | N120: =+H120+G122+G118 -> 2.3 | O120: =IF(+$K120=O$11,+$L120*$M120*$N120,0) -> 0 | P120: =IF(+$K120=P$11,+$L120*$M120*$N120,0) -> 0 | Q120: =IF(+$K120=Q$11,+$L120*$M120*$N120,0) -> 0 | R120: =IF(+$K120=R$11,+$L120*$M120*$N120,0) -> 0 | S120: =IF(+$K120=S$11,+$L120*$M120*$N120,0) -> 0 | T120: =IF(+$K120=T$11,+$L120*$M120*$N120,0) -> 0
D123: Umbral terminal - Acero Vertical
H125: 0.285 | K125: 1/2" | L125: 0 | M125: 2 | N125: =+H125 -> 0.285 | O125: =IF(+$K125=O$11,+$L125*$M125*$N125,0) -> 0 | P125: =IF(+$K125=P$11,+$L125*$M125*$N125,0) -> 0 | Q125: =IF(+$K125=Q$11,+$L125*$M125*$N125,0) -> 0 | R125: =IF(+$K125=R$11,+$L125*$M125*$N125,0) -> 0 | S125: =IF(+$K125=S$11,+$L125*$M125*$N125,0) -> 0 | T125: =IF(+$K125=T$11,+$L125*$M125*$N125,0) -> 0
H127: 0.1
B128: Losa | C128: Losa de Fondo | D128: Acero Longitudinal
G129: 4.266
F130: 0.5 | I130: 0.5 | K130: 3/8" | L130: 0 | M130: 10 | N130: =G129+I130+F130 -> 5.266 | O130: =IF(+$K130=O$11,+$L130*$M130*$N130,0) -> 0 | P130: =IF(+$K130=P$11,+$L130*$M130*$N130,0) -> 0 | Q130: =IF(+$K130=Q$11,+$L130*$M130*$N130,0) -> 0 | R130: =IF(+$K130=R$11,+$L130*$M130*$N130,0) -> 0 | S130: =IF(+$K130=S$11,+$L130*$M130*$N130,0) -> 0 | T130: =IF(+$K130=T$11,+$L130*$M130*$N130,0) -> 0
D133: Acero Vertical | H133: 0.25
K135: 3/8" | L135: 0 | M135: 22 | N135: =G136+H133+H137 -> 2.909 | O135: =IF(+$K135=O$11,+$L135*$M135*$N135,0) -> 0 | P135: =IF(+$K135=P$11,+$L135*$M135*$N135,0) -> 0 | Q135: =IF(+$K135=Q$11,+$L135*$M135*$N135,0) -> 0 | R135: =IF(+$K135=R$11,+$L135*$M135*$N135,0) -> 0 | S135: =IF(+$K135=S$11,+$L135*$M135*$N135,0) -> 0 | T135: =IF(+$K135=T$11,+$L135*$M135*$N135,0) -> 0
G136: 2.409
H137: 0.25
C138: Uña de losa | D138: Acero Vertical
H140: 0.475 | K140: 1/2" | L140: 0 | M140: 10 | N140: =H140 -> 0.475 | O140: =IF(+$K140=O$11,+$L140*$M140*$N140,0) -> 0 | P140: =IF(+$K140=P$11,+$L140*$M140*$N140,0) -> 0 | Q140: =IF(+$K140=Q$11,+$L140*$M140*$N140,0) -> 0 | R140: =IF(+$K140=R$11,+$L140*$M140*$N140,0) -> 0 | S140: =IF(+$K140=S$11,+$L140*$M140*$N140,0) -> 0 | T140: =IF(+$K140=T$11,+$L140*$M140*$N140,0) -> 0
D143: Acero Transversal
G145: 2.34 | K145: 1/2" | L145: 0 | M145: 3 | N145: =G145 -> 2.34 | O145: =IF(+$K145=O$11,+$L145*$M145*$N145,0) -> 0 | P145: =IF(+$K145=P$11,+$L145*$M145*$N145,0) -> 0 | Q145: =IF(+$K145=Q$11,+$L145*$M145*$N145,0) -> 0 | R145: =IF(+$K145=R$11,+$L145*$M145*$N145,0) -> 0 | S145: =IF(+$K145=S$11,+$L145*$M145*$N145,0) -> 0 | T145: =IF(+$K145=T$11,+$L145*$M145*$N145,0) -> 0
B148: Camara humeda y caja de valvulas | C148: Losa de fondo | D148: Acero Longitudinal - Camara humeda
I149: =+F151 -> 0.085
K150: 3/8" | L150: 0 | M150: 9 | N150: =+F151+G151+I149 -> 1.32 | O150: =IF(+$K150=O$11,+$L150*$M150*$N150,0) -> 0 | P150: =IF(+$K150=P$11,+$L150*$M150*$N150,0) -> 0 | Q150: =IF(+$K150=Q$11,+$L150*$M150*$N150,0) -> 0 | R150: =IF(+$K150=R$11,+$L150*$M150*$N150,0) -> 0 | S150: =IF(+$K150=S$11,+$L150*$M150*$N150,0) -> 0 | T150: =IF(+$K150=T$11,+$L150*$M150*$N150,0) -> 0
F151: 0.085 | G151: 1.15
D153: Acero Transversal - Camara humeda | H153: 0.1
H155: 1.64 | K155: 3/8" | L155: 0 | M155: 6 | N155: =+H153+G157+H155 -> 1.84 | O155: =IF(+$K155=O$11,+$L155*$M155*$N155,0) -> 0 | P155: =IF(+$K155=P$11,+$L155*$M155*$N155,0) -> 0 | Q155: =IF(+$K155=Q$11,+$L155*$M155*$N155,0) -> 0 | R155: =IF(+$K155=R$11,+$L155*$M155*$N155,0) -> 0 | S155: =IF(+$K155=S$11,+$L155*$M155*$N155,0) -> 0 | T155: =IF(+$K155=T$11,+$L155*$M155*$N155,0) -> 0
G157: 0.1
D158: Acero Longitudinal - Camara seca
F159: 0.1 | I159: =+F159 -> 0.1
K160: 3/8" | L160: 0 | M160: 9 | N160: =+F159+G161+I159 -> 1.72
G161: 1.52 | O161: =IF(+$K161=O$11,+$L161*$M161*$N161,0) -> 0 | P161: =IF(+$K161=P$11,+$L161*$M161*$N161,0) -> 0 | Q161: =IF(+$K161=Q$11,+$L161*$M161*$N161,0) -> 0 | R161: =IF(+$K161=R$11,+$L161*$M161*$N161,0) -> 0 | S161: =IF(+$K161=S$11,+$L161*$M161*$N161,0) -> 0 | T161: =IF(+$K161=T$11,+$L161*$M161*$N161,0) -> 0
D163: Acero Transversal - Camara seca | H163: =G167 -> 0.1
H165: 1.64 | K165: 3/8" | L165: 0 | M165: 6 | N165: =+H165+G167+H163 -> 1.84 | O165: =IF(+$K165=O$11,+$L165*$M165*$N165,0) -> 0 | P165: =IF(+$K165=P$11,+$L165*$M165*$N165,0) -> 0 | Q165: =IF(+$K165=Q$11,+$L165*$M165*$N165,0) -> 0 | R165: =IF(+$K165=R$11,+$L165*$M165*$N165,0) -> 0 | S165: =IF(+$K165=S$11,+$L165*$M165*$N165,0) -> 0 | T165: =IF(+$K165=T$11,+$L165*$M165*$N165,0) -> 0
G167: 0.1
C168: Muro | D168: Vertedero - Horizontal
F170: 0.1 | I170: 0.1 | K170: 3/8" | L170: 0 | M170: 2 | N170: =+F170+G171 -> 1.2 | O170: =IF(+$K170=O$11,+$L170*$M170*$N170,0) -> 0 | P170: =IF(+$K170=P$11,+$L170*$M170*$N170,0) -> 0 | Q170: =IF(+$K170=Q$11,+$L170*$M170*$N170,0) -> 0 | R170: =IF(+$K170=R$11,+$L170*$M170*$N170,0) -> 0 | S170: =IF(+$K170=S$11,+$L170*$M170*$N170,0) -> 0 | T170: =IF(+$K170=T$11,+$L170*$M170*$N170,0) -> 0
G171: 1.1
D173: Vertedero - Vertical
H175: 0.66 | K175: 3/8" | L175: 0 | M175: 6 | N175: =+G177+H175 -> 0.91 | O175: =IF(+$K175=O$11,+$L175*$M175*$N175,0) -> 0 | P175: =IF(+$K175=P$11,+$L175*$M175*$N175,0) -> 0 | Q175: =IF(+$K175=Q$11,+$L175*$M175*$N175,0) -> 0 | R175: =IF(+$K175=R$11,+$L175*$M175*$N175,0) -> 0 | S175: =IF(+$K175=S$11,+$L175*$M175*$N175,0) -> 0 | T175: =IF(+$K175=T$11,+$L175*$M175*$N175,0) -> 0
G177: 0.25
D178: Acero Vertical - Camara humeda - lateral
F180: 1.15 | K180: 3/8" | L180: 0 | M180: 8 | N180: =+F180+G182+G178 -> 1.4 | O180: =IF(+$K180=O$11,+$L180*$M180*$N180,0) -> 0 | P180: =IF(+$K180=P$11,+$L180*$M180*$N180,0) -> 0 | Q180: =IF(+$K180=Q$11,+$L180*$M180*$N180,0) -> 0 | R180: =IF(+$K180=R$11,+$L180*$M180*$N180,0) -> 0 | S180: =IF(+$K180=S$11,+$L180*$M180*$N180,0) -> 0 | T180: =IF(+$K180=T$11,+$L180*$M180*$N180,0) -> 0
G182: 0.25
D183: Acero Horizontal - camara humeda - lateral | G183: =G187 -> 0.25
K185: 3/8" | L185: 0 | M185: 6 | N185: =+H186+G187+G183 -> 2.047 | O185: =IF(+$K185=O$11,+$L185*$M185*$N185,0) -> 0 | P185: =IF(+$K185=P$11,+$L185*$M185*$N185,0) -> 0 | Q185: =IF(+$K185=Q$11,+$L185*$M185*$N185,0) -> 0 | R185: =IF(+$K185=R$11,+$L185*$M185*$N185,0) -> 0 | S185: =IF(+$K185=S$11,+$L185*$M185*$N185,0) -> 0 | T185: =IF(+$K185=T$11,+$L185*$M185*$N185,0) -> 0
...

Sheet 1.10 CRUCE AEREO 2.50 M
A1: PLANILLA DE METRADOS DE AGUA POTABLE
A2: PROYECTO: | B2: "CREACION DEL SERVICIO DE AGUA POTABLE RURAL Y CREACION DEL SERVICIO DE ALCANTARILLADO U OTRAS FORMAS DE DISPOSICION SANITARIA DE EXCRETAS EN EL SECTOR NUEVA ESPERANZA DE LA CC.NN. BAJO PITOCUNA DISTRITO DE RIO NEGRO, PROVINCIA DE SATIPO, DEPARTAMENTO DE JUNIN"
A4: CRUCE AEREO DE CONCRETO EN ZANJAS L= 2.50 m
A5: 1.15 | B5: PASE AEREO | D5: L= | E5: 4 | H5: PLANO : | I5: AP
A7: ITEM | B7: DESCRIPCION | C7: UND | D7: CANT. | E7: DIMENSIONES | H7: PARCIAL | I7: TOTAL
E8: LARGO | F8: ANCHO | G8: ALTO
A9: 1.1 | B9: CRUCE EN ZANJAS DE VIGA DE CONCRETO ARMADO (01 UND)
A10: =+"01.10" -> 01.10 | B10: CRUCE AEREOS EN ZANJAS DE 2.5m (1 und) | D10: 1
A11: =A$10 & ".01" -> 01.10.01 | B11: TRABAJOS PRELIMINARES
A12: =A$11 & ".01" -> 01.10.01.01 | B12: LIMPIEZA Y DESBROCE DE TERRENO MANUAL | C12: m2 | I12: =SUM(H13:H13) -> 2.21
B13: PASES AEREOS, L=2.5 m | D13: 1 | E13: 3.4 | F13: 0.65 | H13: =+PRODUCT(D13:G13) -> 2.21
A15: =A$11 & ".02" -> 01.10.01.02 | B15: TRAZO Y REPLANTEO PRELIMINAR PARA ESTRUCTURAS | C15: m2 | I15: =SUM(H16:H16) -> 2.21
B16: PASES AEREOS, L=2.5 m | D16: 1 | E16: =E13 -> 3.4 | F16: =F13 -> 0.65 | H16: =+PRODUCT(D16:G16) -> 2.21
A18: =A$11 & ".03" -> 01.10.01.03 | B18: TRAZO Y REPLANTEO DURANTE EL PROCESO PARA ESTRUCTURAS | C18: m2 | I18: =SUM(H19:H19) -> 2.21
B19: PASES AEREOS, L=2.5 m | D19: 1 | E19: =E13 -> 3.4 | F19: =F13 -> 0.65 | H19: =+PRODUCT(D19:G19) -> 2.21
A21: =A$10 & ".02" -> 01.10.02 | B21: MOVIMIENTO DE TIERRAS
A22: =A$10 & ".02.01" -> 01.10.02.01 | B22: EXCAVACION MANUAL DE TERRENO NORMAL | C22: m3 | I22: =SUM(H23:H23) -> 0.9945
B23: PASES AEREOS, L=2.5 m | D23: 1 | E23: =E19 -> 3.4 | F23: 0.65 | G23: 0.45 | H23: =+PRODUCT(D23:G23) -> 0.9945
A25: =A$10& ".02.02" -> 01.10.02.02 | B25: NIVELACION INTERIOR Y APISONADO (MANUAL) | C25: m2 | I25: =SUM(H26:H26) -> 2.21
B26: PASES AEREOS, L=2.5 m | D26: 1 | E26: =E23 -> 3.4 | F26: =F23 -> 0.65 | H26: =+PRODUCT(D26:G26) -> 2.21
A28: =A$10& ".02.03" -> 01.10.02.03 | B28: RELLENO COMPACTADO CON MATERIAL PROPIO | C28: m3 | I28: =SUM(H29:H29) -> 0.102375
B29: PASES AEREOS, L=2.5 m | D29: 1 | E29: 0.65 | F29: 0.45 | G29: 0.35 | H29: =D29*E29*F29*G29 -> 0.102375
A31: =A$10& ".02.04" -> 01.10.02.04 | B31: ACARREO Y ELIMINACION DE MAT. EXCEDENTE Dmax=30 m | C31: m3 | E31: Factor esponj. | I31: =PRODUCT(D32:H32) -> 1.07055
D32: 1 | E32: 1.2 | H32: =I22-I28 -> 0.892125
A34: =A$10 & ".03" -> 01.10.03 | B34: OBRAS DE CONCRETO ARMADO
A35: =A$10 & ".03.01" -> 01.10.03.01 | B35: CONCRETO f'c = 175 Kg/cm2, EN VIGAS | C35: m3 | I35: =+SUM(H36:H36) -> 0.105
B36: PASES AEREOS, L=2.5 m | D36: 1 | E36: 2.5 | F36: 0.2 | G36: 0.2 | H36: =+PRODUCT(D36:G36)*1.05 -> 0.105
A37: =A$10 & ".03.02" -> 01.10.03.02 | B37: CONCRETO f'c = 175 Kg/cm2, EN DADOS DE ANCLAJE | C37: m3 | I37: =+SUM(H38:H38) -> 0.26325
B38: PASES AEREOS, L=2.5 m | D38: 2 | E38: 0.65 | F38: 0.45 | G38: 0.45 | H38: =PRODUCT(D38:G38) -> 0.26325
A40: =A$10 & ".03.03" -> 01.10.03.03 | B40: ENCOFRADO Y DESENCOFRADO EN VIGAS Y DADOS | C40: m2 | I40: =+SUM(H41:H44) -> 3.828
B41: PASES AEREOS, L=2.5 m | D41: 2 | E41: 2.5 | G41: 0.2 | H41: =+PRODUCT(D41:G41)*1.1 -> 1.1
D42: 1 | E42: 2.5 | F42: 0.2 | H42: =+PRODUCT(D42:G42)*1.1 -> 0.55
D43: 4 | F43: 0.65 | G43: 0.45 | H43: =+PRODUCT(D43:G43)*1.1 -> 1.287
D44: 4 | F44: 0.45 | G44: 0.45 | H44: =+PRODUCT(D44:G44)*1.1 -> 0.891
A46: =A$10 & ".03.04" -> 01.10.03.04 | B46: ACERO CORRUGADO fy=4200 kg/cm2 G-60 | C46: kg | I46: =+SUM(H47:H49) -> 23.8728
B47: PASES AEREOS, L=2.5 m
B48: Longitudinal | D48: 4 | E48: 3.5 | F48: pesoxml = | G48: 0.56 | H48: =+PRODUCT(D48:G48)*1.05 -> 8.232
B49: Estribos | D49: 28 | E49: 0.95 | F49: pesoxml = | G49: 0.56 | H49: =+PRODUCT(D49:G49)*1.05 -> 15.6408
A51: =A$10 & ".04" -> 01.10.04 | B51: SUMINISTRO E INSTALACION DE ACCESORIOS
A52: =A$10 & ".04.01" -> 01.10.04.01 | B52: SUM. E INSTALACION DE TUB. HIERRO DUCTIL DE Ø 2" | C52: ML | I52: =SUM(H53:H54) -> 3.4
B53: PASES AEREOS, L=2.5 m | C53: m
B54: Tuberia HD Ø 2" | D54: 1 | E54: 3.4 | H54: =D54*E54 -> 3.4
A57: =A$10 & ".04.02" -> 01.10.04.02 | B57: SUMINISTRO E INSTALACION DE MANGUERA HDPE NTP - ISO 4427: 2008 PE 80, PN=10, ø=44.4mm | C57: ML | I57: =SUM(H59:H60) -> 3.4
B58: PASES AEREOS, L=2.5 m | C58: m
B59: MANGUERA HDPE Ø 1 1/2" | D59: 1 | E59: 3.4 | H59: =D59*E59 -> 3.4

Sheet 1.11 TUB. ANCL. A PUENTE
A1: PLANILLA DE METRADOS DE AGUA POTABLE
A2: PROYECTO: | B2: "CREACION DEL SERVICIO DE AGUA POTABLE RURAL Y CREACION DEL SERVICIO DE ALCANTARILLADO U OTRAS FORMAS DE DISPOSICION SANITARIA DE EXCRETAS EN EL SECTOR NUEVA ESPERANZA DE LA CC.NN. BAJO PITOCUNA DISTRITO DE RIO NEGRO, PROVINCIA DE SATIPO, DEPARTAMENTO DE JUNIN"
A4: CRUCE DE TUBERIA EN PUENTE MODULAR L= 24.5 m
A5: 1.15 | B5: PASE AEREO | D5: L= | E5: 4 | H5: PLANO : | I5: AP
A7: ITEM | B7: DESCRIPCION | C7: UND | D7: CANT. | E7: DIMENSIONES | H7: PARCIAL | I7: TOTAL
E8: LARGO | F8: ANCHO | G8: ALTO
B9: CRUCE DE TUBERIA EN PUENTE L= 24.5 m (01 UND)
A10: =+"01.11" -> 01.11 | B10: CRUCE DE TUBERIA EN PUENTE MODULAR L= 24.5 m (1 und) | D10: 1
A11: =A$10 & ".01" -> 01.11.01 | B11: TRABAJOS PRELIMINARES
A12: =A$11& ".01" -> 01.11.01.01 | B12: LIMPIEZA DE TERRENO MANUAL | C12: m2 | I12: =SUM(H13:H13) -> 0.405
B13: tuberia anclada a puente L=24.5 m | D13: 1 | E13: 0.9 | F13: 0.45 | H13: =+PRODUCT(D13:G13) -> 0.405
A15: =A$11& ".02" -> 01.11.01.02 | B15: TRAZO Y REPLANTEO PRELIMINAR PARA ESTRUCTURAS | C15: m2 | I15: =SUM(H16:H16) -> 11.025
B16: tuberia anclada a puente L=24.5 m | D16: 1 | E16: 24.5 | F16: =F13 -> 0.45 | H16: =+PRODUCT(D16:G16) -> 11.025
A18: =A$11 & ".03" -> 01.11.01.03 | B18: TRAZO Y REPLANTEO DURANTE EL PROCESO PARA ESTRUCTURAS | C18: m2 | I18: =SUM(H19:H19) -> 11.025
B19: tuberia anclada a puente L=24.5 m | D19: 1 | E19: =E16 -> 24.5 | F19: =F13 -> 0.45 | H19: =+PRODUCT(D19:G19) -> 11.025
A21: =A$10 & ".02" -> 01.11.02 | B21: MOVIMIENTO DE TIERRAS
A22: =A$21 & ".01" -> 01.11.02.01 | B22: EXCAVACION MANUAL DE TERRENO NORMAL | C22: m3 | I22: =SUM(H23:H23) -> 0.324
B23: dados de concreto | D23: 2 | E23: 0.8 | F23: 0.45 | G23: 0.45 | H23: =+PRODUCT(D23:G23) -> 0.324
A25: =A$21 & ".02" -> 01.11.02.02 | B25: NIVELACION INTERIOR Y APISONADO (MANUAL) | C25: m2 | I25: =SUM(H26:H26) -> 0.72
B26: dados de concreto | D26: 2 | E26: 0.8 | F26: 0.45 | H26: =+PRODUCT(D26:G26) -> 0.72
A28: =A$21 & ".03" -> 01.11.02.03 | B28: RELLENO COMPACTADO CON MATERIAL PROPIO SELECCIONADO | C28: m3 | I28: =SUM(H29:H29) -> 0.168
B29: dados de concreto | D29: 2 | E29: 0.8 | F29: 0.3 | G29: 0.35 | H29: =D29*E29*F29*G29 -> 0.168
A31: =A$21 & ".04" -> 01.11.02.04 | B31: ACARREO Y ELIMINACION DE MAT. EXCEDENTE Dmax=30 m | C31: m3 | E31: Factor esponj. | I31: =PRODUCT(D32:H32) -> 0.1872
D32: 1 | E32: 1.2 | H32: =I22-I28 -> 0.156
A34: =A$10 & ".03" -> 01.11.03 | B34: OBRAS DE CONCRETO ARMADO
A35: =A$10 & ".03.01" -> 01.11.03.01 | B35: CONCRETO f'c = 175 Kg/cm2, EN DADOS DE ANCLAJE | C35: m3 | I35: =+SUM(H36:H36) -> 0.3402
B36: dados de concreto | D36: 2 | E36: =E23 -> 0.8 | F36: =F23 -> 0.45 | G36: =G23 -> 0.45 | H36: =+PRODUCT(D36:G36)*1.05 -> 0.3402
A38: =A$10 & ".03.02" -> 01.11.03.02 | B38: ENCOFRADO Y DESENCOFRADO EN DADOS | C38: m2 | I38: =+SUM(H39:H41) -> 2.475
B39: dados de concreto
D40: 4 | F40: 0.8 | G40: 0.45 | H40: =+PRODUCT(D40:G40)*1.1 -> 1.584
D41: 4 | F41: 0.45 | G41: 0.45 | H41: =+PRODUCT(D41:G41)*1.1 -> 0.891
A43: =A$10 & ".04" -> 01.11.04 | B43: SUMINISTRO E INSTALACION DE ACCESORIOS
A44: =A$10 & ".04.01" -> 01.11.04.01 | B44: SUMINISTRO E INSTALACION DE TUBERIA FºGº DE Ø 1 1/2" | C44: ML | I44: =SUM(H45:H45) -> 25
B45: Tuberia FºGºØ 1 1/2" | D45: 1 | E45: 25 | H45: =D45*E45 -> 25
A48: =A$10 & ".04.02" -> 01.11.04.02 | B48: SUMINISTRO E INSTALACION DE ANCLAJE A PUENTE METALICO | C48: und | D48: 8 | I48: =D48 -> 8
B49: ABRAZADERA PLANCHA e=1/8 MOLDEADA EN OBRA | C49: und | D49: 1 | H49: =D49 -> 1
B50: PERNO ∅x2" | C50: und | D50: 2 | H50: =D50 -> 2
B51: TUERCA ∅1/2" ROSCADA | C51: und | D51: 2 | H51: =D51 -> 2

Sheet 1.12 TUB. ANCL. ALCANT.
A1: PLANILLA DE METRADOS DE AGUA POTABLE
A2: PROYECTO: | B2: "CREACION DEL SERVICIO DE AGUA POTABLE RURAL Y CREACION DEL SERVICIO DE ALCANTARILLADO U OTRAS FORMAS DE DISPOSICION SANITARIA DE EXCRETAS EN EL SECTOR NUEVA ESPERANZA DE LA CC.NN. BAJO PITOCUNA DISTRITO DE RIO NEGRO, PROVINCIA DE SATIPO, DEPARTAMENTO DE JUNIN"
A4: CRUCE DE TUBERIA EN ALCANTARILLA TMC 24"
A5: 1.15 | B5: PASE AEREO | D5: L= | E5: 4 | H5: PLANO : | I5: AP
A7: ITEM | B7: DESCRIPCION | C7: UND | D7: CANT. | E7: DIMENSIONES | H7: PARCIAL | I7: TOTAL
E8: LARGO | F8: ANCHO | G8: ALTO
A9: 1.12 | B9: CRUCE DE TUBERIA EN ALCANTARILLA (01 UND)
A10: 1.12 | B10: CRUCE DE TUBERIA EN ALCANTARILLA TMC 24" (01 und) | D10: 1
A11: =A$10 & ".01" -> 1.12.01 | B11: TRABAJOS PRELIMINARES
A12: =A$11 & ".01" -> 1.12.01.01 | B12: LIMPIEZA DE TERRENO MANUAL | C12: m2 | I12: =SUM(H13:H13) -> 1.2
B13: tuberia anclada a alcantarilla TMC 24" | D13: 1 | E13: 6 | F13: 0.2 | H13: =+PRODUCT(D13:G13) -> 1.2
A15: =A$11 & ".02" -> 1.12.01.02 | B15: TRAZO Y REPLANTEO PRELIMINAR PARA ESTRUCTURAS | C15: m2 | I15: =SUM(H16:H16) -> 1.2
B16: tuberia anclada a alcantarilla TMC 24" | D16: 1 | E16: 6 | F16: =F13 -> 0.2 | H16: =+PRODUCT(D16:G16) -> 1.2
A18: =A$11 & ".03" -> 1.12.01.03 | B18: TRAZO Y REPLANTEO DURANTE EL PROCESO PARA ESTRUCTURAS | C18: m2 | I18: =SUM(H19:H19) -> 1.2
B19: tuberia anclada a alcantarilla TMC 24" | D19: 1 | E19: =E16 -> 6 | F19: =F13 -> 0.2 | H19: =+PRODUCT(D19:G19) -> 1.2
A21: =A$10 & ".02" -> 1.12.02 | B21: SUMINISTRO E INSTALACION DE ACCESORIOS
A22: =A$10 & ".02.01" -> 1.12.02.01 | B22: SUMINISTRO E INSTALACION DE TUBERIA FºGº DE Ø 1 1/2" | C22: ML | I22: =SUM(H23:H23) -> 6 | L22: 15 | M22: =L22/1.18 -> 12.711864
B23: Tuberia FºGºØ 1 1/2" | D23: 1 | E23: 6 | H23: =D23*E23 -> 6
A25: =A$10 & ".02.02" -> 1.12.02.02 | B25: SUMINISTRO E INSTALACION DE CODO FºGº DE Ø 1 1/2" | C25: UND | I25: =SUM(H26:H27) -> 4
B26: codo FºGº 90º - Ø 1 1/2" | C26: und | D26: 2 | H26: =D26 -> 2
B27: codo FºGº 45º - Ø 1 1/2" | C27: und | D27: 2 | H27: =D27 -> 2
A29: =A$10 & ".02.03" -> 1.12.02.03 | B29: SUMINISTRO E INSTALACION DE ANCLAJE A PUENTE METALICO | C29: und | D29: 6 | I29: =D29 -> 6
B30: ABRAZADERA PLANCHA e=1/8 MOLDEADA EN OBRA | C30: und | D30: 1 | H30: =D30 -> 1
B31: PERNO ∅x2" | C31: und | D31: 2 | H31: =D31 -> 2
B32: TUERCA ∅1/2" ROSCADA | C32: und | D32: 2 | H32: =D32 -> 2

Sheet 1.13 CONEX. DOMIC.
B1: METRADOS SISTEMA DE AGUA POTABLE
B2: "CREACION DEL SERVICIO DE AGUA POTABLE RURAL Y CREACION DEL SERVICIO DE ALCANTARILLADO U OTRAS FORMAS DE DISPOSICION SANITARIA DE EXCRETAS EN EL SECTOR NUEVA ESPERANZA DE LA CC.NN. BAJO PITOCUNA DISTRITO DE RIO NEGRO, PROVINCIA DE SATIPO, DEPARTAMENTO DE JUNIN"
B3: CONEXIÓNES DOMICILIARIAS
B18: PARTIDA | C18: DESCRIPCION | D18: UNIDAD | E18: VECES | F18: LONGITUD | G18: ANCHO | H18: ALTURA | I18: SUB-TOTAL | J18: TOTAL | L18: Suma Total
B19: ="01.13" -> 01.13 | C19: =+"CONEXIÓNES DOMICILIARIAS ("&E19&" Und.)" -> CONEXIÓNES DOMICILIARIAS (15 Und.) | E19: 15 | L19: =76.95*1.5 -> 115.425
C20: Longitud promedio de Acometida de Tuberia PVC Ø 1/2" CL-10 | F20: =+L19/E19 -> 7.695
B22: =B$19 & ".01" -> 01.13.01 | C22: TRABAJOS PRELIMINARES | E22: =+$E$19 -> 15
B23: =B$22 & ".01" -> 01.13.01.01 | C23: LIMPIEZA Y DESBROCE DE TERRENO MANUAL | D23: m | E23: 1 | F23: =+$F$20 -> 7.695 | I23: =+ROUND(PRODUCT(E23:H23),2) -> 7.7 | J23: =+I23*$E$22 -> 115.5
B24: =B$22 & ".02" -> 01.13.01.02 | C24: TRAZO Y REPLANTEO INICIAL PARA LINEAS DE AGUA | D24: m | E24: 1 | F24: =+$F$20 -> 7.695 | I24: =+ROUND(PRODUCT(E24:H24),2) -> 7.7 | J24: =+I24*$E$22 -> 115.5
B25: =B$22 & ".03" -> 01.13.01.03 | C25: TRAZO Y REPLANTEO FINAL PARA LINEAS DE AGUA | D25: m | E25: 1 | F25: =+$F$20 -> 7.695 | I25: =+ROUND(PRODUCT(E25:H25),2) -> 7.7 | J25: =+I25*$E$22 -> 115.5 | L25: Caja prefabricada | P25: Losa
B27: =B$19 & ".02" -> 01.13.02 | C27: MOVIMIENTO DE TIERRAS | E27: =+$E$19 -> 15 | L27: Largo | M27: 0.4 | N27: m | P27: Largo | Q27: 0.8 | R27: m
B28: =B27 & ".01" -> 01.13.02.01 | C28: EXCAVACION MANUAL EN TERRENO NORMAL DE ZANJA DE 0.50 x 0.80 m P/TUBERIA | D28: m3 | E28: 1 | I28: =+SUM(I29:I35) -> 2.82 | J28: =+I28*$E$27 -> 42.3 | L28: Ancho | M28: 0.3 | N28: m | P28: Ancho | Q28: 0.7 | R28: m
C29: Desde la tub matriz hasta la caja de registro | E29: 1 | F29: =+$F$20 -> 7.695 | G29: 0.5 | H29: 0.7 | I29: =+ROUND(PRODUCT(E29:H29),2) -> 2.69 | L29: Altura | M29: 0.3 | N29: m | P29: Altura | Q29: 0.1 | R29: m
C30: Losa | L30: Solado | M30: 0.05 | N30: m | P30: Espesor | Q30: 0.1 | R30: m
C31: Se concidera excavacion 10 cm en todo los lados, para encofrado | E31: 1 | F31: =+Q27+2*Q32 -> 1 | G31: =+Q28+2*Q32 -> 0.9 | H31: =+Q32 -> 0.1 | I31: =+ROUND(PRODUCT(E31:H31),2) -> 0.09 | L31: Excavacion | P31: Excavacion Losa
C32: Caja Prefabricada | L32: Excavacion | M32: 0.05 | N32: m | P32: Encofrado | Q32: 0.1 | R32: m
C33: Se concidera excavacion 5cm en todo los lados, para mejor colocación | E33: 1 | F33: =+M27+2*M32 -> 0.5 | G33: =+M28+2*M32 -> 0.4 | H33: =+M29-Q30 -> 0.2 | I33: =+ROUND(PRODUCT(E33:H33),2) -> 0.04
C34: Cama de apoyo | E34: 1 | F34: =+M27+2*M32 -> 0.5 | G34: =+M28+2*M32 -> 0.4 | H34: =+M30 -> 0.05 | I34: =+ROUND(PRODUCT(E34:H34),2) -> 0.01
C35: Descuento de tapa termoplastica | E35: -1 | F35: =+M27 -> 0.4 | G35: =+M28 -> 0.3 | H35: =+M30 -> 0.05 | I35: =ROUND(PRODUCT(E35:H35),2) -> -0.01
B37: =B27 & ".02" -> 01.13.02.02 | C37: REFINE Y NIVELACION DE FONDO PARA ZANJA DE 0.50 x 0.80 m P/TUBERIA | D37: m | E37: 1 | F37: =+$F$20 -> 7.695 | I37: =+ROUND(PRODUCT(E37:H37),2) -> 7.7 | J37: =+I37*$E$27 -> 115.5
B40: =B27 & ".03" -> 01.13.02.03 | C40: CAMA DE APOYO PARA TUBERIA CON MAT. PROPIO ZARANDEADO E=0.10m, A=0.50 m | D40: m | E40: 1 | F40: =+$F$20 -> 7.695 | I40: =+ROUND(PRODUCT(E40:H40),2) -> 7.7 | J40: =+I40*$E$27 -> 115.5
B42: =B27 & ".04" -> 01.13.02.04 | C42: PRIMER RELLENO COMPACTADO DE ZANJA, CON MAT. PROPIO ZARANDEADO, E=0.30m, A=0.50 m | D42: m | E42: 1 | F42: =+$F$20 -> 7.695 | I42: =+ROUND(PRODUCT(E42:H42),2) -> 7.7 | J42: =+I42*$E$27 -> 115.5
B44: =$B$27 & ".05" -> 01.13.02.05 | C44: SEGUNDO RELLENO COMPACTADO DE ZANJA CON MAT. PROPIO, E=0.40m, A=0.50 m | D44: m | E44: 1 | F44: =+$F$20 -> 7.695 | I44: =+ROUND(PRODUCT(E44:H44),2) -> 7.7 | J44: =+I44*$E$27 -> 115.5
B46: =$B$27 & ".06" -> 01.13.02.06 | C46: RELLENO CON MATERIAL PROPIO SELECCIONADO | D46: m3 | E46: 1 | F46: 0.4 | G46: 0.3 | H46: 0.1 | I46: =PRODUCT(E46:H46) -> 0.012 | J46: =+I46*$E$27 -> 0.18
B48: =$B$27 & ".07" -> 01.13.02.07 | C48: ACARREO Y ELIMINACION DE MAT. EXCEDENTE Dmax=30 m | D48: m3 | E48: diametro de tub. | G48: factor de esp. | I48: =+I49-I52 -> 0.28915778 | J48: =+I48*E27 -> 4.3373667
C49: De la acometida | E49: 0.021 | F49: 13.15 | G49: 1.2 | I49: =PRODUCT(E49:H49) -> 0.33138
C50: Relleno de camara de caja prefabricada | E50: 1 | H50: 0.038 | I50: =PRODUCT(E50:H50) -> 0.038
H51: Total | I51: =SUM(I50:I50) -> 0.038
G52: Compa. | H52: =1/0.9 -> 1.1111111 | I52: =I51*H52 -> 0.042222222
B54: =B$19 & ".03" -> 01.13.03 | C54: OBRAS DE CONCRETO SIMPLE | E54: =+$E$19 -> 15
B55: =B$54 & ".01" -> 01.13.03.01 | C55: SOLADO f'c=100 kg/cm2, e=5 cm | D55: m2 | I55: =SUM(I56:I57) -> 0.44 | J55: =+I55*$E$54 -> 6.6
C56: Losa de concreto | E56: 1 | F56: 0.7 | G56: 0.8 | I56: =+ROUND(PRODUCT(E56:H56),3) -> 0.56
C57: Descuento de tapa termoplastica | E57: -1 | F57: 0.4 | G57: 0.3 | I57: =+ROUND(PRODUCT(E57:H57),3) -> -0.12
B59: =B$54 & ".02" -> 01.13.03.02 | C59: CONCRETO f'c=140 kg/cm2 EN LOSA | D59: m3 | I59: =SUM(I60:I61) -> 0.05 | J59: =+I59*$E$54 -> 0.75
C60: Losa de concreto | E60: 1 | F60: =+Q27 -> 0.8 | G60: =+Q28 -> 0.7 | H60: =+Q30 -> 0.1 | I60: =+ROUND(PRODUCT(E60:H60),3) -> 0.056
C61: Descuento de tapa termoplastica | E61: -1 | F61: =+M27 -> 0.4 | G61: =+M28 -> 0.3 | H61: =+M30 -> 0.05 | I61: =+ROUND(PRODUCT(E61:H61),3) -> -0.006
B63: =B$54 & ".03" -> 01.13.03.03 | C63: ENCOFRADO Y DESENCOFRADO EN LOSA | D63: m2 | I63: =SUM(I64) -> 0.3 | J63: =+I63*$E$54 -> 4.5
C64: Losa | E64: 2 | F64: =+Q27+Q28 -> 1.5 | H64: =+Q30 -> 0.1 | I64: =+ROUND(PRODUCT(E64:H64),3) -> 0.3
B66: =B$19 & ".04" -> 01.13.04 | C66: SUMINISTRO E INSTALACION DE CAJA PREFABRICADA INC. ACCESESORIOS | E66: =+$E$19 -> 15
B67: =B66 & ".01" -> 01.13.04.01 | C67: SUMINISTRO E INSTALACION DE CAJA PREFABRICADA INC. ACCESESORIOS - TUB. MATRIZ 3/4" | D67: und | E67: 7 | I67: =E67 -> 7 | J67: =I67 -> 7
C68: Valvula de Paso PVC Ø = 1/2" | D68: und | E68: 1
C69: Niple PVC L=1 1/2" Ø = 1/2" | D69: und | E69: 2
C70: Union universal PVC Ø = 1/2" | D70: und | E70: 2
C71: Adaptador UPR PVC Ø = 1/2" | D71: und | E71: 2
C72: Codo PVC SP x 45° Ø = 1/2" | D72: und | E72: 1
C73: Marco y tapa termoplastica de 1/2" + llave p/cerradura magnetica | D73: und | E73: 1
C74: Caja prefabricada de 0.30 x 0.40m, f´c=140 kg/cm2 | D74: und | E74: 1
C75: Tubería PVC C-10 Ø = 1/2" | D75: m | E75: 1
C76: Abrazadera 2 cuerpos termoplastica PVC de 3/4" con salida 1/2" | D76: und | E76: 1
C77: Cinta teflon | D77: und | E77: 5
C78: Pegamento para PVC 1/4 gln | D78: und | E78: 1
B80: 01.14.04.02 | C80: SUMINISTRO E INSTALACION DE CAJA PREFABRICADA INC. ACCESESORIOS - TUB. MATRIZ 1 " | D80: und | E80: 8 | I80: =E80 -> 8 | J80: =I80 -> 8
C81: Valvula de Paso PVC Ø = 1/2" | D81: und | E81: 1
C82: Niple PVC L=1 1/2" Ø = 1/2" | D82: und | E82: 2
C83: Union universal PVC Ø = 1/2" | D83: und | E83: 2
C84: Adaptador UPR PVC Ø = 1/2" | D84: und | E84: 2
C85: Codo PVC SP x 45° Ø = 1/2" | D85: und | E85: 1
C86: Marco y tapa termoplastica de 1/2" + llave p/cerradura magnetica | D86: und | E86: 1
C87: Caja prefabricada de 0.30 x 0.40m, f´c=140 kg/cm2 | D87: und | E87: 1
C88: Tubería PVC C-10 Ø = 1/2" | D88: m | E88: 1
C89: Abrazadera 2 cuerpos termoplastica PVC de 1" con salida 1/2" | D89: und | E89: 1
C90: Cinta teflon | D90: und | E90: 5
C91: Pegamento para PVC 1/4 gln | D91: und | E91: 1
B94: =B$19 & ".05" -> 01.13.05 | C94: SUMINISTRO E INSTALACION DE TUBERIAS | E94: =+$E$19 -> 15
B95: =B94 &".01" -> 01.13.05.01 | C95: SUMINISTRO E INSTALACION DE TUBERIA PVC Ø 1/2" CL-10 | D95: m | E95: 1 | F95: =+$F$20 -> 7.695 | I95: =+ROUND(PRODUCT(E95:H95),2) -> 7.7 | J95: =+I95*E94 -> 115.5
B96: =B94 &".02" -> 01.13.05.02 | C96: PRUEBA HIDRÁULICA Y DESINFECCIÓN DE LA TUBERÍA | D96: m | E96: 1 | F96: =+$F$20 -> 7.695 | I96: =+ROUND(PRODUCT(E96:H96),2) -> 7.7 | J96: =+I96*E94 -> 115.5

Sheet 1.14 LAV. DOMIC.
A2: PLANILLA DE METRADOS DE AGUA POTABLE
A3: "CREACION DEL SERVICIO DE AGUA POTABLE RURAL Y CREACION DEL SERVICIO DE ALCANTARILLADO U OTRAS FORMAS DE DISPOSICION SANITARIA DE EXCRETAS EN EL SECTOR NUEVA ESPERANZA DE LA CC.NN. BAJO PITOCUNA DISTRITO DE RIO NEGRO, PROVINCIA DE SATIPO, DEPARTAMENTO DE JUNIN"
A6: LAVADERO MULTIUSO PARA VIVIENDAS PARA VIVIENDAS CON UBS
A21: PARTIDA | B21: DESCRIPCION | C21: UNIDAD | D21: VECES | E21: LONGITUD | F21: ANCHO | G21: ALTURA | H21: SUB-TOTAL | I21: TOTAL
A22: =+"01.14" -> 01.14 | B22: =+"LAVADERO MULTIUSO PARA VIVIENDAS DOMICILIARIAS ("&+D22&" Und.)" -> LAVADERO MULTIUSO PARA VIVIENDAS DOMICILIARIAS (13 Und.) | D22: =D23 -> 13
A23: =A$22 & ".01" -> 01.14.01 | B23: TRABAJOS PRELIMINARES | D23: 13 | K23: LAVADERO MULTIUSO PARA VIVIENDAS CON UBS (14 Und.)
A24: =$A$23 & ".01" -> 01.14.01.01 | B24: LIMPIEZA Y DESBROCE DE TERRENO MANUAL | C24: M2 | H24: =SUM(H25:H27) -> 4.01 | I24: =H24*$D$23 -> 52.13
B25: Tuberia de agua potable 1/2" | D25: 1 | H25: 1.29
B26: Tubería de desagüe 2" | D26: 1 | H26: 2
B27: Lavadero | D27: 1 | E27: 1.2 | F27: 0.6 | H27: =+ROUND(PRODUCT(D27:G27),2) -> 0.72
A29: =$A$23 & ".02" -> 01.14.01.02 | B29: TRAZO Y REPLANTEO PRELIMINAR DE ESTRUCTURAS | C29: M2 | H29: =SUM(H30:H32) -> 4.01 | I29: =H29*$D$23 -> 52.13
B30: Tuberia de agua potable 1/2" | D30: 1 | H30: 1.29
B31: Tubería de desagüe 2" | D31: 1 | H31: 2
B32: Lavadero | D32: 1 | E32: =E27 -> 1.2 | F32: =F27 -> 0.6 | H32: =+ROUND(PRODUCT(D32:G32),2) -> 0.72
A34: =$A$23 & ".03" -> 01.14.01.03 | B34: TRAZO Y REPLANTEO DURANTE EL PROCESO PARA ESTRUCTURAS | C34: M2 | H34: =SUM(H35:H37) -> 4.01 | I34: =H34*$D$23 -> 52.13
B35: Tuberia de agua potable 1/2" | D35: 1 | H35: 1.29
B36: Tubería de desagüe 2" | D36: 1 | H36: 2
B37: Lavadero | D37: 1 | E37: =E32 -> 1.2 | F37: =F32 -> 0.6 | H37: =+ROUND(PRODUCT(D37:G37),2) -> 0.72
A39: =A$22 & ".02" -> 01.14.02 | B39: MOVIMIENTO DE TIERRAS | D39: =+$D$22 -> 13
A40: =$A$39 & ".01" -> 01.14.02.01 | B40: EXCAVACIÓN MANUAL EN TERRENO NORMAL | C40: m3 | H40: =SUM(H41:H44) -> 2.12 | I40: =H40*$D$39 -> 27.56
B41: Tuberia de agua potable 1/2" | D41: 1 | H41: =+ROUND(PRODUCT(D41:G41),2) -> 1
B42: Tubería de desagüe 2" | D42: 1 | H42: =+ROUND(PRODUCT(D42:G42),2) -> 1
B43: Lavadero- cimiento | D43: 2 | E43: 0.25 | F43: 0.65 | G43: 0.2 | H43: =+ROUND(PRODUCT(D43:G43),2) -> 0.07
B44: Lavadero cimiento | D44: 1 | E44: 0.8 | F44: 0.65 | G44: 0.1 | H44: =+ROUND(PRODUCT(D44:G44),2) -> 0.05
A46: =$A$39 & ".02" -> 01.14.02.02 | B46: RELLENO COMPACTADO CON MATERIAL PROPIO SELECCIONADO | C46: m3 | H46: =SUM(H47:H49) -> 2.07 | I46: =H46*$D$39 -> 26.91
B47: Tuberia de agua potable 1/2" | D47: =D41 -> 1 | H47: =+ROUND(PRODUCT(D47:G47),2) -> 1
B48: Tubería de desagüe 2" | D48: =D47 -> 1 | H48: =+ROUND(PRODUCT(D48:G48),2) -> 1
B49: Cimentacion -Lavadero | D49: 2 | E49: =E43 -> 0.25 | F49: =F43 -> 0.65 | G49: =G43 -> 0.2 | H49: =+ROUND(PRODUCT(D49:G49),2) -> 0.07
A51: =$A$39 & ".03" -> 01.14.02.03 | B51: ACARREO Y ELIMINACION DE MAT. EXCEDENTE Dmax=30 m | C51: m3 | H51: =SUM(H52:H53) -> 0.98 | I51: =H51*$D$39 -> 12.74
B52: Excavacion - Esponjamiento 20% | D52: 1 | E52: 1.2 | F52: Volumen | G52: =1.2*H40 -> 2.544 | H52: =+ROUND(PRODUCT(D52:G52),2) -> 3.05
B53: Relleno | D53: -1 | E53: 1 | F53: Volumen | G53: =+H46 -> 2.07 | H53: =+ROUND(PRODUCT(D53:G53),2) -> -2.07
A55: =A$22 & ".03" -> 01.14.03 | B55: OBRAS DE CONCRETO SIMPLE | D55: =+$D$22 -> 13
A56: =$A$55 & ".01" -> 01.14.03.01 | B56: CONCRETO CICLOPEO 1:10 + 30% PM EN CIMIENTO | C56: m3 | H56: =SUM(H57:H57) -> 0.07 | I56: =H56*$D$55 -> 0.91
B57: Cimentacion lavadero | D57: 2 | E57: =+E43 -> 0.25 | F57: 0.7 | G57: =+G43 -> 0.2 | H57: =+ROUND(PRODUCT(D57:G57),2) -> 0.07
A59: =A$22 & ".04" -> 01.14.04 | B59: OBRAS DE CONCRETO ARMADO | D59: =+$D$22 -> 13
A60: =$A$59 & ".01" -> 01.14.04.01 | B60: CONCRETO f'c = 175 kg/cm2 EN MURO | C60: m3 | H60: =SUM(H61:H66) -> 0.43 | I60: =H60*$D$59 -> 5.59
B61: Lavadero - Muro Frontal | D61: 2 | E61: 1.2 | F61: 0.08 | G61: 0.25 | H61: =+ROUND(PRODUCT(D61:G61),2) -> 0.05
B62: Descuento Lavadero cajon | D62: 1 | E62: area = | F62: 0.52 | G62: 0.564 | H62: =+ROUND(PRODUCT(D62:G62),2) -> 0.29
B63: Lavadero - Muro lateral de medio | D63: 1 | E63: 0.08 | F63: 0.44 | G63: 0.25 | H63: =+ROUND(PRODUCT(D63:G63),2) -> 0.01
B64: Lavadero - Muro lateral Posterior | D64: 1 | E64: 0.08 | F64: 0.44 | G64: 0.3 | H64: =+ROUND(PRODUCT(D64:G64),2) -> 0.01
B65: Lavadero - Muro lateral | D65: 1 | E65: 0.08 | F65: 0.44 | G65: 0.25 | H65: =+ROUND(PRODUCT(D65:G65),2) -> 0.01
B66: Muros de posterior | D66: 1 | E66: =E61 -> 1.2 | F66: 0.08 | G66: 0.67 | H66: =+ROUND(PRODUCT(D66:G66),2) -> 0.06
A68: =$A$59 & ".02" -> 01.14.04.02 | B68: CONCRETO f'c = 175 kg/cm2 EN LOSA | C68: m3 | H68: =SUM(H69:H70) -> 0.08 | I68: =H68*D59 -> 1.04
B69: Losa Fondo de Lavadero | D69: 1 | E69: 1.2 | F69: 0.6 | G69: 0.08 | H69: =+ROUND(PRODUCT(D69:G69),2) -> 0.06
B70: Lavadero - Losa techo cajon inclinado | D70: 1 | E70: 0.4528 | F70: 0.52 | G70: 0.08 | H70: =+ROUND(PRODUCT(D70:G70),2) -> 0.02
A72: =$A$59 & ".03" -> 01.14.04.03 | B72: ENCOFRADO Y DESENCOFRADO / PARA LAVADEROS EN MURO | C72: m2 | H72: =SUM(H73:H78) -> 2.688 | I72: =H72*$D$59 -> 34.944
B73: Muro frontal - cara interior | D73: 1 | E73: 0.67 | G73: =G61 -> 0.25 | H73: =+ROUND(PRODUCT(D73:G73),3) -> 0.168
B74: Muro frontal - cara exterior | D74: 1 | E74: 0.83 | G74: =G61 -> 0.25 | H74: =+ROUND(PRODUCT(D74:G74),3) -> 0.208
B75: Muro posterior - cara interior y exterior | D75: 2 | E75: =E32 -> 1.2 | G75: =G66 -> 0.67 | H75: =+ROUND(PRODUCT(D75:G75),3) -> 1.608
B76: Muro Latreal derecho - cara interior y exterior | D76: 2 | F76: 0.44 | G76: 0.25 | H76: =+ROUND(PRODUCT(D76:G76),3) -> 0.22
B77: Muro Latreal Medio - cara interior y exterior | D77: 2 | F77: 0.44 | G77: 0.25 | H77: =+ROUND(PRODUCT(D77:G77),3) -> 0.22
B78: Muro Latreal isquierdo - cara interior y exterior | D78: 2 | F78: 0.44 | G78: 0.3 | H78: =+ROUND(PRODUCT(D78:G78),3) -> 0.264
A80: =$A$59 & ".04" -> 01.14.04.04 | B80: ENCOFRADO Y DESENCOFRADO / PARA LAVADEROS EN LOSA | C80: m2 | H80: =SUM(H81:H86) -> 0.632 | I80: =H80*$D$59 -> 8.216
B81: Losa frontal - cara exterior | D81: 2 | E81: 1.2 | G81: 0.08 | H81: =+ROUND(PRODUCT(D81:G81),3) -> 0.192
B82: Losa - cara horizontal exterior | D82: 2 | E82: 1.2 | G82: 0.08 | H82: =+ROUND(PRODUCT(D82:G82),3) -> 0.192
B83: Losa - cara lateral exterior | D83: 2 | F83: 0.6 | G83: 0.08 | H83: =+ROUND(PRODUCT(D83:G83),3) -> 0.096
B84: Losa techo- cara inferior | D84: 1 | E84: 0.2918 | F84: 0.52 | H84: =+ROUND(PRODUCT(D84:G84),3) -> 0.152
A87: =$A$59 & ".05" -> 01.14.04.05 | B87: ACERO CORRUGADO f'y=4200 kg/cm2 G-60 | C87: kg | H87: =+H88 -> 12.046697 | I87: =H87*$D$59 -> 156.60706
B88: Ver planilla de metrado de acero | D88: 1 | H88: ='1.14 M- ACERO LAV.'!O243 -> 12.046697
A90: =A$22 & ".05" -> 01.14.05 | B90: ALBAÑILERIA | D90: =+$D$22 -> 13
A91: =$A$90&".01" -> 01.14.05.01 | B91: MURO DE LADRILLO KK 18 HUECOS INDUSTRIAL DE SOGA , C:A:1:4, e=1.50 cm | C91: m2 | H91: =SUM(H92:H93) -> 1.04 | I91: =H91*D90 -> 13.52
B92: Soporte Lavadero | D92: 2 | F92: 0.65 | G92: 0.5 | H92: =+ROUND(PRODUCT(D92:G92),2) -> 0.65
B93: Cimiento de lavadero | D93: 2 | F93: 0.65 | G93: 0.3 | H93: =+ROUND(PRODUCT(D93:G93),2) -> 0.39
A95: =A$22 & ".06" -> 01.14.06 | B95: REVOQUES Y ENLUCIDOS | D95: =+$D$22 -> 13
A96: =$A$95 & ".01" -> 01.14.06.01 | B96: TARRAJEO CON IMPERMEABILIZANTE PULIDO C:A 1:2 / PARA LAVADEROS DOMICILIARIOS | C96: m2 | H96: =SUM(H97:H102) -> 1.27 | I96: =H96*$D$39 -> 16.51
B97: Muro frontal y posterior - cara interior | D97: 2 | E97: 0.67 | G97: 0.25 | H97: =+ROUND(PRODUCT(D97:G97),2) -> 0.34
B98: Muro posterior - cara lateral | D98: 2 | F98: 0.44 | G98: 0.25 | H98: =+ROUND(PRODUCT(D98:G98),2) -> 0.22
B99: Losa - cara superior | D99: 1 | E99: 0.67 | F99: 0.44 | H99: =+ROUND(PRODUCT(D99:G99),2) -> 0.29
B100: Losa techo cajon - cara superior | D100: 1 | E100: 0.4528 | F100: 0.52 | G100: . | H100: =+ROUND(PRODUCT(D100:G100),2) -> 0.24
B101: Muro frontal- cara superior | D101: =+D73 -> 1 | E101: 1.2 | F101: 0.08 | H101: =+ROUND(PRODUCT(D101:G101),2) -> 0.1
B102: Muro lateral - cara superior | D102: 2 | E102: 0.08 | F102: 0.52 | H102: =+ROUND(PRODUCT(D102:G102),2) -> 0.08
A104: =$A$95 & ".02" -> 01.14.06.02 | B104: TARRAJEO EXTERIOR MEZCLA C:A 1:4, e=1.5 cm / PARA LAVADEROS | C104: m2 | H104: =SUM(H105:H111) -> 2.42 | I104: =H104*$D$59 -> 31.46
B105: Muro frontal - cara exterior | D105: 1 | E105: 0.83 | G105: 0.25 | H105: =+ROUND(PRODUCT(D105:G105),2) -> 0.21
B106: Muro lateral - cara exterior | D106: 2 | F106: 0.6 | G106: 0.25 | H106: =+ROUND(PRODUCT(D106:G106),2) -> 0.3
B107: Losa - cara frontal exterior | D107: 2 | E107: 1.2 | G107: 0.08 | H107: =+ROUND(PRODUCT(D107:G107),2) -> 0.19
B108: Losa - cara lateral exterior | D108: 2 | F108: 0.6 | G108: 0.08 | H108: =+ROUND(PRODUCT(D108:G108),2) -> 0.1
B109: Muro frontal - cara exterior | D109: 1 | E109: 0.08 | G109: 0.3 | H109: =+ROUND(PRODUCT(D109:G109),2) -> 0.02
B110: Zoporte laterales - cara interior y exterior | D110: 4 | F110: 0.65 | G110: 0.5 | H110: =+ROUND(PRODUCT(D110:G110),2) -> 1.3
B111: Zoporte laterales - cara frontal y posterior | D111: 4 | E111: 0.15 | G111: 0.5 | H111: =+ROUND(PRODUCT(D111:G111),2) -> 0.3
A113: =A$22 & ".07" -> 01.14.07 | B113: INSTALACIONES SANITARIAS | D113: =+$D$22 -> 13
A114: =$A$113 & ".01" -> 01.14.07.01 | B114: SUMINISTRO Y COLOC. DE ACCESORIOS EN LAVADERO DOMICILIARIO | C114: und | D114: 1 | H114: =+D114 -> 1 | I114: =H114*$D$113 -> 13
B115: Instalaciones de agua
B116: Codo PVC SP x 90° Ø = 1/2" | C116: und | D116: 2
B117: Codo F°G° x 90° Ø = 1/2" | C117: und | D117: 1
B118: Grifo de Bronce Ø = 1/2" | C118: und | D118: 1
B119: TEE PVC 1/2" | C119: und | D119: 1
B120: Adaptador UPR PVC 1/2" | C120: und | D120: 1
B121: Tuberia PVC SP C-10-1/2" | C121: m | D121: 10
B122: Cinta teflon | C122: und | D122: 5
B123: Pegamento para PVC 1/4 gln | C123: und | D123: 1
B125: Instalaciones de desague
B126: Sumidero de Bronce Ø = 2" | C126: und | D126: 1
B127: Trampa PVC SAL Ø = 2" | C127: und | D127: 1
B128: Codo PVC SAL x 90° Ø = 2" | C128: und | D128: 2
B129: Tubería PVC NTP 399.003 CLASE LIVIANA Ø = 2" | C129: m | D129: 5
D135: CARACTERISTICAS DE ACERO CORRUGADO
D136: Diametro | F136: Area (cm2) | G136: Diametro (cm) | H136: Perimetro (cm) | I136: Peso (kg/m)
D137: Pulg. | E137: mm
D138: 0.25 | E138: 6 | F138: =+PI()*G138*G138/4 -> 0.31669217 | G138: =2.54*1/4 -> 0.635 | H138: =+G138*PI() -> 1.9949113 | I138: 0.222
E139: 8 | F139: =+PI()*G139*G139/4 -> 0.50265482 | G139: 0.8 | I139: 0.4
...

Sheet 1.14 M- ACERO LAV.
B3: RESUMEN DE METRADOS DE AGUA POTABLE
B4: "CREACION DEL SERVICIO DE AGUA POTABLE RURAL Y CREACION DEL SERVICIO DE ALCANTARILLADO U OTRAS FORMAS DE DISPOSICION SANITARIA DE EXCRETAS EN EL SECTOR NUEVA ESPERANZA DE LA CC.NN. BAJO PITOCUNA DISTRITO DE RIO NEGRO, PROVINCIA DE SATIPO, DEPARTAMENTO DE JUNIN"
B7: METRADO DE ACERO DE LAVADERO MULTIUSO VIVIENDAS
B9: ='1.14 LAV. DOMIC.'!D22 -> 13 | E9: =+'[26]Captación Dique'!C143 -> REVOQUES Y ENLUCIDOS
B11: DESCRIPCION | E11: ELEMENTO | K11: Ø (Pulg.) | L11: CANTIDAD | M11: N° DE ELEMENTOS | N11: LONG. DEL ELEMENTO (m) | O11: LONGITUD (m)
O12: 1/4" | P12: 3/8" | Q12: 1/2" | R12: 5/8" | S12: 3/4" | T12: 1"
B13: LAVADERO | C13: MURO | D13: Acero Vertical frontal | G13: 0.05
H15: 0.2763 | K15: 1/4" | L15: 1 | M15: 6 | N15: =+H15+G17+G13 -> 0.4263 | O15: =IF(+$K15=O$12,+$L15*$M15*$N15,0) -> 2.5578 | P15: =IF(+$K15=P$12,+$L15*$M15*$N15,0) -> 0 | Q15: =IF(+$K15=Q$12,+$L15*$M15*$N15,0) -> 0 | R15: =IF(+$K15=R$12,+$L15*$M15*$N15,0) -> 0 | S15: =IF(+$K15=S$12,+$L15*$M15*$N15,0) -> 0 | T15: =IF(+$K15=T$12,+$L15*$M15*$N15,0) -> 0
G17: 0.1
D18: Acero Horizontal frontal
K20: 1/4" | L20: 1 | M20: 3 | N20: 1.3 | O20: =IF(+$K20=O$12,+$L20*$M20*$N20,0) -> 3.9 | P20: =IF(+$K20=P$12,+$L20*$M20*$N20,0) -> 0 | Q20: =IF(+$K20=Q$12,+$L20*$M20*$N20,0) -> 0 | R20: =IF(+$K20=R$12,+$L20*$M20*$N20,0) -> 0 | S20: =IF(+$K20=S$12,+$L20*$M20*$N20,0) -> 0 | T20: =IF(+$K20=T$12,+$L20*$M20*$N20,0) -> 0
G21: 1.15
D23: Respaldo Lavadero - Acero Longitudinal
F25: 0.075 | I25: 0.075 | K25: 1/4" | L25: 1 | M25: 5 | N25: =+G26 -> 0.865 | O25: =IF(+$K25=O$12,+$L25*$M25*$N25,0) -> 4.325 | P25: =IF(+$K25=P$12,+$L25*$M25*$N25,0) -> 0 | Q25: =IF(+$K25=Q$12,+$L25*$M25*$N25,0) -> 0 | R25: =IF(+$K25=R$12,+$L25*$M25*$N25,0) -> 0 | S25: =IF(+$K25=S$12,+$L25*$M25*$N25,0) -> 0 | T25: =IF(+$K25=T$12,+$L25*$M25*$N25,0) -> 0
G26: 0.865
D28: Respaldo Lavadero - Acero vertical
G30: 0.6955 | K30: 1/4" | L30: 1 | M30: 6 | N30: =I29+G30 -> 0.6955 | O30: =IF(+$K30=O$12,+$L30*$M30*$N30,0) -> 4.173 | P30: =IF(+$K30=P$12,+$L30*$M30*$N30,0) -> 0 | Q30: =IF(+$K30=Q$12,+$L30*$M30*$N30,0) -> 0 | R30: =IF(+$K30=R$12,+$L30*$M30*$N30,0) -> 0 | S30: =IF(+$K30=S$12,+$L30*$M30*$N30,0) -> 0 | T30: =IF(+$K30=T$12,+$L30*$M30*$N30,0) -> 0
D33: Muero medio - Acero lateral
F34: 0.08 | I34: 0.08
G35: 0.63 | K35: 1/4" | L35: 1 | M35: 3 | N35: =+G35+I34+F34 -> 0.79 | O35: =IF(+$K35=O$12,+$L35*$M35*$N35,0) -> 2.37 | P35: =IF(+$K35=P$12,+$L35*$M35*$N35,0) -> 0 | Q35: =IF(+$K35=Q$12,+$L35*$M35*$N35,0) -> 0 | R35: =IF(+$K35=R$12,+$L35*$M35*$N35,0) -> 0 | S35: =IF(+$K35=S$12,+$L35*$M35*$N35,0) -> 0 | T35: =IF(+$K35=T$12,+$L35*$M35*$N35,0) -> 0
D38: Muro medio Lateral - Acero Vertical | H38: 0.075
G40: 0.2793 | K40: 1/4" | L40: 1 | M40: 5 | N40: 0.44 | O40: =IF(+$K40=O$12,+$L40*$M40*$N40,0) -> 2.2 | P40: =IF(+$K40=P$12,+$L40*$M40*$N40,0) -> 0 | Q40: =IF(+$K40=Q$12,+$L40*$M40*$N40,0) -> 0 | R40: =IF(+$K40=R$12,+$L40*$M40*$N40,0) -> 0 | S40: =IF(+$K40=S$12,+$L40*$M40*$N40,0) -> 0 | T40: =IF(+$K40=T$12,+$L40*$M40*$N40,0) -> 0
H42: 0.075
D43: Lateral - Acero Horizontal
G45: 0.63 | K45: 1/4" | L45: 2 | M45: 4 | N45: =+G45 -> 0.63 | O45: =IF(+$K45=O$12,+$L45*$M45*$N45,0) -> 5.04 | P45: =IF(+$K45=P$12,+$L45*$M45*$N45,0) -> 0 | Q45: =IF(+$K45=Q$12,+$L45*$M45*$N45,0) -> 0 | R45: =IF(+$K45=R$12,+$L45*$M45*$N45,0) -> 0 | S45: =IF(+$K45=S$12,+$L45*$M45*$N45,0) -> 0 | T45: =IF(+$K45=T$12,+$L45*$M45*$N45,0) -> 0
D48: Lateral - Acero Vertical
G50: 0.338 | K50: 1/4" | L50: 2 | M50: 5 | N50: =+G50+G52 -> 0.438 | O50: =IF(+$K50=O$12,+$L50*$M50*$N50,0) -> 4.38 | P50: =IF(+$K50=P$12,+$L50*$M50*$N50,0) -> 0 | Q50: =IF(+$K50=Q$12,+$L50*$M50*$N50,0) -> 0 | R50: =IF(+$K50=R$11,+$L50*$M50*$N50,0) -> 0 | S50: =IF(+$K50=S$11,+$L50*$M50*$N50,0) -> 0 | T50: =IF(+$K50=T$11,+$L50*$M50*$N50,0) -> 0
G52: 0.1
C53: Muro segundario | D53: Acero Vertical (interior y exterior)
G56: 1.23 | K56: 1/2" | L56: 0 | M56: 4 | N56: =+G56+H58+G54 -> 1.33 | O56: =IF(+$K56=O$12,+$L56*$M56*$N56,0) -> 0 | P56: =IF(+$K56=P$12,+$L56*$M56*$N56,0) -> 0 | Q56: =IF(+$K56=Q$12,+$L56*$M56*$N56,0) -> 0 | R56: =IF(+$K56=R$12,+$L56*$M56*$N56,0) -> 0 | S56: =IF(+$K56=S$12,+$L56*$M56*$N56,0) -> 0 | T56: =IF(+$K56=T$12,+$L56*$M56*$N56,0) -> 0
H58: 0.1
D60: Acero Horizontal
K62: 3/8" | L62: 0 | M62: 7 | N62: =+G63 -> 0.839 | O62: =IF(+$K62=O$12,+$L62*$M62*$N62,0) -> 0 | P62: =IF(+$K62=P$12,+$L62*$M62*$N62,0) -> 0 | Q62: =IF(+$K62=Q$12,+$L62*$M62*$N62,0) -> 0 | R62: =IF(+$K62=R$12,+$L62*$M62*$N62,0) -> 0 | S62: =IF(+$K62=S$12,+$L62*$M62*$N62,0) -> 0 | T62: =IF(+$K62=T$12,+$L62*$M62*$N62,0) -> 0
G63: 0.839
D65: Zapata - Acero Longitudinal
K67: 1/2" | L67: 0 | M67: 6 | N67: =+G68 -> 0.839 | O67: =IF(+$K67=O$12,+$L67*$M67*$N67,0) -> 0 | P67: =IF(+$K67=P$12,+$L67*$M67*$N67,0) -> 0 | Q67: =IF(+$K67=Q$12,+$L67*$M67*$N67,0) -> 0 | R67: =IF(+$K67=R$12,+$L67*$M67*$N67,0) -> 0 | S67: =IF(+$K67=S$12,+$L67*$M67*$N67,0) -> 0 | T67: =IF(+$K67=T$12,+$L67*$M67*$N67,0) -> 0
G68: =+G63 -> 0.839
D70: Zapata - Acero Transversal
G72: 0.91 | K72: 1/2" | L72: 0 | M72: =+M56 -> 4 | N72: =+G72 -> 0.91 | O72: =IF(+$K72=O$12,+$L72*$M72*$N72,0) -> 0 | P72: =IF(+$K72=P$12,+$L72*$M72*$N72,0) -> 0 | Q72: =IF(+$K72=Q$12,+$L72*$M72*$N72,0) -> 0 | R72: =IF(+$K72=R$12,+$L72*$M72*$N72,0) -> 0 | S72: =IF(+$K72=S$12,+$L72*$M72*$N72,0) -> 0 | T72: =IF(+$K72=T$12,+$L72*$M72*$N72,0) -> 0
H75: 0.137
G77: 1.101 | K77: 1/2" | L77: 0 | M77: 7 | N77: =+G77+G79+H75 -> 1.488 | O77: =IF(+$K77=O$12,+$L77*$M77*$N77,0) -> 0 | P77: =IF(+$K77=P$12,+$L77*$M77*$N77,0) -> 0 | Q77: =IF(+$K77=Q$12,+$L77*$M77*$N77,0) -> 0 | R77: =IF(+$K77=R$12,+$L77*$M77*$N77,0) -> 0 | S77: =IF(+$K77=S$12,+$L77*$M77*$N77,0) -> 0 | T77: =IF(+$K77=T$12,+$L77*$M77*$N77,0) -> 0
G79: 0.25
D80: Acero Horizontal
G82: 1.26 | K82: 1/2" | L82: 0 | M82: 11 | N82: =+G82 -> 1.26 | O82: =IF(+$K82=O$12,+$L82*$M82*$N82,0) -> 0 | P82: =IF(+$K82=P$12,+$L82*$M82*$N82,0) -> 0 | Q82: =IF(+$K82=Q$12,+$L82*$M82*$N82,0) -> 0 | R82: =IF(+$K82=R$12,+$L82*$M82*$N82,0) -> 0 | S82: =IF(+$K82=S$12,+$L82*$M82*$N82,0) -> 0 | T82: =IF(+$K82=T$12,+$L82*$M82*$N82,0) -> 0
D85: Acero Vertical (Frontal) | H85: 0.2
G87: =+G82 -> 1.26 | K87: 1/2" | L87: 0 | M87: 7 | N87: =+G87+H85+H89 -> 1.96 | O87: =IF(+$K87=O$12,+$L87*$M87*$N87,0) -> 0 | P87: =IF(+$K87=P$12,+$L87*$M87*$N87,0) -> 0 | Q87: =IF(+$K87=Q$12,+$L87*$M87*$N87,0) -> 0 | R87: =IF(+$K87=R$12,+$L87*$M87*$N87,0) -> 0 | S87: =IF(+$K87=S$12,+$L87*$M87*$N87,0) -> 0 | T87: =IF(+$K87=T$12,+$L87*$M87*$N87,0) -> 0
H89: 0.5
D90: Losa sobre compuerta de cierre - Acero Longitudinal
G92: 0.695 | K92: 1/2" | L92: 0 | M92: 4 | N92: =+G92 -> 0.695 | O92: =IF(+$K92=O$12,+$L92*$M92*$N92,0) -> 0 | P92: =IF(+$K92=P$12,+$L92*$M92*$N92,0) -> 0 | Q92: =IF(+$K92=Q$12,+$L92*$M92*$N92,0) -> 0 | R92: =IF(+$K92=R$12,+$L92*$M92*$N92,0) -> 0 | S92: =IF(+$K92=S$12,+$L92*$M92*$N92,0) -> 0 | T92: =IF(+$K92=T$12,+$L92*$M92*$N92,0) -> 0
D95: Losa sobre compuerta de cierre - Acero Transversal
G97: 0.76 | K97: 1/2" | L97: 0 | M97: 5 | N97: =+G97 -> 0.76 | O97: =IF(+$K97=O$12,+$L97*$M97*$N97,0) -> 0 | P97: =IF(+$K97=P$12,+$L97*$M97*$N97,0) -> 0 | Q97: =IF(+$K97=Q$12,+$L97*$M97*$N97,0) -> 0 | R97: =IF(+$K97=R$12,+$L97*$M97*$N97,0) -> 0 | S97: =IF(+$K97=S$12,+$L97*$M97*$N97,0) -> 0 | T97: =IF(+$K97=T$12,+$L97*$M97*$N97,0) -> 0
H100: 0.2
G102: 0.2 | K102: 3/8" | L102: 0 | M102: 4 | N102: =+G102+H104+H100 -> 0.4 | O102: =IF(+$K102=O$12,+$L102*$M102*$N102,0) -> 0 | P102: =IF(+$K102=P$12,+$L102*$M102*$N102,0) -> 0 | Q102: =IF(+$K102=Q$12,+$L102*$M102*$N102,0) -> 0 | R102: =IF(+$K102=R$12,+$L102*$M102*$N102,0) -> 0 | S102: =IF(+$K102=S$12,+$L102*$M102*$N102,0) -> 0 | T102: =IF(+$K102=T$12,+$L102*$M102*$N102,0) -> 0
D105: Bloque de canal de descarga Acero Horizontal
G107: 0.1 | K107: 3/8" | L107: 0 | M107: 2 | N107: =+G107 -> 0.1 | O107: =IF(+$K107=O$12,+$L107*$M107*$N107,0) -> 0 | P107: =IF(+$K107=P$12,+$L107*$M107*$N107,0) -> 0 | Q107: =IF(+$K107=Q$12,+$L107*$M107*$N107,0) -> 0 | R107: =IF(+$K107=R$12,+$L107*$M107*$N107,0) -> 0 | S107: =IF(+$K107=S$12,+$L107*$M107*$N107,0) -> 0 | T107: =IF(+$K107=T$12,+$L107*$M107*$N107,0) -> 0
D110: Dientes - Acero Longitudinal
H112: 0.43 | K112: 3/8" | L112: 0 | M112: 2 | N112: =+H112+G114 -> 0.53 | O112: =IF(+$K112=O$12,+$L112*$M112*$N112,0) -> 0 | P112: =IF(+$K112=P$12,+$L112*$M112*$N112,0) -> 0 | Q112: =IF(+$K112=Q$12,+$L112*$M112*$N112,0) -> 0 | R112: =IF(+$K112=R$12,+$L112*$M112*$N112,0) -> 0 | S112: =IF(+$K112=S$12,+$L112*$M112*$N112,0) -> 0 | T112: =IF(+$K112=T$12,+$L112*$M112*$N112,0) -> 0
G114: 0.1
D115: Dientes - Acero Vertical
H117: 0.29 | K117: 3/8" | L117: 0 | M117: 2 | N117: =+H117+H119 -> 0.39 | O117: =IF(+$K117=O$12,+$L117*$M117*$N117,0) -> 0 | P117: =IF(+$K117=P$12,+$L117*$M117*$N117,0) -> 0 | Q117: =IF(+$K117=Q$12,+$L117*$M117*$N117,0) -> 0 | R117: =IF(+$K117=R$12,+$L117*$M117*$N117,0) -> 0 | S117: =IF(+$K117=S$12,+$L117*$M117*$N117,0) -> 0 | T117: =IF(+$K117=T$12,+$L117*$M117*$N117,0) -> 0
H119: 0.1
D120: Dientes - Acero Longitudinal
H122: 0.8 | K122: 3/8" | L122: 0 | M122: 2 | N122: =+H122+G124 -> 0.8 | O122: =IF(+$K122=O$12,+$L122*$M122*$N122,0) -> 0 | P122: =IF(+$K122=P$12,+$L122*$M122*$N122,0) -> 0 | Q122: =IF(+$K122=Q$12,+$L122*$M122*$N122,0) -> 0 | R122: =IF(+$K122=R$12,+$L122*$M122*$N122,0) -> 0 | S122: =IF(+$K122=S$12,+$L122*$M122*$N122,0) -> 0 | T122: =IF(+$K122=T$12,+$L122*$M122*$N122,0) -> 0
D125: Umbral terminal - Acero Transversal | G125: 0.223
H127: 0.155 | K127: 3/8" | L127: 0 | M127: 11 | N127: =+H127+H129+G125 -> 0.732 | O127: =IF(+$K127=O$12,+$L127*$M127*$N127,0) -> 0 | P127: =IF(+$K127=P$12,+$L127*$M127*$N127,0) -> 0 | Q127: =IF(+$K127=Q$12,+$L127*$M127*$N127,0) -> 0 | R127: =IF(+$K127=R$12,+$L127*$M127*$N127,0) -> 0 | S127: =IF(+$K127=S$12,+$L127*$M127*$N127,0) -> 0 | T127: =IF(+$K127=T$12,+$L127*$M127*$N127,0) -> 0
H129: 0.354
D130: Umbral terminal - Acero Longitudinal
H132: 2.3 | K132: 3/8" | L132: 0 | M132: 2 | N132: =+H132+G134+G130 -> 2.3 | O132: =IF(+$K132=O$12,+$L132*$M132*$N132,0) -> 0 | P132: =IF(+$K132=P$12,+$L132*$M132*$N132,0) -> 0 | Q132: =IF(+$K132=Q$12,+$L132*$M132*$N132,0) -> 0 | R132: =IF(+$K132=R$12,+$L132*$M132*$N132,0) -> 0 | S132: =IF(+$K132=S$12,+$L132*$M132*$N132,0) -> 0 | T132: =IF(+$K132=T$12,+$L132*$M132*$N132,0) -> 0
D135: Umbral terminal - Acero Vertical
H137: 0.285 | K137: 1/2" | L137: 0 | M137: 2 | N137: =+H137 -> 0.285 | O137: =IF(+$K137=O$12,+$L137*$M137*$N137,0) -> 0 | P137: =IF(+$K137=P$12,+$L137*$M137*$N137,0) -> 0 | Q137: =IF(+$K137=Q$12,+$L137*$M137*$N137,0) -> 0 | R137: =IF(+$K137=R$12,+$L137*$M137*$N137,0) -> 0 | S137: =IF(+$K137=S$12,+$L137*$M137*$N137,0) -> 0 | T137: =IF(+$K137=T$12,+$L137*$M137*$N137,0) -> 0
H139: 0.1
B140: Losa | C140: Losa de Fondo | D140: Acero Longitudinal
G141: 4.266
F142: 0.5 | I142: 0.5 | K142: 3/8" | L142: 0 | M142: 10 | N142: =G141+I142+F142 -> 5.266 | O142: =IF(+$K142=O$12,+$L142*$M142*$N142,0) -> 0 | P142: =IF(+$K142=P$12,+$L142*$M142*$N142,0) -> 0 | Q142: =IF(+$K142=Q$12,+$L142*$M142*$N142,0) -> 0 | R142: =IF(+$K142=R$12,+$L142*$M142*$N142,0) -> 0 | S142: =IF(+$K142=S$12,+$L142*$M142*$N142,0) -> 0 | T142: =IF(+$K142=T$12,+$L142*$M142*$N142,0) -> 0
D146: Acero Vertical | H146: 0.25
K147: 3/8" | L147: 0 | M147: 22 | N147: =G148+H146+H149 -> 2.909 | O147: =IF(+$K147=O$12,+$L147*$M147*$N147,0) -> 0 | P147: =IF(+$K147=P$12,+$L147*$M147*$N147,0) -> 0 | Q147: =IF(+$K147=Q$12,+$L147*$M147*$N147,0) -> 0 | R147: =IF(+$K147=R$12,+$L147*$M147*$N147,0) -> 0 | S147: =IF(+$K147=S$12,+$L147*$M147*$N147,0) -> 0 | T147: =IF(+$K147=T$12,+$L147*$M147*$N147,0) -> 0
G148: 2.409
H149: 0.25
C150: Uña de losa | D150: Acero Vertical
H152: 0.475 | K152: 1/2" | L152: 0 | M152: 10 | N152: =H152 -> 0.475 | O152: =IF(+$K152=O$12,+$L152*$M152*$N152,0) -> 0 | P152: =IF(+$K152=P$12,+$L152*$M152*$N152,0) -> 0 | Q152: =IF(+$K152=Q$12,+$L152*$M152*$N152,0) -> 0 | R152: =IF(+$K152=R$12,+$L152*$M152*$N152,0) -> 0 | S152: =IF(+$K152=S$12,+$L152*$M152*$N152,0) -> 0 | T152: =IF(+$K152=T$12,+$L152*$M152*$N152,0) -> 0
D155: Acero Transversal
G157: 2.34 | K157: 1/2" | L157: 0 | M157: 3 | N157: =G157 -> 2.34 | O157: =IF(+$K157=O$12,+$L157*$M157*$N157,0) -> 0 | P157: =IF(+$K157=P$12,+$L157*$M157*$N157,0) -> 0 | Q157: =IF(+$K157=Q$12,+$L157*$M157*$N157,0) -> 0 | R157: =IF(+$K157=R$12,+$L157*$M157*$N157,0) -> 0 | S157: =IF(+$K157=S$12,+$L157*$M157*$N157,0) -> 0 | T157: =IF(+$K157=T$12,+$L157*$M157*$N157,0) -> 0
I161: =+F163 -> 0.085
K162: 3/8" | L162: 0 | M162: 9 | N162: =+F163+G163+I161 -> 1.32 | O162: =IF(+$K162=O$12,+$L162*$M162*$N162,0) -> 0 | P162: =IF(+$K162=P$12,+$L162*$M162*$N162,0) -> 0 | Q162: =IF(+$K162=Q$12,+$L162*$M162*$N162,0) -> 0 | R162: =IF(+$K162=R$12,+$L162*$M162*$N162,0) -> 0 | S162: =IF(+$K162=S$12,+$L162*$M162*$N162,0) -> 0 | T162: =IF(+$K162=T$12,+$L162*$M162*$N162,0) -> 0
F163: 0.085 | G163: 1.15
H165: 0.1
H167: 1.64 | K167: 3/8" | L167: 0 | M167: 6 | N167: =+H165+G169+H167 -> 1.84 | O167: =IF(+$K167=O$12,+$L167*$M167*$N167,0) -> 0 | P167: =IF(+$K167=P$12,+$L167*$M167*$N167,0) -> 0 | Q167: =IF(+$K167=Q$12,+$L167*$M167*$N167,0) -> 0 | R167: =IF(+$K167=R$12,+$L167*$M167*$N167,0) -> 0 | S167: =IF(+$K167=S$12,+$L167*$M167*$N167,0) -> 0 | T167: =IF(+$K167=T$12,+$L167*$M167*$N167,0) -> 0
G169: 0.1
D170: Acero Longitudinal - Camara seca
F171: 0.1 | I171: =+F171 -> 0.1
K172: 3/8" | L172: 0 | M172: 9 | N172: =+F171+G173+I171 -> 1.72 | O172: =IF(+$K172=O$12,+$L172*$M172*$N172,0) -> 0 | P172: =IF(+$K172=P$12,+$L172*$M172*$N172,0) -> 0 | Q172: =IF(+$K172=Q$12,+$L172*$M172*$N172,0) -> 0 | R172: =IF(+$K172=R$12,+$L172*$M172*$N172,0) -> 0 | S172: =IF(+$K172=S$12,+$L172*$M172*$N172,0) -> 0 | T172: =IF(+$K172=T$12,+$L172*$M172*$N172,0) -> 0
G173: 1.52
D175: Acero Transversal - Camara seca | H175: =G179 -> 0.1
H177: 1.64 | K177: 3/8" | L177: 0 | M177: 6 | N177: =+H177+G179+H175 -> 1.84 | O177: =IF(+$K177=O$12,+$L177*$M177*$N177,0) -> 0 | P177: =IF(+$K177=P$12,+$L177*$M177*$N177,0) -> 0 | Q177: =IF(+$K177=Q$12,+$L177*$M177*$N177,0) -> 0 | R177: =IF(+$K177=R$12,+$L177*$M177*$N177,0) -> 0 | S177: =IF(+$K177=S$12,+$L177*$M177*$N177,0) -> 0 | T177: =IF(+$K177=T$12,+$L177*$M177*$N177,0) -> 0
G179: 0.1
C180: LOSA LAVADERO | D180: Vertedero - Horizontal
F182: 0.1 | I182: 0.1 | K182: 3/8" | L182: 0 | M182: 2 | N182: =+F182+G183 -> 1.2 | O182: =IF(+$K182=O$12,+$L182*$M182*$N182,0) -> 0 | P182: =IF(+$K182=P$12,+$L182*$M182*$N182,0) -> 0 | Q182: =IF(+$K182=Q$12,+$L182*$M182*$N182,0) -> 0 | R182: =IF(+$K182=R$12,+$L182*$M182*$N182,0) -> 0 | S182: =IF(+$K182=S$12,+$L182*$M182*$N182,0) -> 0 | T182: =IF(+$K182=T$12,+$L182*$M182*$N182,0) -> 0
G183: 1.1
D185: Vertedero - Vertical
H187: 0.66 | K187: 3/8" | L187: 0 | M187: 6 | N187: =+G189+H187 -> 0.91 | O187: =IF(+$K187=O$12,+$L187*$M187*$N187,0) -> 0 | P187: =IF(+$K187=P$12,+$L187*$M187*$N187,0) -> 0 | Q187: =IF(+$K187=Q$12,+$L187*$M187*$N187,0) -> 0 | R187: =IF(+$K187=R$12,+$L187*$M187*$N187,0) -> 0 | S187: =IF(+$K187=S$12,+$L187*$M187*$N187,0) -> 0 | T187: =IF(+$K187=T$12,+$L187*$M187*$N187,0) -> 0
...

Sheet 1.15 LAV. INICIAL.
A2: PLANILLA DE METRADOS DE AGUA POTABLE
A3: "CREACION DEL SERVICIO DE AGUA POTABLE RURAL Y CREACION DEL SERVICIO DE ALCANTARILLADO U OTRAS FORMAS DE DISPOSICION SANITARIA DE EXCRETAS EN EL SECTOR NUEVA ESPERANZA DE LA CC.NN. BAJO PITOCUNA DISTRITO DE RIO NEGRO, PROVINCIA DE SATIPO, DEPARTAMENTO DE JUNIN"
A4: LAVADERO MULTIUSO PARA I.E. INICIAL
A19: PARTIDA | B19: DESCRIPCION | C19: UNIDAD | D19: VECES | E19: LONGITUD | F19: ANCHO | G19: ALTURA | H19: SUB-TOTAL | I19: TOTAL
A20: =+"01.15" -> 01.15 | B20: =+"LAVADERO MULTIUSO PARA I.E.INICIAL ("&+D20&" Und.)" -> LAVADERO MULTIUSO PARA I.E.INICIAL (1 Und.) | D20: 1
B21: TRABAJOS PRELIMINARES
A22: =A$20 & ".01" -> 01.15.01 | B22: TRABAJOS PRELIMINARES | D22: =+$D$20 -> 1
A23: =$A$22 & ".01" -> 01.15.01.01 | B23: LIMPIEZA Y DESBROCE DE TERRENO MANUAL | C23: m2 | I23: =SUM(H24:H28) -> 6.25
B24: Tuberia de agua potable 1/2" | D24: 1 | E24: 3 | F24: 0.5 | H24: =+ROUND(PRODUCT(D24:G24),2) -> 1.5
B25: Tubería de desagüe 2" | D25: 1 | E25: =E24 -> 3 | F25: =F24 -> 0.5 | H25: =+ROUND(PRODUCT(D25:G25),2) -> 1.5
B26: Lavadero | D26: 1 | E26: 2 | F26: 0.65 | H26: =+ROUND(PRODUCT(D26:G26),2) -> 1.3
B27: Vereda Frontal | D27: 1 | E27: 2.6 | F27: 0.6 | H27: =+ROUND(PRODUCT(D27:G27),2) -> 1.56
B28: Vereda lateral | D28: 2 | E28: 0.3 | F28: 0.65 | H28: =+ROUND(PRODUCT(D28:G28),2) -> 0.39
A31: =$A$22 & ".02" -> 01.15.01.02 | B31: TRAZO Y REPLANTEO PRELIMINAR PARA ESTRUCTURAS | C31: m2 | I31: =SUM(H32:H37) -> 6.25
B32: Tuberia de agua potable 1/2" | D32: 1 | E32: =E24 -> 3 | F32: =F24 -> 0.5 | H32: =+ROUND(PRODUCT(D32:G32),2) -> 1.5
B33: Tubería de desagüe 2" | D33: 1 | E33: =E25 -> 3 | F33: =F25 -> 0.5 | H33: =+ROUND(PRODUCT(D33:G33),2) -> 1.5
B34: Lavadero | D34: 1 | E34: =E26 -> 2 | F34: =F26 -> 0.65 | H34: =+ROUND(PRODUCT(D34:G34),2) -> 1.3
B35: Vereda Frontal | D35: 1 | E35: =E27 -> 2.6 | F35: =F27 -> 0.6 | H35: =+ROUND(PRODUCT(D35:G35),2) -> 1.56
B36: Vereda Lateral | D36: 2 | E36: =E28 -> 0.3 | F36: =F28 -> 0.65 | H36: =+ROUND(PRODUCT(D36:G36),2) -> 0.39
A38: =$A$22 & ".03" -> 01.15.01.03 | B38: TRAZO Y REPLANTEO DURANTE EL PROCESO PARA ESTRUCTURAS | C38: m2 | I38: =SUM(H39:H44) -> 6.25
B39: Tuberia de agua potable 1/2" | D39: 1 | E39: =E24 -> 3 | F39: =F24 -> 0.5 | H39: =+ROUND(PRODUCT(D39:G39),2) -> 1.5
B40: Tubería de desagüe 2" | D40: 1 | E40: =E25 -> 3 | F40: =F25 -> 0.5 | H40: =+ROUND(PRODUCT(D40:G40),2) -> 1.5
B41: Lavadero | D41: 1 | E41: =E26 -> 2 | F41: =F26 -> 0.65 | H41: =+ROUND(PRODUCT(D41:G41),2) -> 1.3
B42: Vereda Frontal | D42: 1 | E42: =E27 -> 2.6 | F42: =F27 -> 0.6 | H42: =+ROUND(PRODUCT(D42:G42),2) -> 1.56
B43: Vereda Lateral | D43: 2 | E43: =E28 -> 0.3 | F43: =F28 -> 0.65 | H43: =+ROUND(PRODUCT(D43:G43),2) -> 0.39
A45: =A$20 & ".02" -> 01.15.02 | B45: MOVIMIENTO DE TIERRAS
A46: =$A$45 & ".01" -> 01.15.02.01 | B46: EXCAVACIÓN MANUAL EN TERRENO NORMAL | C46: m3 | I46: =SUM(H47:H49) -> 0.33
B47: Lavadero - cimiento | D47: 1 | E47: 2 | F47: 0.65 | G47: 0.1 | H47: =+ROUND(PRODUCT(D47:G47),2) -> 0.13
B48: Vereda frontal | D48: 1 | E48: =E35 -> 2.6 | F48: =F35 -> 0.6 | G48: 0.1 | H48: =+ROUND(PRODUCT(D48:G48),2) -> 0.16
B49: Vereda lateral | D49: =D36 -> 2 | E49: 0.3 | F49: =F28 -> 0.65 | G49: 0.1 | H49: =+ROUND(PRODUCT(D49:G49),2) -> 0.04
A51: =$A$45 & ".02" -> 01.15.02.02 | B51: RELLENO CON MATERIAL PROPIO SELECCIONADO | C51: m3 | I51: =SUM(H52:H53) -> 0.14
B52: Lavadero - cimiento | D52: 1 | E52: 1.5 | F52: =F47 -> 0.65 | G52: 0.1 | H52: =+ROUND(PRODUCT(D52:G52),2) -> 0.1
B53: Vereda frontal | D53: 1 | E53: Area= | F53: 0.015 | G53: 2.6 | H53: =+ROUND(PRODUCT(D53:G53),2) -> 0.04
A55: =$A$45 & ".03" -> 01.15.02.03 | B55: ELIMINACION DE DESMONTE DE TERRENO NORMAL D= 500m | C55: m3 | I55: =SUM(H56:H56) -> 0.228
B56: Excavacion - Esponjamiento 20% | D56: 1 | E56: 1.2 | F56: Volumen | G56: =I46-I51 -> 0.19 | H56: =E56*G56 -> 0.228
A58: =A$20 & ".03" -> 01.15.03 | B58: OBRAS DE CONCRETO SIMPLE
A59: =$A$58 & ".01" -> 01.15.03.01 | B59: CONCRETO CICLOPEO 1:10 + 30% PM | C59: m3 | I59: =SUM(H60) -> 0.0735
B60: Cimentacion lavadero | D60: 2 | E60: 0.25 | F60: =+F47 -> 0.65 | G60: 0.2 | H60: =+ROUND(PRODUCT(D60:G60),2)*1.05 -> 0.0735
A62: =A$20 & ".04" -> 01.15.04 | B62: OBRAS DE CONCRETO ARMADO
A63: =$A$62 & ".01" -> 01.15.04.01 | B63: CONCRETO f'c=210 kg/cm2 EN MUROS | C63: m3 | I63: =SUM(H64:H66) -> 0.231
B64: Muro Posterior Lavadero | D64: 1 | E64: 0.15 | F64: Area = | G64: 0.99 | H64: =+ROUND(PRODUCT(D64:G64),2)*1.05 -> 0.1575
B65: Lavadero Muro lateral | D65: 2 | E65: 0.1 | F65: 0.4 | G65: 0.25 | H65: =+ROUND(PRODUCT(D65:G65),2)*1.05 -> 0.021
B66: Lavadero Muro frontal | D66: 1 | E66: 2 | F66: 0.1 | G66: 0.25 | H66: =+ROUND(PRODUCT(D66:G66),2)*1.05 -> 0.0525
A68: =$A$62 & ".02" -> 01.15.04.02 | B68: CONCRETO f'c=210 kg/cm2 EN LOSA | C68: m3 | I68: =SUM(H69:H69) -> 0.1365
B69: Lavadero Losa | D69: 1 | E69: 2 | F69: 0.65 | G69: 0.1 | H69: =+ROUND(PRODUCT(D69:G69),2)*1.05 -> 0.1365
A71: =$A$62 & ".03" -> 01.15.04.03 | B71: ENCOFRADO Y DESENCOFRADO / PARA LAVADEROS - MURO | C71: m2 | I71: =SUM(H72:H78) -> 4.4935
B72: Muro posterior - cara interior | D72: 1 | E72: Area = | F72: 0.94 | H72: =+ROUND(PRODUCT(D72:G72),3)*1.1 -> 1.034
B73: Muro posterior - cara exterior | D73: 1 | E73: Area = | F73: 1.19 | H73: =+ROUND(PRODUCT(D73:G73),3)*1.1 -> 1.309
B74: Muro posterior - cara lateral | D74: 2 | F74: 0.15 | G74: 0.5 | H74: =+ROUND(PRODUCT(D74:G74),3)*1.1 -> 0.165
B75: Muro - cara lateral exterior | D75: 2 | F75: 0.65 | G75: 0.35 | H75: =+ROUND(PRODUCT(D75:G75),3)*1.1 -> 0.5005
B76: Muro - cara Lateral Interior | D76: 2 | F76: 0.4 | G76: 0.25 | H76: =+ROUND(PRODUCT(D76:G76),3)*1.1 -> 0.22
B77: Muro Frontal - interior | D77: 1 | E77: 1.8 | G77: 0.25 | H77: =+ROUND(PRODUCT(D77:G77),3)*1.1 -> 0.495
B78: Muro Frontal - exterior | D78: 1 | E78: 2 | G78: 0.35 | H78: =+ROUND(PRODUCT(D78:G78),3)*1.1 -> 0.77
A80: =$A$62 & ".04" -> 01.15.04.04 | B80: ACERO CORRUGADO f'y=4200 kg/cm2 G-60 | C80: kg | I80: =H81 -> 8.9265645
B81: Ver planilla de metrado de acero | H81: ='1.15 METR- ACERO'!O41*1.05 -> 8.9265645
A83: =A$20 & ".05" -> 01.15.05 | B83: REVOQUES Y ENLUCIDOS | D83: =+$D$20 -> 1
A84: =$A$83 & ".01" -> 01.15.05.01 | B84: TARRAJEO CON IMPERMEABILIZANTE PULIDO C:A 1:2 / PARA LAVADEROS INST. EDUCATIVO | C84: m2 | I84: =SUM(H85:H89) -> 3.03
B85: Muro posterior - cara interior | D85: 1 | E85: Area = | G85: 0.94 | H85: =+ROUND(PRODUCT(D85:G85),3) -> 0.94
B86: Losa inferior - cara superior | D86: 1 | E86: 1.8 | F86: 0.4 | H86: =+ROUND(PRODUCT(D86:G86),3) -> 0.72
B87: Muro - cara Lateral Interior | D87: 2 | F87: 0.4 | G87: 0.25 | H87: =+ROUND(PRODUCT(D87:G87),3) -> 0.2
B88: Muro Frontal - interior | D88: 1 | E88: 1.8 | G88: 0.25 | H88: =+ROUND(PRODUCT(D88:G88),3) -> 0.45
B89: Mortero para pendiente de fondo S=2% | D89: 1 | E89: 1.8 | F89: 0.4 | H89: =+ROUND(PRODUCT(D89:G89),3) -> 0.72
A91: =$A$83 & ".02" -> 01.15.05.02 | B91: TARRAJEO EXTERIOR MEZCLA C:A 1:4, e=1.5 cm / PARA LAVADEROS | C91: m2 | I91: =SUM(H92:H99) -> 3.14
B92: Muro posterior - cara exterior | D92: 1 | E92: Area = | G92: 1.19 | H92: =+ROUND(PRODUCT(D92:G92),3) -> 1.19
B93: Muro posterior - cara lateral | D93: 2 | F93: 0.15 | G93: 0.5 | H93: =+ROUND(PRODUCT(D93:G93),3) -> 0.15
B94: Muro posterior - cara superior | D94: 1 | E94: 2 | F94: 0.15 | H94: =+ROUND(PRODUCT(D94:G94),3) -> 0.3
B95: Muro lateral - cara exterior | D95: 2 | F95: 0.5 | G95: 0.35 | H95: =+ROUND(PRODUCT(D95:G95),3) -> 0.35
B96: Muro lateral - cara superior | D96: 2 | E96: 0.15 | F96: 0.5 | H96: =+ROUND(PRODUCT(D96:G96),3) -> 0.15
B97: Muro Frontal - cara exterior | D97: 1 | E97: 2 | G97: 0.35 | H97: =+ROUND(PRODUCT(D97:G97),3) -> 0.7
B98: Muro Frontal - cara superior | D98: 1 | E98: 2 | F98: 0.15 | H98: =+ROUND(PRODUCT(D98:G98),3) -> 0.3
A100: =A$20 & ".06" -> 01.15.06 | B100: INSTALACIONES SANITARIAS | D100: =+$D$20 -> 1
A101: =$A$100 & ".01" -> 01.15.06.01 | B101: SUMINISTRO Y COLOC. DE ACCESORIOS EN LAVADERO I.E. INICIAL | C101: und | D101: 1 | H101: =+D101 -> 1 | I101: =H101*$D$100 -> 1
B102: Instalaciones de agua
B103: Tee PVC SP Ø = 3/4" | C103: und | D103: 3
B104: CODO SP PVC Ø = 3/4" x 90° | C104: und | D104: 3
B105: REDUCCIÓN SP PVC 3/4" A 1/2" | C105: und | D105: 3
B106: ADAPTADOR UPR PVC 1/2" | C106: und | D106: 3 | L106: 89
B107: CODO PVC C/ROSCAx 90° Ø = 1/2" | C107: und | D107: 3 | L107: =L106/1.18 -> 75.423729
B108: NIPLE C/ROSCA PVC 1/2" x 2" | C108: und | D108: 3
B109: UNION DE ROSCA INTERNA DE BRONCE 1/2" | C109: und | D109: 3
B110: LLAVE DE ALTA RESISTENCIA BRONCE CROMADO 1/2", 250 lbs. | C110: und | D110: 3
B111: CODO SP PVC 1/2" X 90° | C111: und | D111: 1
B112: TUBERÍA PVC CLASE 10 DE 3/4" | C112: m | D112: 4
